Workbook

Sheet Начните здесь
D2: B2B SaaS
B3: Елизавета Трибунская | F3: tribunska.ru
B5: Три тарифа, три сценария и ваш способ продажи. Посчитайте, сколько компаний нужно привлечь и какие деньги потребуются на запуск.
B7: Изменить параметры | F7: Посмотреть результат
B9: На листе «Допущения» выберите сценарий и способ продажи, замените цены и расходы в жёлтых ячейках. Результат — на листе «Итог».
B11: Инструкция для ИИ-агента
B12: 1. Сначала расспроси владельца об идее, клиентах, географии, тарифах, способе продажи и расходах. Найди пробелы в данных. В книге три тарифа; сценарий экономики и способ продажи выбираются отдельно. 2. Проверь рекламу под эту аудиторию в Яндекс Директе, Google Ads, VK Рекламе и Facebook / Meta Ads там, где доступно размещение. Возьми из кабинетов прогноз цены клика, показов и кликов при выбранном бюджете. Поиск, рекламные сети, таргетинг и ретаргетинг оцени отдельно. Если доступа нет, попроси владельца прислать прогноз или выгрузку. 3. Приценивайся к тематическим блогерам и сообществам: запроси цену, средний охват рекламных публикаций, состав аудитории и доступные даты. Учитывай комиссии и налоги. Число подписчиков не подменяет охват рекламы. 4. Собери медиаплан по каналам, укажи источники, даты, географию и валюту. Отдели факты от прогнозов и гипотез. Используй прошлые кампании владельца, если они есть. Обнови бюджет и цену клика на основе медиаплана, сверяя клики с визитами. Конверсии без своих замеров оставь гипотезами для теста. Стартовые цифры книги не используй как рыночные. 5. Работай в копии. Меняй жёлтые ячейки, сохраняй формулы и авторство. Изменение логики или числа тарифов согласуй с владельцем. Разделяй выручку, вклад клиента и деньги на запуск; не считай часы менеджера и поддержки повторно в постоянном ФОТ. 6. Проверь формулы, нулевой бюджет, отток 0% и 100%, лаг демо и все способы продажи. Верни заполненный файл и объясни результат. Если Excel недоступен, посчитай в доступном инструменте и сделай сводку с картинкой. Запуск рекламы согласуй отдельно.
B14: Оплата помесячно за компанию. Стартовые цифры — модельные; годовой оплаты, налогов и переходов между тарифами здесь нет.
B16: Хороший расчёт начинается с разговора о вашем продукте, клиентах и способе продажи.
B17: Разобрать модель своего проекта → t.me/tribunska

Sheet Итог
A1: B2B SaaS • экономика запуска
A3: Сценарий: | B3: =IFERROR(CHOOSE(Допущения!$B$3,"Осторожный","Базовый","Сильный"),"Проверьте выбор") -> Базовый | D3: Продажи: | E3: =IFERROR(CHOOSE(Допущения!$B$4,"Самостоятельно","Через демо","Смешанные"),"Проверьте выбор") -> Смешанные
A5: За первые 12 месяцев | D5: Как читать цифры
A7: Новых платящих компаний | B7: =SUM(Деньги!B7:B18) -> 537.3 | D7: Стоимость привлечения включает рекламу и часы менеджера. В конце периода часть демо ещё ждёт оплаты — эти компании в продажи не попадают.
A8: Активных к концу периода | B8: =Деньги!C18 -> 416.47018
A9: Выручка за 12 месяцев, ₽ | B9: =SUM(Деньги!D7:D18) -> 22747109
A10: Выручка в 12-м месяце, ₽ | B10: =Деньги!D18 -> 3745696.9
A11: Средняя стоимость привлечения, ₽ | B11: =IF(B7=0,"Нет оплат",(SUM(Деньги!G7:H18))/B7) -> 4142.9369 | D11: Сравните стоимость привлечения с вкладом клиента ниже. Затем проверьте, сколько денег потребует запуск: прибыльный тариф и запуск без кассового разрыва — разные вопросы.
A12: Первый месяц с положительным потоком | B12: =IF(COUNTIF(Деньги!M7:M18,1)=0,"За 12 месяцев не достигнут","Месяц "&MATCH(1,Деньги!M7:M18,0)) -> Месяц 4
A13: Возврат вложенных денег | B13: =IF(COUNTIF(Деньги!N7:N18,1)=0,"За 12 месяцев не достигнут","Месяц "&MATCH(1,Деньги!N7:N18,0)) -> Месяц 7
A15: Максимальный дефицит, ₽ | B15: =MAX(Деньги!L6:L18) -> 2242686.7
A16: Запас на запуск, ₽ | B16: =B15*IF(AND(ISNUMBER(Допущения!$B$9),Допущения!$B$9>=0,Допущения!$B$9<=1),Допущения!$B$9,NA()) -> 448537.34 | D16: Ожидаемые компании могут быть дробными. Сценарий меняет цену клика, конверсию оплаты и отток, но не переписывает ваши тарифы.
A17: Денег на запуск с запасом, ₽ | B17: =B15+B16 -> 2691224
A18: Накопленный поток к концу, ₽ | B18: =Деньги!K18 -> 10532932
A21: Тариф | B21: Цена / месяц, ₽ | D21: Новых за год | E21: Активных в конце | F21: Привлечение, ₽ | G21: Вклад клиента, ₽ | H21: Вклад за вычетом привлечения, ₽
A22: =Допущения!$A$30 -> Старт | B22: =Допущения!$B$30 -> 4900 | D22: =SUMIF(Подписка!$B$6:$B$41,A22,Подписка!$F$6:$F$41) -> 420 | E22: =Подписка!G39 -> 317.69526 | F22: =IF(D22=0,"Нет оплат",(SUMIF(Привлечение!$B$6:$B$41,A22,Привлечение!$D$6:$D$41)+SUMIF(Привлечение!$B$6:$B$41,A22,Привлечение!$N$6:$N$41))/D22) -> 2500 | G22: =Подписка!E46 -> 21317.661 | H22: =IF(ISNUMBER(F22),G22-F22,"Нет оплат") -> 18817.661
A23: =Допущения!$A$31 -> Команда | B23: =Допущения!$B$31 -> 14900 | D23: =SUMIF(Подписка!$B$6:$B$41,A23,Подписка!$F$6:$F$41) -> 94.5 | E23: =Подписка!G40 -> 78.282241 | F23: =IF(D23=0,"Нет оплат",(SUMIF(Привлечение!$B$6:$B$41,A23,Привлечение!$D$6:$D$41)+SUMIF(Привлечение!$B$6:$B$41,A23,Привлечение!$N$6:$N$41))/D23) -> 7777.7778 | G23: =Подписка!E47 -> 67251.386 | H23: =IF(ISNUMBER(F23),G23-F23,"Нет оплат") -> 59473.608
A24: =Допущения!$A$32 -> Бизнес | B24: =Допущения!$B$32 -> 49900 | D24: =SUMIF(Подписка!$B$6:$B$41,A24,Подписка!$F$6:$F$41) -> 22.8 | E24: =Подписка!G41 -> 20.49268 | F24: =IF(D24=0,"Нет оплат",(SUMIF(Привлечение!$B$6:$B$41,A24,Привлечение!$D$6:$D$41)+SUMIF(Привлечение!$B$6:$B$41,A24,Привлечение!$N$6:$N$41))/D24) -> 19342.105 | G24: =Подписка!E48 -> 235844.43 | H24: =IF(ISNUMBER(F24),G24-F24,"Нет оплат") -> 216502.33
A26: ="Вклад клиента за "&Допущения!B16&" месяцев: выручка минус переменные затраты, с учётом оттока. Постоянные расходы — в общем потоке." -> Вклад клиента за 6 месяцев: выручка минус переменные затраты, с учётом оттока. Постоянные расходы — в общем потоке.
A28: Месяц | B28: Новых компаний | D28: Выручка, ₽ | E28: Реклама + менеджер, ₽ | F28: Поток, ₽ | G28: Накопленно, ₽ | H28: Дефицит, ₽
A29: Месяц 1 | B29: =Деньги!B7 -> 12.25 | D29: =Деньги!D7 -> 82525 | E29: =SUM(Деньги!G7:H7) -> 53000 | F29: =Деньги!J7 -> -391600.25 | G29: =Деньги!K7 -> -1841600.2 | H29: =Деньги!L7 -> 1841600.2
A30: Месяц 2 | B30: =Деньги!B8 -> 25.1 | D30: =Деньги!D8 -> 273234 | E30: =SUM(Деньги!G8:H8) -> 106000 | F30: =Деньги!J8 -> -293840.34 | G30: =Деньги!K8 -> -2135440.6 | H30: =Деньги!L8 -> 2135440.6
A31: Месяц 3 | B31: =Деньги!B9 -> 37.95 | D31: =Деньги!D9 -> 567327.54 | E31: =SUM(Деньги!G9:H9) -> 159000 | F31: =Деньги!J9 -> -107246.12 | G31: =Деньги!K9 -> -2242686.7 | H31: =Деньги!L9 -> 2242686.7
A32: Месяц 4 | B32: =Деньги!B10 -> 50.8 | D32: =Деньги!D10 -> 960242.18 | E32: =SUM(Деньги!G10:H10) -> 212000 | F32: =Деньги!J10 -> 164259.57 | G32: =Деньги!K10 -> -2078427.1 | H32: =Деньги!L10 -> 2242686.7
A33: Месяц 5 | B33: =Деньги!B11 -> 51.4 | D33: =Деньги!D11 -> 1365113 | E33: =SUM(Деньги!G11:H11) -> 212000 | F33: =Деньги!J11 -> 508546.38 | G33: =Деньги!K11 -> -1569880.8 | H33: =Деньги!L11 -> 2242686.7
A34: Месяц 6 | B34: =Деньги!B12 -> 51.4 | D34: =Деньги!D12 -> 1752153 | E34: =SUM(Деньги!G12:H12) -> 212000 | F34: =Деньги!J12 -> 841105.43 | G34: =Деньги!K12 -> -728775.33 | H34: =Деньги!L12 -> 2242686.7
A35: Месяц 7 | B35: =Деньги!B13 -> 51.4 | D35: =Деньги!D13 -> 2122234 | E35: =SUM(Деньги!G13:H13) -> 212000 | F35: =Деньги!J13 -> 1159086.6 | G35: =Деньги!K13 -> 430311.29 | H35: =Деньги!L13 -> 2242686.7
A36: Месяц 8 | B36: =Деньги!B14 -> 51.4 | D36: =Деньги!D14 -> 2476182 | E36: =SUM(Деньги!G14:H14) -> 212000 | F36: =Деньги!J14 -> 1463200.4 | G36: =Деньги!K14 -> 1893511.6 | H36: =Деньги!L14 -> 2242686.7
A37: Месяц 9 | B37: =Деньги!B15 -> 51.4 | D37: =Деньги!D15 -> 2814779.8 | E37: =SUM(Деньги!G15:H15) -> 212000 | F37: =Деньги!J15 -> 1754119.7 | G37: =Деньги!K15 -> 3647631.4 | H37: =Деньги!L15 -> 2242686.7
A38: Месяц 10 | B38: =Деньги!B16 -> 51.4 | D38: =Деньги!D16 -> 3138769 | E38: =SUM(Деньги!G16:H16) -> 212000 | F38: =Деньги!J16 -> 2032482.5 | G38: =Деньги!K16 -> 5680113.9 | H38: =Деньги!L16 -> 2242686.7
A39: Месяц 11 | B39: =Деньги!B17 -> 51.4 | D39: =Деньги!D17 -> 3448852.6 | E39: =SUM(Деньги!G17:H17) -> 212000 | F39: =Деньги!J17 -> 2298893.3 | G39: =Деньги!K17 -> 7979007.2 | H39: =Деньги!L17 -> 2242686.7
A40: Месяц 12 | B40: =Деньги!B18 -> 51.4 | D40: =Деньги!D18 -> 3745696.9 | E40: =SUM(Деньги!G18:H18) -> 212000 | F40: =Деньги!J18 -> 2553925 | G40: =Деньги!K18 -> 10532932 | H40: =Деньги!L18 -> 2242686.7
A42: =Допущения!A54
A43: Елизавета Трибунская • tribunska.ru

Sheet Допущения
A1: Допущения • три тарифа
A3: Сценарий (1–3) | B3: 2 | D3: Продажи: | E3: =IFERROR(CHOOSE(Допущения!$B$4,"Самостоятельно","Через демо","Смешанные"),"Проверьте выбор") -> Смешанные
A4: Способ продажи (1–3) | B4: 3 | D4: 1 — самостоятельно; 2 — демо с менеджером; 3 — два младших тарифа самостоятельно, старший через демо.
D5: Сценарии: 1 — осторожный, 2 — базовый, 3 — сильный.
A7: Стоимость рабочего часа, ₽ | B7: 1000 | D7: Часы менеджера, поддержки и подключения считаем отдельно от постоянной команды.
A8: Комиссия с оплат | B8: 0.01
A9: Запас к деньгам на запуск | B9: 0.2
A10: Разработка до запуска, ₽ | B10: 1200000 | D10: Все стартовые числа — авторские модельные допущения. Замените своими данными.
A11: Упаковка и материалы, ₽ | B11: 150000
A12: Исследование и подготовка, ₽ | B12: 100000
A13: Постоянная команда в месяц, ₽ | B13: 300000 | D13: Постоянные расходы учитываются каждый месяц, стартовые — только до запуска.
A14: Постоянный маркетинг в месяц, ₽ | B14: 70000
A15: Прочие постоянные расходы, ₽/мес. | B15: 30000
A16: Срок для оценки вклада клиента, мес. | B16: 6
A17: От демо до оплаты, полных месяцев | B17: 1
A22: Параметр сценария | B22: В расчёте | C22: Осторожный | D22: Базовый | E22: Сильный
A23: Цена клика: множитель | B23: =IF(AND(ISNUMBER($B$3),$B$3=INT($B$3),$B$3>=1,$B$3<=3,COUNT(INDEX(C23:E23,1,$B$3))=1,INDEX(C23:E23,1,$B$3)>0),INDEX(C23:E23,1,$B$3),NA()) -> 1 | C23: 1.25 | D23: 1 | E23: 0.85
A24: Конверсия в оплату: множитель | B24: =IF(AND(ISNUMBER($B$3),$B$3=INT($B$3),$B$3>=1,$B$3<=3,COUNT(INDEX(C24:E24,1,$B$3))=1,INDEX(C24:E24,1,$B$3)>=0),INDEX(C24:E24,1,$B$3),NA()) -> 1 | C24: 0.65 | D24: 1 | E24: 1.25
A25: Отток: множитель | B25: =IF(AND(ISNUMBER($B$3),$B$3=INT($B$3),$B$3>=1,$B$3<=3,COUNT(INDEX(C25:E25,1,$B$3))=1,INDEX(C25:E25,1,$B$3)>=0),INDEX(C25:E25,1,$B$3),NA()) -> 1 | C25: 1.3 | D25: 1 | E25: 0.8
A29: Тариф | B29: Цена за месяц, ₽ | C29: Доля бюджета | D29: Отток / мес. | E29: Хостинг / компания, ₽ | F29: Поддержка, ч/мес. | G29: Подключение, ч | H29: Цена клика, ₽ | I29: Визит → оплата | J29: Визит → заявка на демо | K29: Заявка → проведённое демо | L29: Демо → оплата | M29: Часов на демо | N29: Демо в расчёте
A30: Старт | B30: 4900 | C30: 0.5 | D30: 0.06 | E30: 300 | F30: 0.33 | G30: 0.5 | H30: 45 | I30: 0.018 | J30: 0.06 | K30: 0.7 | L30: 0.2 | M30: 0.75 | N30: =IF(AND(ISNUMBER($B$4),$B$4=INT($B$4),$B$4>=1,$B$4<=3),IF($B$4=1,0,IF($B$4=2,1,0)),NA()) -> 0
A31: Команда | B31: 14900 | C31: 0.35 | D31: 0.04 | E31: 1000 | F31: 1 | G31: 2 | H31: 70 | I31: 0.009 | J31: 0.05 | K31: 0.75 | L31: 0.25 | M31: 1 | N31: =IF(AND(ISNUMBER($B$4),$B$4=INT($B$4),$B$4>=1,$B$4<=3),IF($B$4=1,0,IF($B$4=2,1,0)),NA()) -> 0
A32: Бизнес | B32: 49900 | C32: 0.15 | D32: 0.025 | E32: 3500 | F32: 3 | G32: 6 | H32: 120 | I32: 0.004 | J32: 0.04 | K32: 0.8 | L32: 0.3 | M32: 1.5 | N32: =IF(AND(ISNUMBER($B$4),$B$4=INT($B$4),$B$4>=1,$B$4<=3),IF($B$4=1,0,IF($B$4=2,1,1)),NA()) -> 1
A34: Доля бюджета — распределение расходов на трафик между тарифами; сумма — 100%.
A35: Множитель конверсии влияет на самостоятельную покупку и оплату после демо; верх воронки демо задаётся отдельно.
A39: Месяц | B39: Рекламный бюджет, ₽
A40: Месяц 1 | B40: 50000
A41: Месяц 2 | B41: 100000
A42: Месяц 3 | B42: 150000
A43: Месяц 4 | B43: 200000
A44: Месяц 5 | B44: 200000
A45: Месяц 6 | B45: 200000
A46: Месяц 7 | B46: 200000
A47: Месяц 8 | B47: 200000
A48: Месяц 9 | B48: 200000
A49: Месяц 10 | B49: 200000
A50: Месяц 11 | B50: 200000
A51: Месяц 12 | B51: 200000
A54: =IF(IFERROR(AND(AND(ISNUMBER(B3),B3>0,B3=INT(B3),B3<=3),AND(ISNUMBER(B4),B4>0,B4=INT(B4),B4<=3),AND(ISNUMBER(B7),B7>=0),AND(ISNUMBER(B8),B8>=0,B8<=1),AND(ISNUMBER(B9),B9>=0,B9<=1),AND(ISNUMBER(B10),B10>=0),AND(ISNUMBER(B11),B11>=0),AND(ISNUMBER(B12),B12>=0),AND(ISNUMBER(B13),B13>=0),AND(ISNUMBER(B14),B14>=0),AND(ISNUMBER(B15),B15>=0),AND(ISNUMBER(B16),B16>0,B16=INT(B16),B16<=120),AND(ISNUMBER(B17),B17>=0,B17=INT(B17),B17<=12),AND(ISNUMBER(C23),C23>0),AND(ISNUMBER(D23),D23>0),AND(ISNUMBER(E23),E23>0),AND(ISNUMBER(C24),C24>=0),AND(ISNUMBER(D24),D24>=0),AND(ISNUMBER(E24),E24>=0),AND(ISNUMBER(C25),C25>=0),AND(ISNUMBER(D25),D25>=0),AND(ISNUMBER(E25),E25>=0),AND(ISNUMBER(B30),B30>0),AND(ISNUMBER(C30),C30>=0,C30<=1),AND(ISNUMBER(D30),D30>=0,D30<=1),AND(ISNUMBER(E30),E30>=0),AND(ISNUMBER(F30),F30>=0),AND(ISNUMBER(G30),G30>=0),AND(ISNUMBER(H30),H30>0),AND(ISNUMBER(I30),I30>=0,I30<=1),AND(ISNUMBER(J30),J30>=0,J30<=1),AND(ISNUMBER(K30),K30>=0,K30<=1),AND(ISNUMBER(L30),L30>=0,L30<=1),AND(ISNUMBER(M30),M30>=0),AND(ISNUMBER(B31),B31>0),AND(ISNUMBER(C31),C31>=0,C31<=1),AND(ISNUMBER(D31),D31>=0,D31<=1),AND(ISNUMBER(E31),E31>=0),AND(ISNUMBER(F31),F31>=0),AND(ISNUMBER(G31),G31>=0),AND(ISNUMBER(H31),H31>0),AND(ISNUMBER(I31),I31>=0,I31<=1),AND(ISNUMBER(J31),J31>=0,J31<=1),AND(ISNUMBER(K31),K31>=0,K31<=1),AND(ISNUMBER(L31),L31>=0,L31<=1),AND(ISNUMBER(M31),M31>=0),AND(ISNUMBER(B32),B32>0),AND(ISNUMBER(C32),C32>=0,C32<=1),AND(ISNUMBER(D32),D32>=0,D32<=1),AND(ISNUMBER(E32),E32>=0),AND(ISNUMBER(F32),F32>=0),AND(ISNUMBER(G32),G32>=0),AND(ISNUMBER(H32),H32>0),AND(ISNUMBER(I32),I32>=0,I32<=1),AND(ISNUMBER(J32),J32>=0,J32<=1),AND(ISNUMBER(K32),K32>=0,K32<=1),AND(ISNUMBER(L32),L32>=0,L32<=1),AND(ISNUMBER(M32),M32>=0),AND(ISNUMBER(B40),B40>=0),AND(ISNUMBER(B41),B41>=0),AND(ISNUMBER(B42),B42>=0),AND(ISNUMBER(B43),B43>=0),AND(ISNUMBER(B44),B44>=0),AND(ISNUMBER(B45),B45>=0),AND(ISNUMBER(B46),B46>=0),AND(ISNUMBER(B47),B47>=0),AND(ISNUMBER(B48),B48>=0),AND(ISNUMBER(B49),B49>=0),AND(ISNUMBER(B50),B50>=0),AND(ISNUMBER(B51),B51>=0),ABS(SUM(C30:C32)-1)<0.00000001,MAX(D30:D32)*B25<=1,MAX(I30:I32)*B24<=1,MAX(L30:L32)*B24<=1),FALSE),"","Проверьте вводные: красные ячейки, доли бюджета и конверсии с множителями.")

Sheet Привлечение
A1: Привлечение • самостоятельно или через демо
A3: Сценарий: | B3: =IFERROR(CHOOSE(Допущения!$B$3,"Осторожный","Базовый","Сильный"),"Проверьте выбор") -> Базовый | D3: Продажи: | E3: =IFERROR(CHOOSE(Допущения!$B$4,"Самостоятельно","Через демо","Смешанные"),"Проверьте выбор") -> Смешанные
A5: Месяц | B5: Тариф | C5: Через демо | D5: Трафик, ₽ | E5: Цена клика, ₽ | F5: Визиты | G5: Покупки сами | H5: Заявки на демо | I5: Демо проведены | J5: Будущие оплаты с этих демо | K5: Оплаты прошлых демо | L5: Новые компании | M5: Часы менеджера | N5: Менеджер, ₽
A6: Месяц 1 | B6: =Допущения!$A$30 -> Старт | C6: =Допущения!$N$30 -> 0 | D6: =IF(AND(COUNT(Допущения!$C$30:$C$32)=3,MIN(Допущения!$C$30:$C$32)>=0,MAX(Допущения!$C$30:$C$32)<=1,ABS(SUM(Допущения!$C$30:$C$32)-1)<0.00000001),IF(AND(ISNUMBER(Допущения!$B$40),Допущения!$B$40>=0),Допущения!$B$40,NA())*Допущения!$C$30,NA()) -> 25000 | E6: =IF(AND(ISNUMBER(Допущения!$H$30),Допущения!$H$30>0),Допущения!$H$30,NA())*Допущения!$B$23 -> 45 | F6: =D6/E6 -> 555.55556 | G6: =IF(C6=1,0,IF(IF(AND(ISNUMBER(Допущения!$I$30),Допущения!$I$30>=0,Допущения!$I$30<=1),Допущения!$I$30,NA())*Допущения!$B$24<=1,F6*IF(AND(ISNUMBER(Допущения!$I$30),Допущения!$I$30>=0,Допущения!$I$30<=1),Допущения!$I$30,NA())*Допущения!$B$24,NA())) -> 10 | H6: =IF(C6=0,0,F6*IF(AND(ISNUMBER(Допущения!$J$30),Допущения!$J$30>=0,Допущения!$J$30<=1),Допущения!$J$30,NA())) -> 0 | I6: =H6*IF(AND(ISNUMBER(Допущения!$K$30),Допущения!$K$30>=0,Допущения!$K$30<=1),Допущения!$K$30,NA()) -> 0 | J6: =IF(C6=0,0,IF(IF(AND(ISNUMBER(Допущения!$L$30),Допущения!$L$30>=0,Допущения!$L$30<=1),Допущения!$L$30,NA())*Допущения!$B$24<=1,I6*IF(AND(ISNUMBER(Допущения!$L$30),Допущения!$L$30>=0,Допущения!$L$30<=1),Допущения!$L$30,NA())*Допущения!$B$24,NA())) -> 0 | K6: =IF(1<=IF(AND(ISNUMBER(Допущения!$B$17),Допущения!$B$17>=0,Допущения!$B$17=INT(Допущения!$B$17),Допущения!$B$17<=12),Допущения!$B$17,NA()),0,INDEX($J$6:$J$41,(1-IF(AND(ISNUMBER(Допущения!$B$17),Допущения!$B$17>=0,Допущения!$B$17=INT(Допущения!$B$17),Допущения!$B$17<=12),Допущения!$B$17,NA())-1)*3+1)) -> 0 | L6: =G6+K6 -> 10 | M6: =I6*IF(AND(ISNUMBER(Допущения!$M$30),Допущения!$M$30>=0),Допущения!$M$30,NA()) -> 0 | N6: =M6*IF(AND(ISNUMBER(Допущения!$B$7),Допущения!$B$7>=0),Допущения!$B$7,NA()) -> 0
A7: Месяц 1 | B7: =Допущения!$A$31 -> Команда | C7: =Допущения!$N$31 -> 0 | D7: =IF(AND(COUNT(Допущения!$C$30:$C$32)=3,MIN(Допущения!$C$30:$C$32)>=0,MAX(Допущения!$C$30:$C$32)<=1,ABS(SUM(Допущения!$C$30:$C$32)-1)<0.00000001),IF(AND(ISNUMBER(Допущения!$B$40),Допущения!$B$40>=0),Допущения!$B$40,NA())*Допущения!$C$31,NA()) -> 17500 | E7: =IF(AND(ISNUMBER(Допущения!$H$31),Допущения!$H$31>0),Допущения!$H$31,NA())*Допущения!$B$23 -> 70 | F7: =D7/E7 -> 250 | G7: =IF(C7=1,0,IF(IF(AND(ISNUMBER(Допущения!$I$31),Допущения!$I$31>=0,Допущения!$I$31<=1),Допущения!$I$31,NA())*Допущения!$B$24<=1,F7*IF(AND(ISNUMBER(Допущения!$I$31),Допущения!$I$31>=0,Допущения!$I$31<=1),Допущения!$I$31,NA())*Допущения!$B$24,NA())) -> 2.25 | H7: =IF(C7=0,0,F7*IF(AND(ISNUMBER(Допущения!$J$31),Допущения!$J$31>=0,Допущения!$J$31<=1),Допущения!$J$31,NA())) -> 0 | I7: =H7*IF(AND(ISNUMBER(Допущения!$K$31),Допущения!$K$31>=0,Допущения!$K$31<=1),Допущения!$K$31,NA()) -> 0 | J7: =IF(C7=0,0,IF(IF(AND(ISNUMBER(Допущения!$L$31),Допущения!$L$31>=0,Допущения!$L$31<=1),Допущения!$L$31,NA())*Допущения!$B$24<=1,I7*IF(AND(ISNUMBER(Допущения!$L$31),Допущения!$L$31>=0,Допущения!$L$31<=1),Допущения!$L$31,NA())*Допущения!$B$24,NA())) -> 0 | K7: =IF(1<=IF(AND(ISNUMBER(Допущения!$B$17),Допущения!$B$17>=0,Допущения!$B$17=INT(Допущения!$B$17),Допущения!$B$17<=12),Допущения!$B$17,NA()),0,INDEX($J$6:$J$41,(1-IF(AND(ISNUMBER(Допущения!$B$17),Допущения!$B$17>=0,Допущения!$B$17=INT(Допущения!$B$17),Допущения!$B$17<=12),Допущения!$B$17,NA())-1)*3+2)) -> 0 | L7: =G7+K7 -> 2.25 | M7: =I7*IF(AND(ISNUMBER(Допущения!$M$31),Допущения!$M$31>=0),Допущения!$M$31,NA()) -> 0 | N7: =M7*IF(AND(ISNUMBER(Допущения!$B$7),Допущения!$B$7>=0),Допущения!$B$7,NA()) -> 0
A8: Месяц 1 | B8: =Допущения!$A$32 -> Бизнес | C8: =Допущения!$N$32 -> 1 | D8: =IF(AND(COUNT(Допущения!$C$30:$C$32)=3,MIN(Допущения!$C$30:$C$32)>=0,MAX(Допущения!$C$30:$C$32)<=1,ABS(SUM(Допущения!$C$30:$C$32)-1)<0.00000001),IF(AND(ISNUMBER(Допущения!$B$40),Допущения!$B$40>=0),Допущения!$B$40,NA())*Допущения!$C$32,NA()) -> 7500 | E8: =IF(AND(ISNUMBER(Допущения!$H$32),Допущения!$H$32>0),Допущения!$H$32,NA())*Допущения!$B$23 -> 120 | F8: =D8/E8 -> 62.5 | G8: =IF(C8=1,0,IF(IF(AND(ISNUMBER(Допущения!$I$32),Допущения!$I$32>=0,Допущения!$I$32<=1),Допущения!$I$32,NA())*Допущения!$B$24<=1,F8*IF(AND(ISNUMBER(Допущения!$I$32),Допущения!$I$32>=0,Допущения!$I$32<=1),Допущения!$I$32,NA())*Допущения!$B$24,NA())) -> 0 | H8: =IF(C8=0,0,F8*IF(AND(ISNUMBER(Допущения!$J$32),Допущения!$J$32>=0,Допущения!$J$32<=1),Допущения!$J$32,NA())) -> 2.5 | I8: =H8*IF(AND(ISNUMBER(Допущения!$K$32),Допущения!$K$32>=0,Допущения!$K$32<=1),Допущения!$K$32,NA()) -> 2 | J8: =IF(C8=0,0,IF(IF(AND(ISNUMBER(Допущения!$L$32),Допущения!$L$32>=0,Допущения!$L$32<=1),Допущения!$L$32,NA())*Допущения!$B$24<=1,I8*IF(AND(ISNUMBER(Допущения!$L$32),Допущения!$L$32>=0,Допущения!$L$32<=1),Допущения!$L$32,NA())*Допущения!$B$24,NA())) -> 0.6 | K8: =IF(1<=IF(AND(ISNUMBER(Допущения!$B$17),Допущения!$B$17>=0,Допущения!$B$17=INT(Допущения!$B$17),Допущения!$B$17<=12),Допущения!$B$17,NA()),0,INDEX($J$6:$J$41,(1-IF(AND(ISNUMBER(Допущения!$B$17),Допущения!$B$17>=0,Допущения!$B$17=INT(Допущения!$B$17),Допущения!$B$17<=12),Допущения!$B$17,NA())-1)*3+3)) -> 0 | L8: =G8+K8 -> 0 | M8: =I8*IF(AND(ISNUMBER(Допущения!$M$32),Допущения!$M$32>=0),Допущения!$M$32,NA()) -> 3 | N8: =M8*IF(AND(ISNUMBER(Допущения!$B$7),Допущения!$B$7>=0),Допущения!$B$7,NA()) -> 3000
A9: Месяц 2 | B9: =Допущения!$A$30 -> Старт | C9: =Допущения!$N$30 -> 0 | D9: =IF(AND(COUNT(Допущения!$C$30:$C$32)=3,MIN(Допущения!$C$30:$C$32)>=0,MAX(Допущения!$C$30:$C$32)<=1,ABS(SUM(Допущения!$C$30:$C$32)-1)<0.00000001),IF(AND(ISNUMBER(Допущения!$B$41),Допущения!$B$41>=0),Допущения!$B$41,NA())*Допущения!$C$30,NA()) -> 50000 | E9: =IF(AND(ISNUMBER(Допущения!$H$30),Допущения!$H$30>0),Допущения!$H$30,NA())*Допущения!$B$23 -> 45 | F9: =D9/E9 -> 1111.1111 | G9: =IF(C9=1,0,IF(IF(AND(ISNUMBER(Допущения!$I$30),Допущения!$I$30>=0,Допущения!$I$30<=1),Допущения!$I$30,NA())*Допущения!$B$24<=1,F9*IF(AND(ISNUMBER(Допущения!$I$30),Допущения!$I$30>=0,Допущения!$I$30<=1),Допущения!$I$30,NA())*Допущения!$B$24,NA())) -> 20 | H9: =IF(C9=0,0,F9*IF(AND(ISNUMBER(Допущения!$J$30),Допущения!$J$30>=0,Допущения!$J$30<=1),Допущения!$J$30,NA())) -> 0 | I9: =H9*IF(AND(ISNUMBER(Допущения!$K$30),Допущения!$K$30>=0,Допущения!$K$30<=1),Допущения!$K$30,NA()) -> 0 | J9: =IF(C9=0,0,IF(IF(AND(ISNUMBER(Допущения!$L$30),Допущения!$L$30>=0,Допущения!$L$30<=1),Допущения!$L$30,NA())*Допущения!$B$24<=1,I9*IF(AND(ISNUMBER(Допущения!$L$30),Допущения!$L$30>=0,Допущения!$L$30<=1),Допущения!$L$30,NA())*Допущения!$B$24,NA())) -> 0 | K9: =IF(2<=IF(AND(ISNUMBER(Допущения!$B$17),Допущения!$B$17>=0,Допущения!$B$17=INT(Допущения!$B$17),Допущения!$B$17<=12),Допущения!$B$17,NA()),0,INDEX($J$6:$J$41,(2-IF(AND(ISNUMBER(Допущения!$B$17),Допущения!$B$17>=0,Допущения!$B$17=INT(Допущения!$B$17),Допущения!$B$17<=12),Допущения!$B$17,NA())-1)*3+1)) -> 0 | L9: =G9+K9 -> 20 | M9: =I9*IF(AND(ISNUMBER(Допущения!$M$30),Допущения!$M$30>=0),Допущения!$M$30,NA()) -> 0 | N9: =M9*IF(AND(ISNUMBER(Допущения!$B$7),Допущения!$B$7>=0),Допущения!$B$7,NA()) -> 0
A10: Месяц 2 | B10: =Допущения!$A$31 -> Команда | C10: =Допущения!$N$31 -> 0 | D10: =IF(AND(COUNT(Допущения!$C$30:$C$32)=3,MIN(Допущения!$C$30:$C$32)>=0,MAX(Допущения!$C$30:$C$32)<=1,ABS(SUM(Допущения!$C$30:$C$32)-1)<0.00000001),IF(AND(ISNUMBER(Допущения!$B$41),Допущения!$B$41>=0),Допущения!$B$41,NA())*Допущения!$C$31,NA()) -> 35000 | E10: =IF(AND(ISNUMBER(Допущения!$H$31),Допущения!$H$31>0),Допущения!$H$31,NA())*Допущения!$B$23 -> 70 | F10: =D10/E10 -> 500 | G10: =IF(C10=1,0,IF(IF(AND(ISNUMBER(Допущения!$I$31),Допущения!$I$31>=0,Допущения!$I$31<=1),Допущения!$I$31,NA())*Допущения!$B$24<=1,F10*IF(AND(ISNUMBER(Допущения!$I$31),Допущения!$I$31>=0,Допущения!$I$31<=1),Допущения!$I$31,NA())*Допущения!$B$24,NA())) -> 4.5 | H10: =IF(C10=0,0,F10*IF(AND(ISNUMBER(Допущения!$J$31),Допущения!$J$31>=0,Допущения!$J$31<=1),Допущения!$J$31,NA())) -> 0 | I10: =H10*IF(AND(ISNUMBER(Допущения!$K$31),Допущения!$K$31>=0,Допущения!$K$31<=1),Допущения!$K$31,NA()) -> 0 | J10: =IF(C10=0,0,IF(IF(AND(ISNUMBER(Допущения!$L$31),Допущения!$L$31>=0,Допущения!$L$31<=1),Допущения!$L$31,NA())*Допущения!$B$24<=1,I10*IF(AND(ISNUMBER(Допущения!$L$31),Допущения!$L$31>=0,Допущения!$L$31<=1),Допущения!$L$31,NA())*Допущения!$B$24,NA())) -> 0 | K10: =IF(2<=IF(AND(ISNUMBER(Допущения!$B$17),Допущения!$B$17>=0,Допущения!$B$17=INT(Допущения!$B$17),Допущения!$B$17<=12),Допущения!$B$17,NA()),0,INDEX($J$6:$J$41,(2-IF(AND(ISNUMBER(Допущения!$B$17),Допущения!$B$17>=0,Допущения!$B$17=INT(Допущения!$B$17),Допущения!$B$17<=12),Допущения!$B$17,NA())-1)*3+2)) -> 0 | L10: =G10+K10 -> 4.5 | M10: =I10*IF(AND(ISNUMBER(Допущения!$M$31),Допущения!$M$31>=0),Допущения!$M$31,NA()) -> 0 | N10: =M10*IF(AND(ISNUMBER(Допущения!$B$7),Допущения!$B$7>=0),Допущения!$B$7,NA()) -> 0
A11: Месяц 2 | B11: =Допущения!$A$32 -> Бизнес | C11: =Допущения!$N$32 -> 1 | D11: =IF(AND(COUNT(Допущения!$C$30:$C$32)=3,MIN(Допущения!$C$30:$C$32)>=0,MAX(Допущения!$C$30:$C$32)<=1,ABS(SUM(Допущения!$C$30:$C$32)-1)<0.00000001),IF(AND(ISNUMBER(Допущения!$B$41),Допущения!$B$41>=0),Допущения!$B$41,NA())*Допущения!$C$32,NA()) -> 15000 | E11: =IF(AND(ISNUMBER(Допущения!$H$32),Допущения!$H$32>0),Допущения!$H$32,NA())*Допущения!$B$23 -> 120 | F11: =D11/E11 -> 125 | G11: =IF(C11=1,0,IF(IF(AND(ISNUMBER(Допущения!$I$32),Допущения!$I$32>=0,Допущения!$I$32<=1),Допущения!$I$32,NA())*Допущения!$B$24<=1,F11*IF(AND(ISNUMBER(Допущения!$I$32),Допущения!$I$32>=0,Допущения!$I$32<=1),Допущения!$I$32,NA())*Допущения!$B$24,NA())) -> 0 | H11: =IF(C11=0,0,F11*IF(AND(ISNUMBER(Допущения!$J$32),Допущения!$J$32>=0,Допущения!$J$32<=1),Допущения!$J$32,NA())) -> 5 | I11: =H11*IF(AND(ISNUMBER(Допущения!$K$32),Допущения!$K$32>=0,Допущения!$K$32<=1),Допущения!$K$32,NA()) -> 4 | J11: =IF(C11=0,0,IF(IF(AND(ISNUMBER(Допущения!$L$32),Допущения!$L$32>=0,Допущения!$L$32<=1),Допущения!$L$32,NA())*Допущения!$B$24<=1,I11*IF(AND(ISNUMBER(Допущения!$L$32),Допущения!$L$32>=0,Допущения!$L$32<=1),Допущения!$L$32,NA())*Допущения!$B$24,NA())) -> 1.2 | K11: =IF(2<=IF(AND(ISNUMBER(Допущения!$B$17),Допущения!$B$17>=0,Допущения!$B$17=INT(Допущения!$B$17),Допущения!$B$17<=12),Допущения!$B$17,NA()),0,INDEX($J$6:$J$41,(2-IF(AND(ISNUMBER(Допущения!$B$17),Допущения!$B$17>=0,Допущения!$B$17=INT(Допущения!$B$17),Допущения!$B$17<=12),Допущения!$B$17,NA())-1)*3+3)) -> 0.6 | L11: =G11+K11 -> 0.6 | M11: =I11*IF(AND(ISNUMBER(Допущения!$M$32),Допущения!$M$32>=0),Допущения!$M$32,NA()) -> 6 | N11: =M11*IF(AND(ISNUMBER(Допущения!$B$7),Допущения!$B$7>=0),Допущения!$B$7,NA()) -> 6000
A12: Месяц 3 | B12: =Допущения!$A$30 -> Старт | C12: =Допущения!$N$30 -> 0 | D12: =IF(AND(COUNT(Допущения!$C$30:$C$32)=3,MIN(Допущения!$C$30:$C$32)>=0,MAX(Допущения!$C$30:$C$32)<=1,ABS(SUM(Допущения!$C$30:$C$32)-1)<0.00000001),IF(AND(ISNUMBER(Допущения!$B$42),Допущения!$B$42>=0),Допущения!$B$42,NA())*Допущения!$C$30,NA()) -> 75000 | E12: =IF(AND(ISNUMBER(Допущения!$H$30),Допущения!$H$30>0),Допущения!$H$30,NA())*Допущения!$B$23 -> 45 | F12: =D12/E12 -> 1666.6667 | G12: =IF(C12=1,0,IF(IF(AND(ISNUMBER(Допущения!$I$30),Допущения!$I$30>=0,Допущения!$I$30<=1),Допущения!$I$30,NA())*Допущения!$B$24<=1,F12*IF(AND(ISNUMBER(Допущения!$I$30),Допущения!$I$30>=0,Допущения!$I$30<=1),Допущения!$I$30,NA())*Допущения!$B$24,NA())) -> 30 | H12: =IF(C12=0,0,F12*IF(AND(ISNUMBER(Допущения!$J$30),Допущения!$J$30>=0,Допущения!$J$30<=1),Допущения!$J$30,NA())) -> 0 | I12: =H12*IF(AND(ISNUMBER(Допущения!$K$30),Допущения!$K$30>=0,Допущения!$K$30<=1),Допущения!$K$30,NA()) -> 0 | J12: =IF(C12=0,0,IF(IF(AND(ISNUMBER(Допущения!$L$30),Допущения!$L$30>=0,Допущения!$L$30<=1),Допущения!$L$30,NA())*Допущения!$B$24<=1,I12*IF(AND(ISNUMBER(Допущения!$L$30),Допущения!$L$30>=0,Допущения!$L$30<=1),Допущения!$L$30,NA())*Допущения!$B$24,NA())) -> 0 | K12: =IF(3<=IF(AND(ISNUMBER(Допущения!$B$17),Допущения!$B$17>=0,Допущения!$B$17=INT(Допущения!$B$17),Допущения!$B$17<=12),Допущения!$B$17,NA()),0,INDEX($J$6:$J$41,(3-IF(AND(ISNUMBER(Допущения!$B$17),Допущения!$B$17>=0,Допущения!$B$17=INT(Допущения!$B$17),Допущения!$B$17<=12),Допущения!$B$17,NA())-1)*3+1)) -> 0 | L12: =G12+K12 -> 30 | M12: =I12*IF(AND(ISNUMBER(Допущения!$M$30),Допущения!$M$30>=0),Допущения!$M$30,NA()) -> 0 | N12: =M12*IF(AND(ISNUMBER(Допущения!$B$7),Допущения!$B$7>=0),Допущения!$B$7,NA()) -> 0
A13: Месяц 3 | B13: =Допущения!$A$31 -> Команда | C13: =Допущения!$N$31 -> 0 | D13: =IF(AND(COUNT(Допущения!$C$30:$C$32)=3,MIN(Допущения!$C$30:$C$32)>=0,MAX(Допущения!$C$30:$C$32)<=1,ABS(SUM(Допущения!$C$30:$C$32)-1)<0.00000001),IF(AND(ISNUMBER(Допущения!$B$42),Допущения!$B$42>=0),Допущения!$B$42,NA())*Допущения!$C$31,NA()) -> 52500 | E13: =IF(AND(ISNUMBER(Допущения!$H$31),Допущения!$H$31>0),Допущения!$H$31,NA())*Допущения!$B$23 -> 70 | F13: =D13/E13 -> 750 | G13: =IF(C13=1,0,IF(IF(AND(ISNUMBER(Допущения!$I$31),Допущения!$I$31>=0,Допущения!$I$31<=1),Допущения!$I$31,NA())*Допущения!$B$24<=1,F13*IF(AND(ISNUMBER(Допущения!$I$31),Допущения!$I$31>=0,Допущения!$I$31<=1),Допущения!$I$31,NA())*Допущения!$B$24,NA())) -> 6.75 | H13: =IF(C13=0,0,F13*IF(AND(ISNUMBER(Допущения!$J$31),Допущения!$J$31>=0,Допущения!$J$31<=1),Допущения!$J$31,NA())) -> 0 | I13: =H13*IF(AND(ISNUMBER(Допущения!$K$31),Допущения!$K$31>=0,Допущения!$K$31<=1),Допущения!$K$31,NA()) -> 0 | J13: =IF(C13=0,0,IF(IF(AND(ISNUMBER(Допущения!$L$31),Допущения!$L$31>=0,Допущения!$L$31<=1),Допущения!$L$31,NA())*Допущения!$B$24<=1,I13*IF(AND(ISNUMBER(Допущения!$L$31),Допущения!$L$31>=0,Допущения!$L$31<=1),Допущения!$L$31,NA())*Допущения!$B$24,NA())) -> 0 | K13: =IF(3<=IF(AND(ISNUMBER(Допущения!$B$17),Допущения!$B$17>=0,Допущения!$B$17=INT(Допущения!$B$17),Допущения!$B$17<=12),Допущения!$B$17,NA()),0,INDEX($J$6:$J$41,(3-IF(AND(ISNUMBER(Допущения!$B$17),Допущения!$B$17>=0,Допущения!$B$17=INT(Допущения!$B$17),Допущения!$B$17<=12),Допущения!$B$17,NA())-1)*3+2)) -> 0 | L13: =G13+K13 -> 6.75 | M13: =I13*IF(AND(ISNUMBER(Допущения!$M$31),Допущения!$M$31>=0),Допущения!$M$31,NA()) -> 0 | N13: =M13*IF(AND(ISNUMBER(Допущения!$B$7),Допущения!$B$7>=0),Допущения!$B$7,NA()) -> 0
A14: Месяц 3 | B14: =Допущения!$A$32 -> Бизнес | C14: =Допущения!$N$32 -> 1 | D14: =IF(AND(COUNT(Допущения!$C$30:$C$32)=3,MIN(Допущения!$C$30:$C$32)>=0,MAX(Допущения!$C$30:$C$32)<=1,ABS(SUM(Допущения!$C$30:$C$32)-1)<0.00000001),IF(AND(ISNUMBER(Допущения!$B$42),Допущения!$B$42>=0),Допущения!$B$42,NA())*Допущения!$C$32,NA()) -> 22500 | E14: =IF(AND(ISNUMBER(Допущения!$H$32),Допущения!$H$32>0),Допущения!$H$32,NA())*Допущения!$B$23 -> 120 | F14: =D14/E14 -> 187.5 | G14: =IF(C14=1,0,IF(IF(AND(ISNUMBER(Допущения!$I$32),Допущения!$I$32>=0,Допущения!$I$32<=1),Допущения!$I$32,NA())*Допущения!$B$24<=1,F14*IF(AND(ISNUMBER(Допущения!$I$32),Допущения!$I$32>=0,Допущения!$I$32<=1),Допущения!$I$32,NA())*Допущения!$B$24,NA())) -> 0 | H14: =IF(C14=0,0,F14*IF(AND(ISNUMBER(Допущения!$J$32),Допущения!$J$32>=0,Допущения!$J$32<=1),Допущения!$J$32,NA())) -> 7.5 | I14: =H14*IF(AND(ISNUMBER(Допущения!$K$32),Допущения!$K$32>=0,Допущения!$K$32<=1),Допущения!$K$32,NA()) -> 6 | J14: =IF(C14=0,0,IF(IF(AND(ISNUMBER(Допущения!$L$32),Допущения!$L$32>=0,Допущения!$L$32<=1),Допущения!$L$32,NA())*Допущения!$B$24<=1,I14*IF(AND(ISNUMBER(Допущения!$L$32),Допущения!$L$32>=0,Допущения!$L$32<=1),Допущения!$L$32,NA())*Допущения!$B$24,NA())) -> 1.8 | K14: =IF(3<=IF(AND(ISNUMBER(Допущения!$B$17),Допущения!$B$17>=0,Допущения!$B$17=INT(Допущения!$B$17),Допущения!$B$17<=12),Допущения!$B$17,NA()),0,INDEX($J$6:$J$41,(3-IF(AND(ISNUMBER(Допущения!$B$17),Допущения!$B$17>=0,Допущения!$B$17=INT(Допущения!$B$17),Допущения!$B$17<=12),Допущения!$B$17,NA())-1)*3+3)) -> 1.2 | L14: =G14+K14 -> 1.2 | M14: =I14*IF(AND(ISNUMBER(Допущения!$M$32),Допущения!$M$32>=0),Допущения!$M$32,NA()) -> 9 | N14: =M14*IF(AND(ISNUMBER(Допущения!$B$7),Допущения!$B$7>=0),Допущения!$B$7,NA()) -> 9000
A15: Месяц 4 | B15: =Допущения!$A$30 -> Старт | C15: =Допущения!$N$30 -> 0 | D15: =IF(AND(COUNT(Допущения!$C$30:$C$32)=3,MIN(Допущения!$C$30:$C$32)>=0,MAX(Допущения!$C$30:$C$32)<=1,ABS(SUM(Допущения!$C$30:$C$32)-1)<0.00000001),IF(AND(ISNUMBER(Допущения!$B$43),Допущения!$B$43>=0),Допущения!$B$43,NA())*Допущения!$C$30,NA()) -> 100000 | E15: =IF(AND(ISNUMBER(Допущения!$H$30),Допущения!$H$30>0),Допущения!$H$30,NA())*Допущения!$B$23 -> 45 | F15: =D15/E15 -> 2222.2222 | G15: =IF(C15=1,0,IF(IF(AND(ISNUMBER(Допущения!$I$30),Допущения!$I$30>=0,Допущения!$I$30<=1),Допущения!$I$30,NA())*Допущения!$B$24<=1,F15*IF(AND(ISNUMBER(Допущения!$I$30),Допущения!$I$30>=0,Допущения!$I$30<=1),Допущения!$I$30,NA())*Допущения!$B$24,NA())) -> 40 | H15: =IF(C15=0,0,F15*IF(AND(ISNUMBER(Допущения!$J$30),Допущения!$J$30>=0,Допущения!$J$30<=1),Допущения!$J$30,NA())) -> 0 | I15: =H15*IF(AND(ISNUMBER(Допущения!$K$30),Допущения!$K$30>=0,Допущения!$K$30<=1),Допущения!$K$30,NA()) -> 0 | J15: =IF(C15=0,0,IF(IF(AND(ISNUMBER(Допущения!$L$30),Допущения!$L$30>=0,Допущения!$L$30<=1),Допущения!$L$30,NA())*Допущения!$B$24<=1,I15*IF(AND(ISNUMBER(Допущения!$L$30),Допущения!$L$30>=0,Допущения!$L$30<=1),Допущения!$L$30,NA())*Допущения!$B$24,NA())) -> 0 | K15: =IF(4<=IF(AND(ISNUMBER(Допущения!$B$17),Допущения!$B$17>=0,Допущения!$B$17=INT(Допущения!$B$17),Допущения!$B$17<=12),Допущения!$B$17,NA()),0,INDEX($J$6:$J$41,(4-IF(AND(ISNUMBER(Допущения!$B$17),Допущения!$B$17>=0,Допущения!$B$17=INT(Допущения!$B$17),Допущения!$B$17<=12),Допущения!$B$17,NA())-1)*3+1)) -> 0 | L15: =G15+K15 -> 40 | M15: =I15*IF(AND(ISNUMBER(Допущения!$M$30),Допущения!$M$30>=0),Допущения!$M$30,NA()) -> 0 | N15: =M15*IF(AND(ISNUMBER(Допущения!$B$7),Допущения!$B$7>=0),Допущения!$B$7,NA()) -> 0
A16: Месяц 4 | B16: =Допущения!$A$31 -> Команда | C16: =Допущения!$N$31 -> 0 | D16: =IF(AND(COUNT(Допущения!$C$30:$C$32)=3,MIN(Допущения!$C$30:$C$32)>=0,MAX(Допущения!$C$30:$C$32)<=1,ABS(SUM(Допущения!$C$30:$C$32)-1)<0.00000001),IF(AND(ISNUMBER(Допущения!$B$43),Допущения!$B$43>=0),Допущения!$B$43,NA())*Допущения!$C$31,NA()) -> 70000 | E16: =IF(AND(ISNUMBER(Допущения!$H$31),Допущения!$H$31>0),Допущения!$H$31,NA())*Допущения!$B$23 -> 70 | F16: =D16/E16 -> 1000 | G16: =IF(C16=1,0,IF(IF(AND(ISNUMBER(Допущения!$I$31),Допущения!$I$31>=0,Допущения!$I$31<=1),Допущения!$I$31,NA())*Допущения!$B$24<=1,F16*IF(AND(ISNUMBER(Допущения!$I$31),Допущения!$I$31>=0,Допущения!$I$31<=1),Допущения!$I$31,NA())*Допущения!$B$24,NA())) -> 9 | H16: =IF(C16=0,0,F16*IF(AND(ISNUMBER(Допущения!$J$31),Допущения!$J$31>=0,Допущения!$J$31<=1),Допущения!$J$31,NA())) -> 0 | I16: =H16*IF(AND(ISNUMBER(Допущения!$K$31),Допущения!$K$31>=0,Допущения!$K$31<=1),Допущения!$K$31,NA()) -> 0 | J16: =IF(C16=0,0,IF(IF(AND(ISNUMBER(Допущения!$L$31),Допущения!$L$31>=0,Допущения!$L$31<=1),Допущения!$L$31,NA())*Допущения!$B$24<=1,I16*IF(AND(ISNUMBER(Допущения!$L$31),Допущения!$L$31>=0,Допущения!$L$31<=1),Допущения!$L$31,NA())*Допущения!$B$24,NA())) -> 0 | K16: =IF(4<=IF(AND(ISNUMBER(Допущения!$B$17),Допущения!$B$17>=0,Допущения!$B$17=INT(Допущения!$B$17),Допущения!$B$17<=12),Допущения!$B$17,NA()),0,INDEX($J$6:$J$41,(4-IF(AND(ISNUMBER(Допущения!$B$17),Допущения!$B$17>=0,Допущения!$B$17=INT(Допущения!$B$17),Допущения!$B$17<=12),Допущения!$B$17,NA())-1)*3+2)) -> 0 | L16: =G16+K16 -> 9 | M16: =I16*IF(AND(ISNUMBER(Допущения!$M$31),Допущения!$M$31>=0),Допущения!$M$31,NA()) -> 0 | N16: =M16*IF(AND(ISNUMBER(Допущения!$B$7),Допущения!$B$7>=0),Допущения!$B$7,NA()) -> 0
A17: Месяц 4 | B17: =Допущения!$A$32 -> Бизнес | C17: =Допущения!$N$32 -> 1 | D17: =IF(AND(COUNT(Допущения!$C$30:$C$32)=3,MIN(Допущения!$C$30:$C$32)>=0,MAX(Допущения!$C$30:$C$32)<=1,ABS(SUM(Допущения!$C$30:$C$32)-1)<0.00000001),IF(AND(ISNUMBER(Допущения!$B$43),Допущения!$B$43>=0),Допущения!$B$43,NA())*Допущения!$C$32,NA()) -> 30000 | E17: =IF(AND(ISNUMBER(Допущения!$H$32),Допущения!$H$32>0),Допущения!$H$32,NA())*Допущения!$B$23 -> 120 | F17: =D17/E17 -> 250 | G17: =IF(C17=1,0,IF(IF(AND(ISNUMBER(Допущения!$I$32),Допущения!$I$32>=0,Допущения!$I$32<=1),Допущения!$I$32,NA())*Допущения!$B$24<=1,F17*IF(AND(ISNUMBER(Допущения!$I$32),Допущения!$I$32>=0,Допущения!$I$32<=1),Допущения!$I$32,NA())*Допущения!$B$24,NA())) -> 0 | H17: =IF(C17=0,0,F17*IF(AND(ISNUMBER(Допущения!$J$32),Допущения!$J$32>=0,Допущения!$J$32<=1),Допущения!$J$32,NA())) -> 10 | I17: =H17*IF(AND(ISNUMBER(Допущения!$K$32),Допущения!$K$32>=0,Допущения!$K$32<=1),Допущения!$K$32,NA()) -> 8 | J17: =IF(C17=0,0,IF(IF(AND(ISNUMBER(Допущения!$L$32),Допущения!$L$32>=0,Допущения!$L$32<=1),Допущения!$L$32,NA())*Допущения!$B$24<=1,I17*IF(AND(ISNUMBER(Допущения!$L$32),Допущения!$L$32>=0,Допущения!$L$32<=1),Допущения!$L$32,NA())*Допущения!$B$24,NA())) -> 2.4 | K17: =IF(4<=IF(AND(ISNUMBER(Допущения!$B$17),Допущения!$B$17>=0,Допущения!$B$17=INT(Допущения!$B$17),Допущения!$B$17<=12),Допущения!$B$17,NA()),0,INDEX($J$6:$J$41,(4-IF(AND(ISNUMBER(Допущения!$B$17),Допущения!$B$17>=0,Допущения!$B$17=INT(Допущения!$B$17),Допущения!$B$17<=12),Допущения!$B$17,NA())-1)*3+3)) -> 1.8 | L17: =G17+K17 -> 1.8 | M17: =I17*IF(AND(ISNUMBER(Допущения!$M$32),Допущения!$M$32>=0),Допущения!$M$32,NA()) -> 12 | N17: =M17*IF(AND(ISNUMBER(Допущения!$B$7),Допущения!$B$7>=0),Допущения!$B$7,NA()) -> 12000
A18: Месяц 5 | B18: =Допущения!$A$30 -> Старт | C18: =Допущения!$N$30 -> 0 | D18: =IF(AND(COUNT(Допущения!$C$30:$C$32)=3,MIN(Допущения!$C$30:$C$32)>=0,MAX(Допущения!$C$30:$C$32)<=1,ABS(SUM(Допущения!$C$30:$C$32)-1)<0.00000001),IF(AND(ISNUMBER(Допущения!$B$44),Допущения!$B$44>=0),Допущения!$B$44,NA())*Допущения!$C$30,NA()) -> 100000 | E18: =IF(AND(ISNUMBER(Допущения!$H$30),Допущения!$H$30>0),Допущения!$H$30,NA())*Допущения!$B$23 -> 45 | F18: =D18/E18 -> 2222.2222 | G18: =IF(C18=1,0,IF(IF(AND(ISNUMBER(Допущения!$I$30),Допущения!$I$30>=0,Допущения!$I$30<=1),Допущения!$I$30,NA())*Допущения!$B$24<=1,F18*IF(AND(ISNUMBER(Допущения!$I$30),Допущения!$I$30>=0,Допущения!$I$30<=1),Допущения!$I$30,NA())*Допущения!$B$24,NA())) -> 40 | H18: =IF(C18=0,0,F18*IF(AND(ISNUMBER(Допущения!$J$30),Допущения!$J$30>=0,Допущения!$J$30<=1),Допущения!$J$30,NA())) -> 0 | I18: =H18*IF(AND(ISNUMBER(Допущения!$K$30),Допущения!$K$30>=0,Допущения!$K$30<=1),Допущения!$K$30,NA()) -> 0 | J18: =IF(C18=0,0,IF(IF(AND(ISNUMBER(Допущения!$L$30),Допущения!$L$30>=0,Допущения!$L$30<=1),Допущения!$L$30,NA())*Допущения!$B$24<=1,I18*IF(AND(ISNUMBER(Допущения!$L$30),Допущения!$L$30>=0,Допущения!$L$30<=1),Допущения!$L$30,NA())*Допущения!$B$24,NA())) -> 0 | K18: =IF(5<=IF(AND(ISNUMBER(Допущения!$B$17),Допущения!$B$17>=0,Допущения!$B$17=INT(Допущения!$B$17),Допущения!$B$17<=12),Допущения!$B$17,NA()),0,INDEX($J$6:$J$41,(5-IF(AND(ISNUMBER(Допущения!$B$17),Допущения!$B$17>=0,Допущения!$B$17=INT(Допущения!$B$17),Допущения!$B$17<=12),Допущения!$B$17,NA())-1)*3+1)) -> 0 | L18: =G18+K18 -> 40 | M18: =I18*IF(AND(ISNUMBER(Допущения!$M$30),Допущения!$M$30>=0),Допущения!$M$30,NA()) -> 0 | N18: =M18*IF(AND(ISNUMBER(Допущения!$B$7),Допущения!$B$7>=0),Допущения!$B$7,NA()) -> 0
A19: Месяц 5 | B19: =Допущения!$A$31 -> Команда | C19: =Допущения!$N$31 -> 0 | D19: =IF(AND(COUNT(Допущения!$C$30:$C$32)=3,MIN(Допущения!$C$30:$C$32)>=0,MAX(Допущения!$C$30:$C$32)<=1,ABS(SUM(Допущения!$C$30:$C$32)-1)<0.00000001),IF(AND(ISNUMBER(Допущения!$B$44),Допущения!$B$44>=0),Допущения!$B$44,NA())*Допущения!$C$31,NA()) -> 70000 | E19: =IF(AND(ISNUMBER(Допущения!$H$31),Допущения!$H$31>0),Допущения!$H$31,NA())*Допущения!$B$23 -> 70 | F19: =D19/E19 -> 1000 | G19: =IF(C19=1,0,IF(IF(AND(ISNUMBER(Допущения!$I$31),Допущения!$I$31>=0,Допущения!$I$31<=1),Допущения!$I$31,NA())*Допущения!$B$24<=1,F19*IF(AND(ISNUMBER(Допущения!$I$31),Допущения!$I$31>=0,Допущения!$I$31<=1),Допущения!$I$31,NA())*Допущения!$B$24,NA())) -> 9 | H19: =IF(C19=0,0,F19*IF(AND(ISNUMBER(Допущения!$J$31),Допущения!$J$31>=0,Допущения!$J$31<=1),Допущения!$J$31,NA())) -> 0 | I19: =H19*IF(AND(ISNUMBER(Допущения!$K$31),Допущения!$K$31>=0,Допущения!$K$31<=1),Допущения!$K$31,NA()) -> 0 | J19: =IF(C19=0,0,IF(IF(AND(ISNUMBER(Допущения!$L$31),Допущения!$L$31>=0,Допущения!$L$31<=1),Допущения!$L$31,NA())*Допущения!$B$24<=1,I19*IF(AND(ISNUMBER(Допущения!$L$31),Допущения!$L$31>=0,Допущения!$L$31<=1),Допущения!$L$31,NA())*Допущения!$B$24,NA())) -> 0 | K19: =IF(5<=IF(AND(ISNUMBER(Допущения!$B$17),Допущения!$B$17>=0,Допущения!$B$17=INT(Допущения!$B$17),Допущения!$B$17<=12),Допущения!$B$17,NA()),0,INDEX($J$6:$J$41,(5-IF(AND(ISNUMBER(Допущения!$B$17),Допущения!$B$17>=0,Допущения!$B$17=INT(Допущения!$B$17),Допущения!$B$17<=12),Допущения!$B$17,NA())-1)*3+2)) -> 0 | L19: =G19+K19 -> 9 | M19: =I19*IF(AND(ISNUMBER(Допущения!$M$31),Допущения!$M$31>=0),Допущения!$M$31,NA()) -> 0 | N19: =M19*IF(AND(ISNUMBER(Допущения!$B$7),Допущения!$B$7>=0),Допущения!$B$7,NA()) -> 0
A20: Месяц 5 | B20: =Допущения!$A$32 -> Бизнес | C20: =Допущения!$N$32 -> 1 | D20: =IF(AND(COUNT(Допущения!$C$30:$C$32)=3,MIN(Допущения!$C$30:$C$32)>=0,MAX(Допущения!$C$30:$C$32)<=1,ABS(SUM(Допущения!$C$30:$C$32)-1)<0.00000001),IF(AND(ISNUMBER(Допущения!$B$44),Допущения!$B$44>=0),Допущения!$B$44,NA())*Допущения!$C$32,NA()) -> 30000 | E20: =IF(AND(ISNUMBER(Допущения!$H$32),Допущения!$H$32>0),Допущения!$H$32,NA())*Допущения!$B$23 -> 120 | F20: =D20/E20 -> 250 | G20: =IF(C20=1,0,IF(IF(AND(ISNUMBER(Допущения!$I$32),Допущения!$I$32>=0,Допущения!$I$32<=1),Допущения!$I$32,NA())*Допущения!$B$24<=1,F20*IF(AND(ISNUMBER(Допущения!$I$32),Допущения!$I$32>=0,Допущения!$I$32<=1),Допущения!$I$32,NA())*Допущения!$B$24,NA())) -> 0 | H20: =IF(C20=0,0,F20*IF(AND(ISNUMBER(Допущения!$J$32),Допущения!$J$32>=0,Допущения!$J$32<=1),Допущения!$J$32,NA())) -> 10 | I20: =H20*IF(AND(ISNUMBER(Допущения!$K$32),Допущения!$K$32>=0,Допущения!$K$32<=1),Допущения!$K$32,NA()) -> 8 | J20: =IF(C20=0,0,IF(IF(AND(ISNUMBER(Допущения!$L$32),Допущения!$L$32>=0,Допущения!$L$32<=1),Допущения!$L$32,NA())*Допущения!$B$24<=1,I20*IF(AND(ISNUMBER(Допущения!$L$32),Допущения!$L$32>=0,Допущения!$L$32<=1),Допущения!$L$32,NA())*Допущения!$B$24,NA())) -> 2.4 | K20: =IF(5<=IF(AND(ISNUMBER(Допущения!$B$17),Допущения!$B$17>=0,Допущения!$B$17=INT(Допущения!$B$17),Допущения!$B$17<=12),Допущения!$B$17,NA()),0,INDEX($J$6:$J$41,(5-IF(AND(ISNUMBER(Допущения!$B$17),Допущения!$B$17>=0,Допущения!$B$17=INT(Допущения!$B$17),Допущения!$B$17<=12),Допущения!$B$17,NA())-1)*3+3)) -> 2.4 | L20: =G20+K20 -> 2.4 | M20: =I20*IF(AND(ISNUMBER(Допущения!$M$32),Допущения!$M$32>=0),Допущения!$M$32,NA()) -> 12 | N20: =M20*IF(AND(ISNUMBER(Допущения!$B$7),Допущения!$B$7>=0),Допущения!$B$7,NA()) -> 12000
A21: Месяц 6 | B21: =Допущения!$A$30 -> Старт | C21: =Допущения!$N$30 -> 0 | D21: =IF(AND(COUNT(Допущения!$C$30:$C$32)=3,MIN(Допущения!$C$30:$C$32)>=0,MAX(Допущения!$C$30:$C$32)<=1,ABS(SUM(Допущения!$C$30:$C$32)-1)<0.00000001),IF(AND(ISNUMBER(Допущения!$B$45),Допущения!$B$45>=0),Допущения!$B$45,NA())*Допущения!$C$30,NA()) -> 100000 | E21: =IF(AND(ISNUMBER(Допущения!$H$30),Допущения!$H$30>0),Допущения!$H$30,NA())*Допущения!$B$23 -> 45 | F21: =D21/E21 -> 2222.2222 | G21: =IF(C21=1,0,IF(IF(AND(ISNUMBER(Допущения!$I$30),Допущения!$I$30>=0,Допущения!$I$30<=1),Допущения!$I$30,NA())*Допущения!$B$24<=1,F21*IF(AND(ISNUMBER(Допущения!$I$30),Допущения!$I$30>=0,Допущения!$I$30<=1),Допущения!$I$30,NA())*Допущения!$B$24,NA())) -> 40 | H21: =IF(C21=0,0,F21*IF(AND(ISNUMBER(Допущения!$J$30),Допущения!$J$30>=0,Допущения!$J$30<=1),Допущения!$J$30,NA())) -> 0 | I21: =H21*IF(AND(ISNUMBER(Допущения!$K$30),Допущения!$K$30>=0,Допущения!$K$30<=1),Допущения!$K$30,NA()) -> 0 | J21: =IF(C21=0,0,IF(IF(AND(ISNUMBER(Допущения!$L$30),Допущения!$L$30>=0,Допущения!$L$30<=1),Допущения!$L$30,NA())*Допущения!$B$24<=1,I21*IF(AND(ISNUMBER(Допущения!$L$30),Допущения!$L$30>=0,Допущения!$L$30<=1),Допущения!$L$30,NA())*Допущения!$B$24,NA())) -> 0 | K21: =IF(6<=IF(AND(ISNUMBER(Допущения!$B$17),Допущения!$B$17>=0,Допущения!$B$17=INT(Допущения!$B$17),Допущения!$B$17<=12),Допущения!$B$17,NA()),0,INDEX($J$6:$J$41,(6-IF(AND(ISNUMBER(Допущения!$B$17),Допущения!$B$17>=0,Допущения!$B$17=INT(Допущения!$B$17),Допущения!$B$17<=12),Допущения!$B$17,NA())-1)*3+1)) -> 0 | L21: =G21+K21 -> 40 | M21: =I21*IF(AND(ISNUMBER(Допущения!$M$30),Допущения!$M$30>=0),Допущения!$M$30,NA()) -> 0 | N21: =M21*IF(AND(ISNUMBER(Допущения!$B$7),Допущения!$B$7>=0),Допущения!$B$7,NA()) -> 0
A22: Месяц 6 | B22: =Допущения!$A$31 -> Команда | C22: =Допущения!$N$31 -> 0 | D22: =IF(AND(COUNT(Допущения!$C$30:$C$32)=3,MIN(Допущения!$C$30:$C$32)>=0,MAX(Допущения!$C$30:$C$32)<=1,ABS(SUM(Допущения!$C$30:$C$32)-1)<0.00000001),IF(AND(ISNUMBER(Допущения!$B$45),Допущения!$B$45>=0),Допущения!$B$45,NA())*Допущения!$C$31,NA()) -> 70000 | E22: =IF(AND(ISNUMBER(Допущения!$H$31),Допущения!$H$31>0),Допущения!$H$31,NA())*Допущения!$B$23 -> 70 | F22: =D22/E22 -> 1000 | G22: =IF(C22=1,0,IF(IF(AND(ISNUMBER(Допущения!$I$31),Допущения!$I$31>=0,Допущения!$I$31<=1),Допущения!$I$31,NA())*Допущения!$B$24<=1,F22*IF(AND(ISNUMBER(Допущения!$I$31),Допущения!$I$31>=0,Допущения!$I$31<=1),Допущения!$I$31,NA())*Допущения!$B$24,NA())) -> 9 | H22: =IF(C22=0,0,F22*IF(AND(ISNUMBER(Допущения!$J$31),Допущения!$J$31>=0,Допущения!$J$31<=1),Допущения!$J$31,NA())) -> 0 | I22: =H22*IF(AND(ISNUMBER(Допущения!$K$31),Допущения!$K$31>=0,Допущения!$K$31<=1),Допущения!$K$31,NA()) -> 0 | J22: =IF(C22=0,0,IF(IF(AND(ISNUMBER(Допущения!$L$31),Допущения!$L$31>=0,Допущения!$L$31<=1),Допущения!$L$31,NA())*Допущения!$B$24<=1,I22*IF(AND(ISNUMBER(Допущения!$L$31),Допущения!$L$31>=0,Допущения!$L$31<=1),Допущения!$L$31,NA())*Допущения!$B$24,NA())) -> 0 | K22: =IF(6<=IF(AND(ISNUMBER(Допущения!$B$17),Допущения!$B$17>=0,Допущения!$B$17=INT(Допущения!$B$17),Допущения!$B$17<=12),Допущения!$B$17,NA()),0,INDEX($J$6:$J$41,(6-IF(AND(ISNUMBER(Допущения!$B$17),Допущения!$B$17>=0,Допущения!$B$17=INT(Допущения!$B$17),Допущения!$B$17<=12),Допущения!$B$17,NA())-1)*3+2)) -> 0 | L22: =G22+K22 -> 9 | M22: =I22*IF(AND(ISNUMBER(Допущения!$M$31),Допущения!$M$31>=0),Допущения!$M$31,NA()) -> 0 | N22: =M22*IF(AND(ISNUMBER(Допущения!$B$7),Допущения!$B$7>=0),Допущения!$B$7,NA()) -> 0
A23: Месяц 6 | B23: =Допущения!$A$32 -> Бизнес | C23: =Допущения!$N$32 -> 1 | D23: =IF(AND(COUNT(Допущения!$C$30:$C$32)=3,MIN(Допущения!$C$30:$C$32)>=0,MAX(Допущения!$C$30:$C$32)<=1,ABS(SUM(Допущения!$C$30:$C$32)-1)<0.00000001),IF(AND(ISNUMBER(Допущения!$B$45),Допущения!$B$45>=0),Допущения!$B$45,NA())*Допущения!$C$32,NA()) -> 30000 | E23: =IF(AND(ISNUMBER(Допущения!$H$32),Допущения!$H$32>0),Допущения!$H$32,NA())*Допущения!$B$23 -> 120 | F23: =D23/E23 -> 250 | G23: =IF(C23=1,0,IF(IF(AND(ISNUMBER(Допущения!$I$32),Допущения!$I$32>=0,Допущения!$I$32<=1),Допущения!$I$32,NA())*Допущения!$B$24<=1,F23*IF(AND(ISNUMBER(Допущения!$I$32),Допущения!$I$32>=0,Допущения!$I$32<=1),Допущения!$I$32,NA())*Допущения!$B$24,NA())) -> 0 | H23: =IF(C23=0,0,F23*IF(AND(ISNUMBER(Допущения!$J$32),Допущения!$J$32>=0,Допущения!$J$32<=1),Допущения!$J$32,NA())) -> 10 | I23: =H23*IF(AND(ISNUMBER(Допущения!$K$32),Допущения!$K$32>=0,Допущения!$K$32<=1),Допущения!$K$32,NA()) -> 8 | J23: =IF(C23=0,0,IF(IF(AND(ISNUMBER(Допущения!$L$32),Допущения!$L$32>=0,Допущения!$L$32<=1),Допущения!$L$32,NA())*Допущения!$B$24<=1,I23*IF(AND(ISNUMBER(Допущения!$L$32),Допущения!$L$32>=0,Допущения!$L$32<=1),Допущения!$L$32,NA())*Допущения!$B$24,NA())) -> 2.4 | K23: =IF(6<=IF(AND(ISNUMBER(Допущения!$B$17),Допущения!$B$17>=0,Допущения!$B$17=INT(Допущения!$B$17),Допущения!$B$17<=12),Допущения!$B$17,NA()),0,INDEX($J$6:$J$41,(6-IF(AND(ISNUMBER(Допущения!$B$17),Допущения!$B$17>=0,Допущения!$B$17=INT(Допущения!$B$17),Допущения!$B$17<=12),Допущения!$B$17,NA())-1)*3+3)) -> 2.4 | L23: =G23+K23 -> 2.4 | M23: =I23*IF(AND(ISNUMBER(Допущения!$M$32),Допущения!$M$32>=0),Допущения!$M$32,NA()) -> 12 | N23: =M23*IF(AND(ISNUMBER(Допущения!$B$7),Допущения!$B$7>=0),Допущения!$B$7,NA()) -> 12000
A24: Месяц 7 | B24: =Допущения!$A$30 -> Старт | C24: =Допущения!$N$30 -> 0 | D24: =IF(AND(COUNT(Допущения!$C$30:$C$32)=3,MIN(Допущения!$C$30:$C$32)>=0,MAX(Допущения!$C$30:$C$32)<=1,ABS(SUM(Допущения!$C$30:$C$32)-1)<0.00000001),IF(AND(ISNUMBER(Допущения!$B$46),Допущения!$B$46>=0),Допущения!$B$46,NA())*Допущения!$C$30,NA()) -> 100000 | E24: =IF(AND(ISNUMBER(Допущения!$H$30),Допущения!$H$30>0),Допущения!$H$30,NA())*Допущения!$B$23 -> 45 | F24: =D24/E24 -> 2222.2222 | G24: =IF(C24=1,0,IF(IF(AND(ISNUMBER(Допущения!$I$30),Допущения!$I$30>=0,Допущения!$I$30<=1),Допущения!$I$30,NA())*Допущения!$B$24<=1,F24*IF(AND(ISNUMBER(Допущения!$I$30),Допущения!$I$30>=0,Допущения!$I$30<=1),Допущения!$I$30,NA())*Допущения!$B$24,NA())) -> 40 | H24: =IF(C24=0,0,F24*IF(AND(ISNUMBER(Допущения!$J$30),Допущения!$J$30>=0,Допущения!$J$30<=1),Допущения!$J$30,NA())) -> 0 | I24: =H24*IF(AND(ISNUMBER(Допущения!$K$30),Допущения!$K$30>=0,Допущения!$K$30<=1),Допущения!$K$30,NA()) -> 0 | J24: =IF(C24=0,0,IF(IF(AND(ISNUMBER(Допущения!$L$30),Допущения!$L$30>=0,Допущения!$L$30<=1),Допущения!$L$30,NA())*Допущения!$B$24<=1,I24*IF(AND(ISNUMBER(Допущения!$L$30),Допущения!$L$30>=0,Допущения!$L$30<=1),Допущения!$L$30,NA())*Допущения!$B$24,NA())) -> 0 | K24: =IF(7<=IF(AND(ISNUMBER(Допущения!$B$17),Допущения!$B$17>=0,Допущения!$B$17=INT(Допущения!$B$17),Допущения!$B$17<=12),Допущения!$B$17,NA()),0,INDEX($J$6:$J$41,(7-IF(AND(ISNUMBER(Допущения!$B$17),Допущения!$B$17>=0,Допущения!$B$17=INT(Допущения!$B$17),Допущения!$B$17<=12),Допущения!$B$17,NA())-1)*3+1)) -> 0 | L24: =G24+K24 -> 40 | M24: =I24*IF(AND(ISNUMBER(Допущения!$M$30),Допущения!$M$30>=0),Допущения!$M$30,NA()) -> 0 | N24: =M24*IF(AND(ISNUMBER(Допущения!$B$7),Допущения!$B$7>=0),Допущения!$B$7,NA()) -> 0
A25: Месяц 7 | B25: =Допущения!$A$31 -> Команда | C25: =Допущения!$N$31 -> 0 | D25: =IF(AND(COUNT(Допущения!$C$30:$C$32)=3,MIN(Допущения!$C$30:$C$32)>=0,MAX(Допущения!$C$30:$C$32)<=1,ABS(SUM(Допущения!$C$30:$C$32)-1)<0.00000001),IF(AND(ISNUMBER(Допущения!$B$46),Допущения!$B$46>=0),Допущения!$B$46,NA())*Допущения!$C$31,NA()) -> 70000 | E25: =IF(AND(ISNUMBER(Допущения!$H$31),Допущения!$H$31>0),Допущения!$H$31,NA())*Допущения!$B$23 -> 70 | F25: =D25/E25 -> 1000 | G25: =IF(C25=1,0,IF(IF(AND(ISNUMBER(Допущения!$I$31),Допущения!$I$31>=0,Допущения!$I$31<=1),Допущения!$I$31,NA())*Допущения!$B$24<=1,F25*IF(AND(ISNUMBER(Допущения!$I$31),Допущения!$I$31>=0,Допущения!$I$31<=1),Допущения!$I$31,NA())*Допущения!$B$24,NA())) -> 9 | H25: =IF(C25=0,0,F25*IF(AND(ISNUMBER(Допущения!$J$31),Допущения!$J$31>=0,Допущения!$J$31<=1),Допущения!$J$31,NA())) -> 0 | I25: =H25*IF(AND(ISNUMBER(Допущения!$K$31),Допущения!$K$31>=0,Допущения!$K$31<=1),Допущения!$K$31,NA()) -> 0 | J25: =IF(C25=0,0,IF(IF(AND(ISNUMBER(Допущения!$L$31),Допущения!$L$31>=0,Допущения!$L$31<=1),Допущения!$L$31,NA())*Допущения!$B$24<=1,I25*IF(AND(ISNUMBER(Допущения!$L$31),Допущения!$L$31>=0,Допущения!$L$31<=1),Допущения!$L$31,NA())*Допущения!$B$24,NA())) -> 0 | K25: =IF(7<=IF(AND(ISNUMBER(Допущения!$B$17),Допущения!$B$17>=0,Допущения!$B$17=INT(Допущения!$B$17),Допущения!$B$17<=12),Допущения!$B$17,NA()),0,INDEX($J$6:$J$41,(7-IF(AND(ISNUMBER(Допущения!$B$17),Допущения!$B$17>=0,Допущения!$B$17=INT(Допущения!$B$17),Допущения!$B$17<=12),Допущения!$B$17,NA())-1)*3+2)) -> 0 | L25: =G25+K25 -> 9 | M25: =I25*IF(AND(ISNUMBER(Допущения!$M$31),Допущения!$M$31>=0),Допущения!$M$31,NA()) -> 0 | N25: =M25*IF(AND(ISNUMBER(Допущения!$B$7),Допущения!$B$7>=0),Допущения!$B$7,NA()) -> 0
A26: Месяц 7 | B26: =Допущения!$A$32 -> Бизнес | C26: =Допущения!$N$32 -> 1 | D26: =IF(AND(COUNT(Допущения!$C$30:$C$32)=3,MIN(Допущения!$C$30:$C$32)>=0,MAX(Допущения!$C$30:$C$32)<=1,ABS(SUM(Допущения!$C$30:$C$32)-1)<0.00000001),IF(AND(ISNUMBER(Допущения!$B$46),Допущения!$B$46>=0),Допущения!$B$46,NA())*Допущения!$C$32,NA()) -> 30000 | E26: =IF(AND(ISNUMBER(Допущения!$H$32),Допущения!$H$32>0),Допущения!$H$32,NA())*Допущения!$B$23 -> 120 | F26: =D26/E26 -> 250 | G26: =IF(C26=1,0,IF(IF(AND(ISNUMBER(Допущения!$I$32),Допущения!$I$32>=0,Допущения!$I$32<=1),Допущения!$I$32,NA())*Допущения!$B$24<=1,F26*IF(AND(ISNUMBER(Допущения!$I$32),Допущения!$I$32>=0,Допущения!$I$32<=1),Допущения!$I$32,NA())*Допущения!$B$24,NA())) -> 0 | H26: =IF(C26=0,0,F26*IF(AND(ISNUMBER(Допущения!$J$32),Допущения!$J$32>=0,Допущения!$J$32<=1),Допущения!$J$32,NA())) -> 10 | I26: =H26*IF(AND(ISNUMBER(Допущения!$K$32),Допущения!$K$32>=0,Допущения!$K$32<=1),Допущения!$K$32,NA()) -> 8 | J26: =IF(C26=0,0,IF(IF(AND(ISNUMBER(Допущения!$L$32),Допущения!$L$32>=0,Допущения!$L$32<=1),Допущения!$L$32,NA())*Допущения!$B$24<=1,I26*IF(AND(ISNUMBER(Допущения!$L$32),Допущения!$L$32>=0,Допущения!$L$32<=1),Допущения!$L$32,NA())*Допущения!$B$24,NA())) -> 2.4 | K26: =IF(7<=IF(AND(ISNUMBER(Допущения!$B$17),Допущения!$B$17>=0,Допущения!$B$17=INT(Допущения!$B$17),Допущения!$B$17<=12),Допущения!$B$17,NA()),0,INDEX($J$6:$J$41,(7-IF(AND(ISNUMBER(Допущения!$B$17),Допущения!$B$17>=0,Допущения!$B$17=INT(Допущения!$B$17),Допущения!$B$17<=12),Допущения!$B$17,NA())-1)*3+3)) -> 2.4 | L26: =G26+K26 -> 2.4 | M26: =I26*IF(AND(ISNUMBER(Допущения!$M$32),Допущения!$M$32>=0),Допущения!$M$32,NA()) -> 12 | N26: =M26*IF(AND(ISNUMBER(Допущения!$B$7),Допущения!$B$7>=0),Допущения!$B$7,NA()) -> 12000
A27: Месяц 8 | B27: =Допущения!$A$30 -> Старт | C27: =Допущения!$N$30 -> 0 | D27: =IF(AND(COUNT(Допущения!$C$30:$C$32)=3,MIN(Допущения!$C$30:$C$32)>=0,MAX(Допущения!$C$30:$C$32)<=1,ABS(SUM(Допущения!$C$30:$C$32)-1)<0.00000001),IF(AND(ISNUMBER(Допущения!$B$47),Допущения!$B$47>=0),Допущения!$B$47,NA())*Допущения!$C$30,NA()) -> 100000 | E27: =IF(AND(ISNUMBER(Допущения!$H$30),Допущения!$H$30>0),Допущения!$H$30,NA())*Допущения!$B$23 -> 45 | F27: =D27/E27 -> 2222.2222 | G27: =IF(C27=1,0,IF(IF(AND(ISNUMBER(Допущения!$I$30),Допущения!$I$30>=0,Допущения!$I$30<=1),Допущения!$I$30,NA())*Допущения!$B$24<=1,F27*IF(AND(ISNUMBER(Допущения!$I$30),Допущения!$I$30>=0,Допущения!$I$30<=1),Допущения!$I$30,NA())*Допущения!$B$24,NA())) -> 40 | H27: =IF(C27=0,0,F27*IF(AND(ISNUMBER(Допущения!$J$30),Допущения!$J$30>=0,Допущения!$J$30<=1),Допущения!$J$30,NA())) -> 0 | I27: =H27*IF(AND(ISNUMBER(Допущения!$K$30),Допущения!$K$30>=0,Допущения!$K$30<=1),Допущения!$K$30,NA()) -> 0 | J27: =IF(C27=0,0,IF(IF(AND(ISNUMBER(Допущения!$L$30),Допущения!$L$30>=0,Допущения!$L$30<=1),Допущения!$L$30,NA())*Допущения!$B$24<=1,I27*IF(AND(ISNUMBER(Допущения!$L$30),Допущения!$L$30>=0,Допущения!$L$30<=1),Допущения!$L$30,NA())*Допущения!$B$24,NA())) -> 0 | K27: =IF(8<=IF(AND(ISNUMBER(Допущения!$B$17),Допущения!$B$17>=0,Допущения!$B$17=INT(Допущения!$B$17),Допущения!$B$17<=12),Допущения!$B$17,NA()),0,INDEX($J$6:$J$41,(8-IF(AND(ISNUMBER(Допущения!$B$17),Допущения!$B$17>=0,Допущения!$B$17=INT(Допущения!$B$17),Допущения!$B$17<=12),Допущения!$B$17,NA())-1)*3+1)) -> 0 | L27: =G27+K27 -> 40 | M27: =I27*IF(AND(ISNUMBER(Допущения!$M$30),Допущения!$M$30>=0),Допущения!$M$30,NA()) -> 0 | N27: =M27*IF(AND(ISNUMBER(Допущения!$B$7),Допущения!$B$7>=0),Допущения!$B$7,NA()) -> 0
A28: Месяц 8 | B28: =Допущения!$A$31 -> Команда | C28: =Допущения!$N$31 -> 0 | D28: =IF(AND(COUNT(Допущения!$C$30:$C$32)=3,MIN(Допущения!$C$30:$C$32)>=0,MAX(Допущения!$C$30:$C$32)<=1,ABS(SUM(Допущения!$C$30:$C$32)-1)<0.00000001),IF(AND(ISNUMBER(Допущения!$B$47),Допущения!$B$47>=0),Допущения!$B$47,NA())*Допущения!$C$31,NA()) -> 70000 | E28: =IF(AND(ISNUMBER(Допущения!$H$31),Допущения!$H$31>0),Допущения!$H$31,NA())*Допущения!$B$23 -> 70 | F28: =D28/E28 -> 1000 | G28: =IF(C28=1,0,IF(IF(AND(ISNUMBER(Допущения!$I$31),Допущения!$I$31>=0,Допущения!$I$31<=1),Допущения!$I$31,NA())*Допущения!$B$24<=1,F28*IF(AND(ISNUMBER(Допущения!$I$31),Допущения!$I$31>=0,Допущения!$I$31<=1),Допущения!$I$31,NA())*Допущения!$B$24,NA())) -> 9 | H28: =IF(C28=0,0,F28*IF(AND(ISNUMBER(Допущения!$J$31),Допущения!$J$31>=0,Допущения!$J$31<=1),Допущения!$J$31,NA())) -> 0 | I28: =H28*IF(AND(ISNUMBER(Допущения!$K$31),Допущения!$K$31>=0,Допущения!$K$31<=1),Допущения!$K$31,NA()) -> 0 | J28: =IF(C28=0,0,IF(IF(AND(ISNUMBER(Допущения!$L$31),Допущения!$L$31>=0,Допущения!$L$31<=1),Допущения!$L$31,NA())*Допущения!$B$24<=1,I28*IF(AND(ISNUMBER(Допущения!$L$31),Допущения!$L$31>=0,Допущения!$L$31<=1),Допущения!$L$31,NA())*Допущения!$B$24,NA())) -> 0 | K28: =IF(8<=IF(AND(ISNUMBER(Допущения!$B$17),Допущения!$B$17>=0,Допущения!$B$17=INT(Допущения!$B$17),Допущения!$B$17<=12),Допущения!$B$17,NA()),0,INDEX($J$6:$J$41,(8-IF(AND(ISNUMBER(Допущения!$B$17),Допущения!$B$17>=0,Допущения!$B$17=INT(Допущения!$B$17),Допущения!$B$17<=12),Допущения!$B$17,NA())-1)*3+2)) -> 0 | L28: =G28+K28 -> 9 | M28: =I28*IF(AND(ISNUMBER(Допущения!$M$31),Допущения!$M$31>=0),Допущения!$M$31,NA()) -> 0 | N28: =M28*IF(AND(ISNUMBER(Допущения!$B$7),Допущения!$B$7>=0),Допущения!$B$7,NA()) -> 0
A29: Месяц 8 | B29: =Допущения!$A$32 -> Бизнес | C29: =Допущения!$N$32 -> 1 | D29: =IF(AND(COUNT(Допущения!$C$30:$C$32)=3,MIN(Допущения!$C$30:$C$32)>=0,MAX(Допущения!$C$30:$C$32)<=1,ABS(SUM(Допущения!$C$30:$C$32)-1)<0.00000001),IF(AND(ISNUMBER(Допущения!$B$47),Допущения!$B$47>=0),Допущения!$B$47,NA())*Допущения!$C$32,NA()) -> 30000 | E29: =IF(AND(ISNUMBER(Допущения!$H$32),Допущения!$H$32>0),Допущения!$H$32,NA())*Допущения!$B$23 -> 120 | F29: =D29/E29 -> 250 | G29: =IF(C29=1,0,IF(IF(AND(ISNUMBER(Допущения!$I$32),Допущения!$I$32>=0,Допущения!$I$32<=1),Допущения!$I$32,NA())*Допущения!$B$24<=1,F29*IF(AND(ISNUMBER(Допущения!$I$32),Допущения!$I$32>=0,Допущения!$I$32<=1),Допущения!$I$32,NA())*Допущения!$B$24,NA())) -> 0 | H29: =IF(C29=0,0,F29*IF(AND(ISNUMBER(Допущения!$J$32),Допущения!$J$32>=0,Допущения!$J$32<=1),Допущения!$J$32,NA())) -> 10 | I29: =H29*IF(AND(ISNUMBER(Допущения!$K$32),Допущения!$K$32>=0,Допущения!$K$32<=1),Допущения!$K$32,NA()) -> 8 | J29: =IF(C29=0,0,IF(IF(AND(ISNUMBER(Допущения!$L$32),Допущения!$L$32>=0,Допущения!$L$32<=1),Допущения!$L$32,NA())*Допущения!$B$24<=1,I29*IF(AND(ISNUMBER(Допущения!$L$32),Допущения!$L$32>=0,Допущения!$L$32<=1),Допущения!$L$32,NA())*Допущения!$B$24,NA())) -> 2.4 | K29: =IF(8<=IF(AND(ISNUMBER(Допущения!$B$17),Допущения!$B$17>=0,Допущения!$B$17=INT(Допущения!$B$17),Допущения!$B$17<=12),Допущения!$B$17,NA()),0,INDEX($J$6:$J$41,(8-IF(AND(ISNUMBER(Допущения!$B$17),Допущения!$B$17>=0,Допущения!$B$17=INT(Допущения!$B$17),Допущения!$B$17<=12),Допущения!$B$17,NA())-1)*3+3)) -> 2.4 | L29: =G29+K29 -> 2.4 | M29: =I29*IF(AND(ISNUMBER(Допущения!$M$32),Допущения!$M$32>=0),Допущения!$M$32,NA()) -> 12 | N29: =M29*IF(AND(ISNUMBER(Допущения!$B$7),Допущения!$B$7>=0),Допущения!$B$7,NA()) -> 12000
A30: Месяц 9 | B30: =Допущения!$A$30 -> Старт | C30: =Допущения!$N$30 -> 0 | D30: =IF(AND(COUNT(Допущения!$C$30:$C$32)=3,MIN(Допущения!$C$30:$C$32)>=0,MAX(Допущения!$C$30:$C$32)<=1,ABS(SUM(Допущения!$C$30:$C$32)-1)<0.00000001),IF(AND(ISNUMBER(Допущения!$B$48),Допущения!$B$48>=0),Допущения!$B$48,NA())*Допущения!$C$30,NA()) -> 100000 | E30: =IF(AND(ISNUMBER(Допущения!$H$30),Допущения!$H$30>0),Допущения!$H$30,NA())*Допущения!$B$23 -> 45 | F30: =D30/E30 -> 2222.2222 | G30: =IF(C30=1,0,IF(IF(AND(ISNUMBER(Допущения!$I$30),Допущения!$I$30>=0,Допущения!$I$30<=1),Допущения!$I$30,NA())*Допущения!$B$24<=1,F30*IF(AND(ISNUMBER(Допущения!$I$30),Допущения!$I$30>=0,Допущения!$I$30<=1),Допущения!$I$30,NA())*Допущения!$B$24,NA())) -> 40 | H30: =IF(C30=0,0,F30*IF(AND(ISNUMBER(Допущения!$J$30),Допущения!$J$30>=0,Допущения!$J$30<=1),Допущения!$J$30,NA())) -> 0 | I30: =H30*IF(AND(ISNUMBER(Допущения!$K$30),Допущения!$K$30>=0,Допущения!$K$30<=1),Допущения!$K$30,NA()) -> 0 | J30: =IF(C30=0,0,IF(IF(AND(ISNUMBER(Допущения!$L$30),Допущения!$L$30>=0,Допущения!$L$30<=1),Допущения!$L$30,NA())*Допущения!$B$24<=1,I30*IF(AND(ISNUMBER(Допущения!$L$30),Допущения!$L$30>=0,Допущения!$L$30<=1),Допущения!$L$30,NA())*Допущения!$B$24,NA())) -> 0 | K30: =IF(9<=IF(AND(ISNUMBER(Допущения!$B$17),Допущения!$B$17>=0,Допущения!$B$17=INT(Допущения!$B$17),Допущения!$B$17<=12),Допущения!$B$17,NA()),0,INDEX($J$6:$J$41,(9-IF(AND(ISNUMBER(Допущения!$B$17),Допущения!$B$17>=0,Допущения!$B$17=INT(Допущения!$B$17),Допущения!$B$17<=12),Допущения!$B$17,NA())-1)*3+1)) -> 0 | L30: =G30+K30 -> 40 | M30: =I30*IF(AND(ISNUMBER(Допущения!$M$30),Допущения!$M$30>=0),Допущения!$M$30,NA()) -> 0 | N30: =M30*IF(AND(ISNUMBER(Допущения!$B$7),Допущения!$B$7>=0),Допущения!$B$7,NA()) -> 0
A31: Месяц 9 | B31: =Допущения!$A$31 -> Команда | C31: =Допущения!$N$31 -> 0 | D31: =IF(AND(COUNT(Допущения!$C$30:$C$32)=3,MIN(Допущения!$C$30:$C$32)>=0,MAX(Допущения!$C$30:$C$32)<=1,ABS(SUM(Допущения!$C$30:$C$32)-1)<0.00000001),IF(AND(ISNUMBER(Допущения!$B$48),Допущения!$B$48>=0),Допущения!$B$48,NA())*Допущения!$C$31,NA()) -> 70000 | E31: =IF(AND(ISNUMBER(Допущения!$H$31),Допущения!$H$31>0),Допущения!$H$31,NA())*Допущения!$B$23 -> 70 | F31: =D31/E31 -> 1000 | G31: =IF(C31=1,0,IF(IF(AND(ISNUMBER(Допущения!$I$31),Допущения!$I$31>=0,Допущения!$I$31<=1),Допущения!$I$31,NA())*Допущения!$B$24<=1,F31*IF(AND(ISNUMBER(Допущения!$I$31),Допущения!$I$31>=0,Допущения!$I$31<=1),Допущения!$I$31,NA())*Допущения!$B$24,NA())) -> 9 | H31: =IF(C31=0,0,F31*IF(AND(ISNUMBER(Допущения!$J$31),Допущения!$J$31>=0,Допущения!$J$31<=1),Допущения!$J$31,NA())) -> 0 | I31: =H31*IF(AND(ISNUMBER(Допущения!$K$31),Допущения!$K$31>=0,Допущения!$K$31<=1),Допущения!$K$31,NA()) -> 0 | J31: =IF(C31=0,0,IF(IF(AND(ISNUMBER(Допущения!$L$31),Допущения!$L$31>=0,Допущения!$L$31<=1),Допущения!$L$31,NA())*Допущения!$B$24<=1,I31*IF(AND(ISNUMBER(Допущения!$L$31),Допущения!$L$31>=0,Допущения!$L$31<=1),Допущения!$L$31,NA())*Допущения!$B$24,NA())) -> 0 | K31: =IF(9<=IF(AND(ISNUMBER(Допущения!$B$17),Допущения!$B$17>=0,Допущения!$B$17=INT(Допущения!$B$17),Допущения!$B$17<=12),Допущения!$B$17,NA()),0,INDEX($J$6:$J$41,(9-IF(AND(ISNUMBER(Допущения!$B$17),Допущения!$B$17>=0,Допущения!$B$17=INT(Допущения!$B$17),Допущения!$B$17<=12),Допущения!$B$17,NA())-1)*3+2)) -> 0 | L31: =G31+K31 -> 9 | M31: =I31*IF(AND(ISNUMBER(Допущения!$M$31),Допущения!$M$31>=0),Допущения!$M$31,NA()) -> 0 | N31: =M31*IF(AND(ISNUMBER(Допущения!$B$7),Допущения!$B$7>=0),Допущения!$B$7,NA()) -> 0
A32: Месяц 9 | B32: =Допущения!$A$32 -> Бизнес | C32: =Допущения!$N$32 -> 1 | D32: =IF(AND(COUNT(Допущения!$C$30:$C$32)=3,MIN(Допущения!$C$30:$C$32)>=0,MAX(Допущения!$C$30:$C$32)<=1,ABS(SUM(Допущения!$C$30:$C$32)-1)<0.00000001),IF(AND(ISNUMBER(Допущения!$B$48),Допущения!$B$48>=0),Допущения!$B$48,NA())*Допущения!$C$32,NA()) -> 30000 | E32: =IF(AND(ISNUMBER(Допущения!$H$32),Допущения!$H$32>0),Допущения!$H$32,NA())*Допущения!$B$23 -> 120 | F32: =D32/E32 -> 250 | G32: =IF(C32=1,0,IF(IF(AND(ISNUMBER(Допущения!$I$32),Допущения!$I$32>=0,Допущения!$I$32<=1),Допущения!$I$32,NA())*Допущения!$B$24<=1,F32*IF(AND(ISNUMBER(Допущения!$I$32),Допущения!$I$32>=0,Допущения!$I$32<=1),Допущения!$I$32,NA())*Допущения!$B$24,NA())) -> 0 | H32: =IF(C32=0,0,F32*IF(AND(ISNUMBER(Допущения!$J$32),Допущения!$J$32>=0,Допущения!$J$32<=1),Допущения!$J$32,NA())) -> 10 | I32: =H32*IF(AND(ISNUMBER(Допущения!$K$32),Допущения!$K$32>=0,Допущения!$K$32<=1),Допущения!$K$32,NA()) -> 8 | J32: =IF(C32=0,0,IF(IF(AND(ISNUMBER(Допущения!$L$32),Допущения!$L$32>=0,Допущения!$L$32<=1),Допущения!$L$32,NA())*Допущения!$B$24<=1,I32*IF(AND(ISNUMBER(Допущения!$L$32),Допущения!$L$32>=0,Допущения!$L$32<=1),Допущения!$L$32,NA())*Допущения!$B$24,NA())) -> 2.4 | K32: =IF(9<=IF(AND(ISNUMBER(Допущения!$B$17),Допущения!$B$17>=0,Допущения!$B$17=INT(Допущения!$B$17),Допущения!$B$17<=12),Допущения!$B$17,NA()),0,INDEX($J$6:$J$41,(9-IF(AND(ISNUMBER(Допущения!$B$17),Допущения!$B$17>=0,Допущения!$B$17=INT(Допущения!$B$17),Допущения!$B$17<=12),Допущения!$B$17,NA())-1)*3+3)) -> 2.4 | L32: =G32+K32 -> 2.4 | M32: =I32*IF(AND(ISNUMBER(Допущения!$M$32),Допущения!$M$32>=0),Допущения!$M$32,NA()) -> 12 | N32: =M32*IF(AND(ISNUMBER(Допущения!$B$7),Допущения!$B$7>=0),Допущения!$B$7,NA()) -> 12000
A33: Месяц 10 | B33: =Допущения!$A$30 -> Старт | C33: =Допущения!$N$30 -> 0 | D33: =IF(AND(COUNT(Допущения!$C$30:$C$32)=3,MIN(Допущения!$C$30:$C$32)>=0,MAX(Допущения!$C$30:$C$32)<=1,ABS(SUM(Допущения!$C$30:$C$32)-1)<0.00000001),IF(AND(ISNUMBER(Допущения!$B$49),Допущения!$B$49>=0),Допущения!$B$49,NA())*Допущения!$C$30,NA()) -> 100000 | E33: =IF(AND(ISNUMBER(Допущения!$H$30),Допущения!$H$30>0),Допущения!$H$30,NA())*Допущения!$B$23 -> 45 | F33: =D33/E33 -> 2222.2222 | G33: =IF(C33=1,0,IF(IF(AND(ISNUMBER(Допущения!$I$30),Допущения!$I$30>=0,Допущения!$I$30<=1),Допущения!$I$30,NA())*Допущения!$B$24<=1,F33*IF(AND(ISNUMBER(Допущения!$I$30),Допущения!$I$30>=0,Допущения!$I$30<=1),Допущения!$I$30,NA())*Допущения!$B$24,NA())) -> 40 | H33: =IF(C33=0,0,F33*IF(AND(ISNUMBER(Допущения!$J$30),Допущения!$J$30>=0,Допущения!$J$30<=1),Допущения!$J$30,NA())) -> 0 | I33: =H33*IF(AND(ISNUMBER(Допущения!$K$30),Допущения!$K$30>=0,Допущения!$K$30<=1),Допущения!$K$30,NA()) -> 0 | J33: =IF(C33=0,0,IF(IF(AND(ISNUMBER(Допущения!$L$30),Допущения!$L$30>=0,Допущения!$L$30<=1),Допущения!$L$30,NA())*Допущения!$B$24<=1,I33*IF(AND(ISNUMBER(Допущения!$L$30),Допущения!$L$30>=0,Допущения!$L$30<=1),Допущения!$L$30,NA())*Допущения!$B$24,NA())) -> 0 | K33: =IF(10<=IF(AND(ISNUMBER(Допущения!$B$17),Допущения!$B$17>=0,Допущения!$B$17=INT(Допущения!$B$17),Допущения!$B$17<=12),Допущения!$B$17,NA()),0,INDEX($J$6:$J$41,(10-IF(AND(ISNUMBER(Допущения!$B$17),Допущения!$B$17>=0,Допущения!$B$17=INT(Допущения!$B$17),Допущения!$B$17<=12),Допущения!$B$17,NA())-1)*3+1)) -> 0 | L33: =G33+K33 -> 40 | M33: =I33*IF(AND(ISNUMBER(Допущения!$M$30),Допущения!$M$30>=0),Допущения!$M$30,NA()) -> 0 | N33: =M33*IF(AND(ISNUMBER(Допущения!$B$7),Допущения!$B$7>=0),Допущения!$B$7,NA()) -> 0
A34: Месяц 10 | B34: =Допущения!$A$31 -> Команда | C34: =Допущения!$N$31 -> 0 | D34: =IF(AND(COUNT(Допущения!$C$30:$C$32)=3,MIN(Допущения!$C$30:$C$32)>=0,MAX(Допущения!$C$30:$C$32)<=1,ABS(SUM(Допущения!$C$30:$C$32)-1)<0.00000001),IF(AND(ISNUMBER(Допущения!$B$49),Допущения!$B$49>=0),Допущения!$B$49,NA())*Допущения!$C$31,NA()) -> 70000 | E34: =IF(AND(ISNUMBER(Допущения!$H$31),Допущения!$H$31>0),Допущения!$H$31,NA())*Допущения!$B$23 -> 70 | F34: =D34/E34 -> 1000 | G34: =IF(C34=1,0,IF(IF(AND(ISNUMBER(Допущения!$I$31),Допущения!$I$31>=0,Допущения!$I$31<=1),Допущения!$I$31,NA())*Допущения!$B$24<=1,F34*IF(AND(ISNUMBER(Допущения!$I$31),Допущения!$I$31>=0,Допущения!$I$31<=1),Допущения!$I$31,NA())*Допущения!$B$24,NA())) -> 9 | H34: =IF(C34=0,0,F34*IF(AND(ISNUMBER(Допущения!$J$31),Допущения!$J$31>=0,Допущения!$J$31<=1),Допущения!$J$31,NA())) -> 0 | I34: =H34*IF(AND(ISNUMBER(Допущения!$K$31),Допущения!$K$31>=0,Допущения!$K$31<=1),Допущения!$K$31,NA()) -> 0 | J34: =IF(C34=0,0,IF(IF(AND(ISNUMBER(Допущения!$L$31),Допущения!$L$31>=0,Допущения!$L$31<=1),Допущения!$L$31,NA())*Допущения!$B$24<=1,I34*IF(AND(ISNUMBER(Допущения!$L$31),Допущения!$L$31>=0,Допущения!$L$31<=1),Допущения!$L$31,NA())*Допущения!$B$24,NA())) -> 0 | K34: =IF(10<=IF(AND(ISNUMBER(Допущения!$B$17),Допущения!$B$17>=0,Допущения!$B$17=INT(Допущения!$B$17),Допущения!$B$17<=12),Допущения!$B$17,NA()),0,INDEX($J$6:$J$41,(10-IF(AND(ISNUMBER(Допущения!$B$17),Допущения!$B$17>=0,Допущения!$B$17=INT(Допущения!$B$17),Допущения!$B$17<=12),Допущения!$B$17,NA())-1)*3+2)) -> 0 | L34: =G34+K34 -> 9 | M34: =I34*IF(AND(ISNUMBER(Допущения!$M$31),Допущения!$M$31>=0),Допущения!$M$31,NA()) -> 0 | N34: =M34*IF(AND(ISNUMBER(Допущения!$B$7),Допущения!$B$7>=0),Допущения!$B$7,NA()) -> 0
A35: Месяц 10 | B35: =Допущения!$A$32 -> Бизнес | C35: =Допущения!$N$32 -> 1 | D35: =IF(AND(COUNT(Допущения!$C$30:$C$32)=3,MIN(Допущения!$C$30:$C$32)>=0,MAX(Допущения!$C$30:$C$32)<=1,ABS(SUM(Допущения!$C$30:$C$32)-1)<0.00000001),IF(AND(ISNUMBER(Допущения!$B$49),Допущения!$B$49>=0),Допущения!$B$49,NA())*Допущения!$C$32,NA()) -> 30000 | E35: =IF(AND(ISNUMBER(Допущения!$H$32),Допущения!$H$32>0),Допущения!$H$32,NA())*Допущения!$B$23 -> 120 | F35: =D35/E35 -> 250 | G35: =IF(C35=1,0,IF(IF(AND(ISNUMBER(Допущения!$I$32),Допущения!$I$32>=0,Допущения!$I$32<=1),Допущения!$I$32,NA())*Допущения!$B$24<=1,F35*IF(AND(ISNUMBER(Допущения!$I$32),Допущения!$I$32>=0,Допущения!$I$32<=1),Допущения!$I$32,NA())*Допущения!$B$24,NA())) -> 0 | H35: =IF(C35=0,0,F35*IF(AND(ISNUMBER(Допущения!$J$32),Допущения!$J$32>=0,Допущения!$J$32<=1),Допущения!$J$32,NA())) -> 10 | I35: =H35*IF(AND(ISNUMBER(Допущения!$K$32),Допущения!$K$32>=0,Допущения!$K$32<=1),Допущения!$K$32,NA()) -> 8 | J35: =IF(C35=0,0,IF(IF(AND(ISNUMBER(Допущения!$L$32),Допущения!$L$32>=0,Допущения!$L$32<=1),Допущения!$L$32,NA())*Допущения!$B$24<=1,I35*IF(AND(ISNUMBER(Допущения!$L$32),Допущения!$L$32>=0,Допущения!$L$32<=1),Допущения!$L$32,NA())*Допущения!$B$24,NA())) -> 2.4 | K35: =IF(10<=IF(AND(ISNUMBER(Допущения!$B$17),Допущения!$B$17>=0,Допущения!$B$17=INT(Допущения!$B$17),Допущения!$B$17<=12),Допущения!$B$17,NA()),0,INDEX($J$6:$J$41,(10-IF(AND(ISNUMBER(Допущения!$B$17),Допущения!$B$17>=0,Допущения!$B$17=INT(Допущения!$B$17),Допущения!$B$17<=12),Допущения!$B$17,NA())-1)*3+3)) -> 2.4 | L35: =G35+K35 -> 2.4 | M35: =I35*IF(AND(ISNUMBER(Допущения!$M$32),Допущения!$M$32>=0),Допущения!$M$32,NA()) -> 12 | N35: =M35*IF(AND(ISNUMBER(Допущения!$B$7),Допущения!$B$7>=0),Допущения!$B$7,NA()) -> 12000
A36: Месяц 11 | B36: =Допущения!$A$30 -> Старт | C36: =Допущения!$N$30 -> 0 | D36: =IF(AND(COUNT(Допущения!$C$30:$C$32)=3,MIN(Допущения!$C$30:$C$32)>=0,MAX(Допущения!$C$30:$C$32)<=1,ABS(SUM(Допущения!$C$30:$C$32)-1)<0.00000001),IF(AND(ISNUMBER(Допущения!$B$50),Допущения!$B$50>=0),Допущения!$B$50,NA())*Допущения!$C$30,NA()) -> 100000 | E36: =IF(AND(ISNUMBER(Допущения!$H$30),Допущения!$H$30>0),Допущения!$H$30,NA())*Допущения!$B$23 -> 45 | F36: =D36/E36 -> 2222.2222 | G36: =IF(C36=1,0,IF(IF(AND(ISNUMBER(Допущения!$I$30),Допущения!$I$30>=0,Допущения!$I$30<=1),Допущения!$I$30,NA())*Допущения!$B$24<=1,F36*IF(AND(ISNUMBER(Допущения!$I$30),Допущения!$I$30>=0,Допущения!$I$30<=1),Допущения!$I$30,NA())*Допущения!$B$24,NA())) -> 40 | H36: =IF(C36=0,0,F36*IF(AND(ISNUMBER(Допущения!$J$30),Допущения!$J$30>=0,Допущения!$J$30<=1),Допущения!$J$30,NA())) -> 0 | I36: =H36*IF(AND(ISNUMBER(Допущения!$K$30),Допущения!$K$30>=0,Допущения!$K$30<=1),Допущения!$K$30,NA()) -> 0 | J36: =IF(C36=0,0,IF(IF(AND(ISNUMBER(Допущения!$L$30),Допущения!$L$30>=0,Допущения!$L$30<=1),Допущения!$L$30,NA())*Допущения!$B$24<=1,I36*IF(AND(ISNUMBER(Допущения!$L$30),Допущения!$L$30>=0,Допущения!$L$30<=1),Допущения!$L$30,NA())*Допущения!$B$24,NA())) -> 0 | K36: =IF(11<=IF(AND(ISNUMBER(Допущения!$B$17),Допущения!$B$17>=0,Допущения!$B$17=INT(Допущения!$B$17),Допущения!$B$17<=12),Допущения!$B$17,NA()),0,INDEX($J$6:$J$41,(11-IF(AND(ISNUMBER(Допущения!$B$17),Допущения!$B$17>=0,Допущения!$B$17=INT(Допущения!$B$17),Допущения!$B$17<=12),Допущения!$B$17,NA())-1)*3+1)) -> 0 | L36: =G36+K36 -> 40 | M36: =I36*IF(AND(ISNUMBER(Допущения!$M$30),Допущения!$M$30>=0),Допущения!$M$30,NA()) -> 0 | N36: =M36*IF(AND(ISNUMBER(Допущения!$B$7),Допущения!$B$7>=0),Допущения!$B$7,NA()) -> 0
A37: Месяц 11 | B37: =Допущения!$A$31 -> Команда | C37: =Допущения!$N$31 -> 0 | D37: =IF(AND(COUNT(Допущения!$C$30:$C$32)=3,MIN(Допущения!$C$30:$C$32)>=0,MAX(Допущения!$C$30:$C$32)<=1,ABS(SUM(Допущения!$C$30:$C$32)-1)<0.00000001),IF(AND(ISNUMBER(Допущения!$B$50),Допущения!$B$50>=0),Допущения!$B$50,NA())*Допущения!$C$31,NA()) -> 70000 | E37: =IF(AND(ISNUMBER(Допущения!$H$31),Допущения!$H$31>0),Допущения!$H$31,NA())*Допущения!$B$23 -> 70 | F37: =D37/E37 -> 1000 | G37: =IF(C37=1,0,IF(IF(AND(ISNUMBER(Допущения!$I$31),Допущения!$I$31>=0,Допущения!$I$31<=1),Допущения!$I$31,NA())*Допущения!$B$24<=1,F37*IF(AND(ISNUMBER(Допущения!$I$31),Допущения!$I$31>=0,Допущения!$I$31<=1),Допущения!$I$31,NA())*Допущения!$B$24,NA())) -> 9 | H37: =IF(C37=0,0,F37*IF(AND(ISNUMBER(Допущения!$J$31),Допущения!$J$31>=0,Допущения!$J$31<=1),Допущения!$J$31,NA())) -> 0 | I37: =H37*IF(AND(ISNUMBER(Допущения!$K$31),Допущения!$K$31>=0,Допущения!$K$31<=1),Допущения!$K$31,NA()) -> 0 | J37: =IF(C37=0,0,IF(IF(AND(ISNUMBER(Допущения!$L$31),Допущения!$L$31>=0,Допущения!$L$31<=1),Допущения!$L$31,NA())*Допущения!$B$24<=1,I37*IF(AND(ISNUMBER(Допущения!$L$31),Допущения!$L$31>=0,Допущения!$L$31<=1),Допущения!$L$31,NA())*Допущения!$B$24,NA())) -> 0 | K37: =IF(11<=IF(AND(ISNUMBER(Допущения!$B$17),Допущения!$B$17>=0,Допущения!$B$17=INT(Допущения!$B$17),Допущения!$B$17<=12),Допущения!$B$17,NA()),0,INDEX($J$6:$J$41,(11-IF(AND(ISNUMBER(Допущения!$B$17),Допущения!$B$17>=0,Допущения!$B$17=INT(Допущения!$B$17),Допущения!$B$17<=12),Допущения!$B$17,NA())-1)*3+2)) -> 0 | L37: =G37+K37 -> 9 | M37: =I37*IF(AND(ISNUMBER(Допущения!$M$31),Допущения!$M$31>=0),Допущения!$M$31,NA()) -> 0 | N37: =M37*IF(AND(ISNUMBER(Допущения!$B$7),Допущения!$B$7>=0),Допущения!$B$7,NA()) -> 0
A38: Месяц 11 | B38: =Допущения!$A$32 -> Бизнес | C38: =Допущения!$N$32 -> 1 | D38: =IF(AND(COUNT(Допущения!$C$30:$C$32)=3,MIN(Допущения!$C$30:$C$32)>=0,MAX(Допущения!$C$30:$C$32)<=1,ABS(SUM(Допущения!$C$30:$C$32)-1)<0.00000001),IF(AND(ISNUMBER(Допущения!$B$50),Допущения!$B$50>=0),Допущения!$B$50,NA())*Допущения!$C$32,NA()) -> 30000 | E38: =IF(AND(ISNUMBER(Допущения!$H$32),Допущения!$H$32>0),Допущения!$H$32,NA())*Допущения!$B$23 -> 120 | F38: =D38/E38 -> 250 | G38: =IF(C38=1,0,IF(IF(AND(ISNUMBER(Допущения!$I$32),Допущения!$I$32>=0,Допущения!$I$32<=1),Допущения!$I$32,NA())*Допущения!$B$24<=1,F38*IF(AND(ISNUMBER(Допущения!$I$32),Допущения!$I$32>=0,Допущения!$I$32<=1),Допущения!$I$32,NA())*Допущения!$B$24,NA())) -> 0 | H38: =IF(C38=0,0,F38*IF(AND(ISNUMBER(Допущения!$J$32),Допущения!$J$32>=0,Допущения!$J$32<=1),Допущения!$J$32,NA())) -> 10 | I38: =H38*IF(AND(ISNUMBER(Допущения!$K$32),Допущения!$K$32>=0,Допущения!$K$32<=1),Допущения!$K$32,NA()) -> 8 | J38: =IF(C38=0,0,IF(IF(AND(ISNUMBER(Допущения!$L$32),Допущения!$L$32>=0,Допущения!$L$32<=1),Допущения!$L$32,NA())*Допущения!$B$24<=1,I38*IF(AND(ISNUMBER(Допущения!$L$32),Допущения!$L$32>=0,Допущения!$L$32<=1),Допущения!$L$32,NA())*Допущения!$B$24,NA())) -> 2.4 | K38: =IF(11<=IF(AND(ISNUMBER(Допущения!$B$17),Допущения!$B$17>=0,Допущения!$B$17=INT(Допущения!$B$17),Допущения!$B$17<=12),Допущения!$B$17,NA()),0,INDEX($J$6:$J$41,(11-IF(AND(ISNUMBER(Допущения!$B$17),Допущения!$B$17>=0,Допущения!$B$17=INT(Допущения!$B$17),Допущения!$B$17<=12),Допущения!$B$17,NA())-1)*3+3)) -> 2.4 | L38: =G38+K38 -> 2.4 | M38: =I38*IF(AND(ISNUMBER(Допущения!$M$32),Допущения!$M$32>=0),Допущения!$M$32,NA()) -> 12 | N38: =M38*IF(AND(ISNUMBER(Допущения!$B$7),Допущения!$B$7>=0),Допущения!$B$7,NA()) -> 12000
A39: Месяц 12 | B39: =Допущения!$A$30 -> Старт | C39: =Допущения!$N$30 -> 0 | D39: =IF(AND(COUNT(Допущения!$C$30:$C$32)=3,MIN(Допущения!$C$30:$C$32)>=0,MAX(Допущения!$C$30:$C$32)<=1,ABS(SUM(Допущения!$C$30:$C$32)-1)<0.00000001),IF(AND(ISNUMBER(Допущения!$B$51),Допущения!$B$51>=0),Допущения!$B$51,NA())*Допущения!$C$30,NA()) -> 100000 | E39: =IF(AND(ISNUMBER(Допущения!$H$30),Допущения!$H$30>0),Допущения!$H$30,NA())*Допущения!$B$23 -> 45 | F39: =D39/E39 -> 2222.2222 | G39: =IF(C39=1,0,IF(IF(AND(ISNUMBER(Допущения!$I$30),Допущения!$I$30>=0,Допущения!$I$30<=1),Допущения!$I$30,NA())*Допущения!$B$24<=1,F39*IF(AND(ISNUMBER(Допущения!$I$30),Допущения!$I$30>=0,Допущения!$I$30<=1),Допущения!$I$30,NA())*Допущения!$B$24,NA())) -> 40 | H39: =IF(C39=0,0,F39*IF(AND(ISNUMBER(Допущения!$J$30),Допущения!$J$30>=0,Допущения!$J$30<=1),Допущения!$J$30,NA())) -> 0 | I39: =H39*IF(AND(ISNUMBER(Допущения!$K$30),Допущения!$K$30>=0,Допущения!$K$30<=1),Допущения!$K$30,NA()) -> 0 | J39: =IF(C39=0,0,IF(IF(AND(ISNUMBER(Допущения!$L$30),Допущения!$L$30>=0,Допущения!$L$30<=1),Допущения!$L$30,NA())*Допущения!$B$24<=1,I39*IF(AND(ISNUMBER(Допущения!$L$30),Допущения!$L$30>=0,Допущения!$L$30<=1),Допущения!$L$30,NA())*Допущения!$B$24,NA())) -> 0 | K39: =IF(12<=IF(AND(ISNUMBER(Допущения!$B$17),Допущения!$B$17>=0,Допущения!$B$17=INT(Допущения!$B$17),Допущения!$B$17<=12),Допущения!$B$17,NA()),0,INDEX($J$6:$J$41,(12-IF(AND(ISNUMBER(Допущения!$B$17),Допущения!$B$17>=0,Допущения!$B$17=INT(Допущения!$B$17),Допущения!$B$17<=12),Допущения!$B$17,NA())-1)*3+1)) -> 0 | L39: =G39+K39 -> 40 | M39: =I39*IF(AND(ISNUMBER(Допущения!$M$30),Допущения!$M$30>=0),Допущения!$M$30,NA()) -> 0 | N39: =M39*IF(AND(ISNUMBER(Допущения!$B$7),Допущения!$B$7>=0),Допущения!$B$7,NA()) -> 0
A40: Месяц 12 | B40: =Допущения!$A$31 -> Команда | C40: =Допущения!$N$31 -> 0 | D40: =IF(AND(COUNT(Допущения!$C$30:$C$32)=3,MIN(Допущения!$C$30:$C$32)>=0,MAX(Допущения!$C$30:$C$32)<=1,ABS(SUM(Допущения!$C$30:$C$32)-1)<0.00000001),IF(AND(ISNUMBER(Допущения!$B$51),Допущения!$B$51>=0),Допущения!$B$51,NA())*Допущения!$C$31,NA()) -> 70000 | E40: =IF(AND(ISNUMBER(Допущения!$H$31),Допущения!$H$31>0),Допущения!$H$31,NA())*Допущения!$B$23 -> 70 | F40: =D40/E40 -> 1000 | G40: =IF(C40=1,0,IF(IF(AND(ISNUMBER(Допущения!$I$31),Допущения!$I$31>=0,Допущения!$I$31<=1),Допущения!$I$31,NA())*Допущения!$B$24<=1,F40*IF(AND(ISNUMBER(Допущения!$I$31),Допущения!$I$31>=0,Допущения!$I$31<=1),Допущения!$I$31,NA())*Допущения!$B$24,NA())) -> 9 | H40: =IF(C40=0,0,F40*IF(AND(ISNUMBER(Допущения!$J$31),Допущения!$J$31>=0,Допущения!$J$31<=1),Допущения!$J$31,NA())) -> 0 | I40: =H40*IF(AND(ISNUMBER(Допущения!$K$31),Допущения!$K$31>=0,Допущения!$K$31<=1),Допущения!$K$31,NA()) -> 0 | J40: =IF(C40=0,0,IF(IF(AND(ISNUMBER(Допущения!$L$31),Допущения!$L$31>=0,Допущения!$L$31<=1),Допущения!$L$31,NA())*Допущения!$B$24<=1,I40*IF(AND(ISNUMBER(Допущения!$L$31),Допущения!$L$31>=0,Допущения!$L$31<=1),Допущения!$L$31,NA())*Допущения!$B$24,NA())) -> 0 | K40: =IF(12<=IF(AND(ISNUMBER(Допущения!$B$17),Допущения!$B$17>=0,Допущения!$B$17=INT(Допущения!$B$17),Допущения!$B$17<=12),Допущения!$B$17,NA()),0,INDEX($J$6:$J$41,(12-IF(AND(ISNUMBER(Допущения!$B$17),Допущения!$B$17>=0,Допущения!$B$17=INT(Допущения!$B$17),Допущения!$B$17<=12),Допущения!$B$17,NA())-1)*3+2)) -> 0 | L40: =G40+K40 -> 9 | M40: =I40*IF(AND(ISNUMBER(Допущения!$M$31),Допущения!$M$31>=0),Допущения!$M$31,NA()) -> 0 | N40: =M40*IF(AND(ISNUMBER(Допущения!$B$7),Допущения!$B$7>=0),Допущения!$B$7,NA()) -> 0
A41: Месяц 12 | B41: =Допущения!$A$32 -> Бизнес | C41: =Допущения!$N$32 -> 1 | D41: =IF(AND(COUNT(Допущения!$C$30:$C$32)=3,MIN(Допущения!$C$30:$C$32)>=0,MAX(Допущения!$C$30:$C$32)<=1,ABS(SUM(Допущения!$C$30:$C$32)-1)<0.00000001),IF(AND(ISNUMBER(Допущения!$B$51),Допущения!$B$51>=0),Допущения!$B$51,NA())*Допущения!$C$32,NA()) -> 30000 | E41: =IF(AND(ISNUMBER(Допущения!$H$32),Допущения!$H$32>0),Допущения!$H$32,NA())*Допущения!$B$23 -> 120 | F41: =D41/E41 -> 250 | G41: =IF(C41=1,0,IF(IF(AND(ISNUMBER(Допущения!$I$32),Допущения!$I$32>=0,Допущения!$I$32<=1),Допущения!$I$32,NA())*Допущения!$B$24<=1,F41*IF(AND(ISNUMBER(Допущения!$I$32),Допущения!$I$32>=0,Допущения!$I$32<=1),Допущения!$I$32,NA())*Допущения!$B$24,NA())) -> 0 | H41: =IF(C41=0,0,F41*IF(AND(ISNUMBER(Допущения!$J$32),Допущения!$J$32>=0,Допущения!$J$32<=1),Допущения!$J$32,NA())) -> 10 | I41: =H41*IF(AND(ISNUMBER(Допущения!$K$32),Допущения!$K$32>=0,Допущения!$K$32<=1),Допущения!$K$32,NA()) -> 8 | J41: =IF(C41=0,0,IF(IF(AND(ISNUMBER(Допущения!$L$32),Допущения!$L$32>=0,Допущения!$L$32<=1),Допущения!$L$32,NA())*Допущения!$B$24<=1,I41*IF(AND(ISNUMBER(Допущения!$L$32),Допущения!$L$32>=0,Допущения!$L$32<=1),Допущения!$L$32,NA())*Допущения!$B$24,NA())) -> 2.4 | K41: =IF(12<=IF(AND(ISNUMBER(Допущения!$B$17),Допущения!$B$17>=0,Допущения!$B$17=INT(Допущения!$B$17),Допущения!$B$17<=12),Допущения!$B$17,NA()),0,INDEX($J$6:$J$41,(12-IF(AND(ISNUMBER(Допущения!$B$17),Допущения!$B$17>=0,Допущения!$B$17=INT(Допущения!$B$17),Допущения!$B$17<=12),Допущения!$B$17,NA())-1)*3+3)) -> 2.4 | L41: =G41+K41 -> 2.4 | M41: =I41*IF(AND(ISNUMBER(Допущения!$M$32),Допущения!$M$32>=0),Допущения!$M$32,NA()) -> 12 | N41: =M41*IF(AND(ISNUMBER(Допущения!$B$7),Допущения!$B$7>=0),Допущения!$B$7,NA()) -> 12000
A43: Менеджера оплачиваем в месяц демо. Покупка приходит через заданное число полных месяцев.

Sheet Подписка
A1: Подписка • клиенты, выручка и обслуживание
A3: Сценарий: | B3: =IFERROR(CHOOSE(Допущения!$B$3,"Осторожный","Базовый","Сильный"),"Проверьте выбор") -> Базовый | D3: Продажи: | E3: =IFERROR(CHOOSE(Допущения!$B$4,"Самостоятельно","Через демо","Смешанные"),"Проверьте выбор") -> Смешанные
A5: Месяц | B5: Тариф | C5: В начале месяца | D5: Ушли | E5: Продлили | F5: Новые компании | G5: Активные компании | H5: Выручка, ₽ | I5: Комиссия, ₽ | J5: Хостинг, ₽ | K5: Поддержка, ₽ | L5: Подключение, ₽ | M5: Вклад после переменных затрат, ₽
A6: Месяц 1 | B6: =Допущения!$A$30 -> Старт | C6: =0 -> 0 | D6: =IF(IF(AND(ISNUMBER(Допущения!$D$30),Допущения!$D$30>=0,Допущения!$D$30<=1),Допущения!$D$30,NA())*Допущения!$B$25<=1,C6*IF(AND(ISNUMBER(Допущения!$D$30),Допущения!$D$30>=0,Допущения!$D$30<=1),Допущения!$D$30,NA())*Допущения!$B$25,NA()) -> 0 | E6: =C6-D6 -> 0 | F6: =Привлечение!L6 -> 10 | G6: =E6+F6 -> 10 | H6: =G6*IF(AND(ISNUMBER(Допущения!$B$30),Допущения!$B$30>0),Допущения!$B$30,NA()) -> 49000 | I6: =H6*IF(AND(ISNUMBER(Допущения!$B$8),Допущения!$B$8>=0,Допущения!$B$8<=1),Допущения!$B$8,NA()) -> 490 | J6: =G6*IF(AND(ISNUMBER(Допущения!$E$30),Допущения!$E$30>=0),Допущения!$E$30,NA()) -> 3000 | K6: =G6*IF(AND(ISNUMBER(Допущения!$F$30),Допущения!$F$30>=0),Допущения!$F$30,NA())*IF(AND(ISNUMBER(Допущения!$B$7),Допущения!$B$7>=0),Допущения!$B$7,NA()) -> 3300 | L6: =F6*IF(AND(ISNUMBER(Допущения!$G$30),Допущения!$G$30>=0),Допущения!$G$30,NA())*IF(AND(ISNUMBER(Допущения!$B$7),Допущения!$B$7>=0),Допущения!$B$7,NA()) -> 5000 | M6: =H6-SUM(I6:L6) -> 37210
A7: Месяц 1 | B7: =Допущения!$A$31 -> Команда | C7: =0 -> 0 | D7: =IF(IF(AND(ISNUMBER(Допущения!$D$31),Допущения!$D$31>=0,Допущения!$D$31<=1),Допущения!$D$31,NA())*Допущения!$B$25<=1,C7*IF(AND(ISNUMBER(Допущения!$D$31),Допущения!$D$31>=0,Допущения!$D$31<=1),Допущения!$D$31,NA())*Допущения!$B$25,NA()) -> 0 | E7: =C7-D7 -> 0 | F7: =Привлечение!L7 -> 2.25 | G7: =E7+F7 -> 2.25 | H7: =G7*IF(AND(ISNUMBER(Допущения!$B$31),Допущения!$B$31>0),Допущения!$B$31,NA()) -> 33525 | I7: =H7*IF(AND(ISNUMBER(Допущения!$B$8),Допущения!$B$8>=0,Допущения!$B$8<=1),Допущения!$B$8,NA()) -> 335.25 | J7: =G7*IF(AND(ISNUMBER(Допущения!$E$31),Допущения!$E$31>=0),Допущения!$E$31,NA()) -> 2250 | K7: =G7*IF(AND(ISNUMBER(Допущения!$F$31),Допущения!$F$31>=0),Допущения!$F$31,NA())*IF(AND(ISNUMBER(Допущения!$B$7),Допущения!$B$7>=0),Допущения!$B$7,NA()) -> 2250 | L7: =F7*IF(AND(ISNUMBER(Допущения!$G$31),Допущения!$G$31>=0),Допущения!$G$31,NA())*IF(AND(ISNUMBER(Допущения!$B$7),Допущения!$B$7>=0),Допущения!$B$7,NA()) -> 4500 | M7: =H7-SUM(I7:L7) -> 24189.75
A8: Месяц 1 | B8: =Допущения!$A$32 -> Бизнес | C8: =0 -> 0 | D8: =IF(IF(AND(ISNUMBER(Допущения!$D$32),Допущения!$D$32>=0,Допущения!$D$32<=1),Допущения!$D$32,NA())*Допущения!$B$25<=1,C8*IF(AND(ISNUMBER(Допущения!$D$32),Допущения!$D$32>=0,Допущения!$D$32<=1),Допущения!$D$32,NA())*Допущения!$B$25,NA()) -> 0 | E8: =C8-D8 -> 0 | F8: =Привлечение!L8 -> 0 | G8: =E8+F8 -> 0 | H8: =G8*IF(AND(ISNUMBER(Допущения!$B$32),Допущения!$B$32>0),Допущения!$B$32,NA()) -> 0 | I8: =H8*IF(AND(ISNUMBER(Допущения!$B$8),Допущения!$B$8>=0,Допущения!$B$8<=1),Допущения!$B$8,NA()) -> 0 | J8: =G8*IF(AND(ISNUMBER(Допущения!$E$32),Допущения!$E$32>=0),Допущения!$E$32,NA()) -> 0 | K8: =G8*IF(AND(ISNUMBER(Допущения!$F$32),Допущения!$F$32>=0),Допущения!$F$32,NA())*IF(AND(ISNUMBER(Допущения!$B$7),Допущения!$B$7>=0),Допущения!$B$7,NA()) -> 0 | L8: =F8*IF(AND(ISNUMBER(Допущения!$G$32),Допущения!$G$32>=0),Допущения!$G$32,NA())*IF(AND(ISNUMBER(Допущения!$B$7),Допущения!$B$7>=0),Допущения!$B$7,NA()) -> 0 | M8: =H8-SUM(I8:L8) -> 0
A9: Месяц 2 | B9: =Допущения!$A$30 -> Старт | C9: =G6 -> 10 | D9: =IF(IF(AND(ISNUMBER(Допущения!$D$30),Допущения!$D$30>=0,Допущения!$D$30<=1),Допущения!$D$30,NA())*Допущения!$B$25<=1,C9*IF(AND(ISNUMBER(Допущения!$D$30),Допущения!$D$30>=0,Допущения!$D$30<=1),Допущения!$D$30,NA())*Допущения!$B$25,NA()) -> 0.6 | E9: =C9-D9 -> 9.4 | F9: =Привлечение!L9 -> 20 | G9: =E9+F9 -> 29.4 | H9: =G9*IF(AND(ISNUMBER(Допущения!$B$30),Допущения!$B$30>0),Допущения!$B$30,NA()) -> 144060 | I9: =H9*IF(AND(ISNUMBER(Допущения!$B$8),Допущения!$B$8>=0,Допущения!$B$8<=1),Допущения!$B$8,NA()) -> 1440.6 | J9: =G9*IF(AND(ISNUMBER(Допущения!$E$30),Допущения!$E$30>=0),Допущения!$E$30,NA()) -> 8820 | K9: =G9*IF(AND(ISNUMBER(Допущения!$F$30),Допущения!$F$30>=0),Допущения!$F$30,NA())*IF(AND(ISNUMBER(Допущения!$B$7),Допущения!$B$7>=0),Допущения!$B$7,NA()) -> 9702 | L9: =F9*IF(AND(ISNUMBER(Допущения!$G$30),Допущения!$G$30>=0),Допущения!$G$30,NA())*IF(AND(ISNUMBER(Допущения!$B$7),Допущения!$B$7>=0),Допущения!$B$7,NA()) -> 10000 | M9: =H9-SUM(I9:L9) -> 114097.4
A10: Месяц 2 | B10: =Допущения!$A$31 -> Команда | C10: =G7 -> 2.25 | D10: =IF(IF(AND(ISNUMBER(Допущения!$D$31),Допущения!$D$31>=0,Допущения!$D$31<=1),Допущения!$D$31,NA())*Допущения!$B$25<=1,C10*IF(AND(ISNUMBER(Допущения!$D$31),Допущения!$D$31>=0,Допущения!$D$31<=1),Допущения!$D$31,NA())*Допущения!$B$25,NA()) -> 0.09 | E10: =C10-D10 -> 2.16 | F10: =Привлечение!L10 -> 4.5 | G10: =E10+F10 -> 6.66 | H10: =G10*IF(AND(ISNUMBER(Допущения!$B$31),Допущения!$B$31>0),Допущения!$B$31,NA()) -> 99234 | I10: =H10*IF(AND(ISNUMBER(Допущения!$B$8),Допущения!$B$8>=0,Допущения!$B$8<=1),Допущения!$B$8,NA()) -> 992.34 | J10: =G10*IF(AND(ISNUMBER(Допущения!$E$31),Допущения!$E$31>=0),Допущения!$E$31,NA()) -> 6660 | K10: =G10*IF(AND(ISNUMBER(Допущения!$F$31),Допущения!$F$31>=0),Допущения!$F$31,NA())*IF(AND(ISNUMBER(Допущения!$B$7),Допущения!$B$7>=0),Допущения!$B$7,NA()) -> 6660 | L10: =F10*IF(AND(ISNUMBER(Допущения!$G$31),Допущения!$G$31>=0),Допущения!$G$31,NA())*IF(AND(ISNUMBER(Допущения!$B$7),Допущения!$B$7>=0),Допущения!$B$7,NA()) -> 9000 | M10: =H10-SUM(I10:L10) -> 75921.66
A11: Месяц 2 | B11: =Допущения!$A$32 -> Бизнес | C11: =G8 -> 0 | D11: =IF(IF(AND(ISNUMBER(Допущения!$D$32),Допущения!$D$32>=0,Допущения!$D$32<=1),Допущения!$D$32,NA())*Допущения!$B$25<=1,C11*IF(AND(ISNUMBER(Допущения!$D$32),Допущения!$D$32>=0,Допущения!$D$32<=1),Допущения!$D$32,NA())*Допущения!$B$25,NA()) -> 0 | E11: =C11-D11 -> 0 | F11: =Привлечение!L11 -> 0.6 | G11: =E11+F11 -> 0.6 | H11: =G11*IF(AND(ISNUMBER(Допущения!$B$32),Допущения!$B$32>0),Допущения!$B$32,NA()) -> 29940 | I11: =H11*IF(AND(ISNUMBER(Допущения!$B$8),Допущения!$B$8>=0,Допущения!$B$8<=1),Допущения!$B$8,NA()) -> 299.4 | J11: =G11*IF(AND(ISNUMBER(Допущения!$E$32),Допущения!$E$32>=0),Допущения!$E$32,NA()) -> 2100 | K11: =G11*IF(AND(ISNUMBER(Допущения!$F$32),Допущения!$F$32>=0),Допущения!$F$32,NA())*IF(AND(ISNUMBER(Допущения!$B$7),Допущения!$B$7>=0),Допущения!$B$7,NA()) -> 1800 | L11: =F11*IF(AND(ISNUMBER(Допущения!$G$32),Допущения!$G$32>=0),Допущения!$G$32,NA())*IF(AND(ISNUMBER(Допущения!$B$7),Допущения!$B$7>=0),Допущения!$B$7,NA()) -> 3600 | M11: =H11-SUM(I11:L11) -> 22140.6
A12: Месяц 3 | B12: =Допущения!$A$30 -> Старт | C12: =G9 -> 29.4 | D12: =IF(IF(AND(ISNUMBER(Допущения!$D$30),Допущения!$D$30>=0,Допущения!$D$30<=1),Допущения!$D$30,NA())*Допущения!$B$25<=1,C12*IF(AND(ISNUMBER(Допущения!$D$30),Допущения!$D$30>=0,Допущения!$D$30<=1),Допущения!$D$30,NA())*Допущения!$B$25,NA()) -> 1.764 | E12: =C12-D12 -> 27.636 | F12: =Привлечение!L12 -> 30 | G12: =E12+F12 -> 57.636 | H12: =G12*IF(AND(ISNUMBER(Допущения!$B$30),Допущения!$B$30>0),Допущения!$B$30,NA()) -> 282416.4 | I12: =H12*IF(AND(ISNUMBER(Допущения!$B$8),Допущения!$B$8>=0,Допущения!$B$8<=1),Допущения!$B$8,NA()) -> 2824.164 | J12: =G12*IF(AND(ISNUMBER(Допущения!$E$30),Допущения!$E$30>=0),Допущения!$E$30,NA()) -> 17290.8 | K12: =G12*IF(AND(ISNUMBER(Допущения!$F$30),Допущения!$F$30>=0),Допущения!$F$30,NA())*IF(AND(ISNUMBER(Допущения!$B$7),Допущения!$B$7>=0),Допущения!$B$7,NA()) -> 19019.88 | L12: =F12*IF(AND(ISNUMBER(Допущения!$G$30),Допущения!$G$30>=0),Допущения!$G$30,NA())*IF(AND(ISNUMBER(Допущения!$B$7),Допущения!$B$7>=0),Допущения!$B$7,NA()) -> 15000 | M12: =H12-SUM(I12:L12) -> 228281.56
A13: Месяц 3 | B13: =Допущения!$A$31 -> Команда | C13: =G10 -> 6.66 | D13: =IF(IF(AND(ISNUMBER(Допущения!$D$31),Допущения!$D$31>=0,Допущения!$D$31<=1),Допущения!$D$31,NA())*Допущения!$B$25<=1,C13*IF(AND(ISNUMBER(Допущения!$D$31),Допущения!$D$31>=0,Допущения!$D$31<=1),Допущения!$D$31,NA())*Допущения!$B$25,NA()) -> 0.2664 | E13: =C13-D13 -> 6.3936 | F13: =Привлечение!L13 -> 6.75 | G13: =E13+F13 -> 13.1436 | H13: =G13*IF(AND(ISNUMBER(Допущения!$B$31),Допущения!$B$31>0),Допущения!$B$31,NA()) -> 195839.64 | I13: =H13*IF(AND(ISNUMBER(Допущения!$B$8),Допущения!$B$8>=0,Допущения!$B$8<=1),Допущения!$B$8,NA()) -> 1958.3964 | J13: =G13*IF(AND(ISNUMBER(Допущения!$E$31),Допущения!$E$31>=0),Допущения!$E$31,NA()) -> 13143.6 | K13: =G13*IF(AND(ISNUMBER(Допущения!$F$31),Допущения!$F$31>=0),Допущения!$F$31,NA())*IF(AND(ISNUMBER(Допущения!$B$7),Допущения!$B$7>=0),Допущения!$B$7,NA()) -> 13143.6 | L13: =F13*IF(AND(ISNUMBER(Допущения!$G$31),Допущения!$G$31>=0),Допущения!$G$31,NA())*IF(AND(ISNUMBER(Допущения!$B$7),Допущения!$B$7>=0),Допущения!$B$7,NA()) -> 13500 | M13: =H13-SUM(I13:L13) -> 154094.04
A14: Месяц 3 | B14: =Допущения!$A$32 -> Бизнес | C14: =G11 -> 0.6 | D14: =IF(IF(AND(ISNUMBER(Допущения!$D$32),Допущения!$D$32>=0,Допущения!$D$32<=1),Допущения!$D$32,NA())*Допущения!$B$25<=1,C14*IF(AND(ISNUMBER(Допущения!$D$32),Допущения!$D$32>=0,Допущения!$D$32<=1),Допущения!$D$32,NA())*Допущения!$B$25,NA()) -> 0.015 | E14: =C14-D14 -> 0.585 | F14: =Привлечение!L14 -> 1.2 | G14: =E14+F14 -> 1.785 | H14: =G14*IF(AND(ISNUMBER(Допущения!$B$32),Допущения!$B$32>0),Допущения!$B$32,NA()) -> 89071.5 | I14: =H14*IF(AND(ISNUMBER(Допущения!$B$8),Допущения!$B$8>=0,Допущения!$B$8<=1),Допущения!$B$8,NA()) -> 890.715 | J14: =G14*IF(AND(ISNUMBER(Допущения!$E$32),Допущения!$E$32>=0),Допущения!$E$32,NA()) -> 6247.5 | K14: =G14*IF(AND(ISNUMBER(Допущения!$F$32),Допущения!$F$32>=0),Допущения!$F$32,NA())*IF(AND(ISNUMBER(Допущения!$B$7),Допущения!$B$7>=0),Допущения!$B$7,NA()) -> 5355 | L14: =F14*IF(AND(ISNUMBER(Допущения!$G$32),Допущения!$G$32>=0),Допущения!$G$32,NA())*IF(AND(ISNUMBER(Допущения!$B$7),Допущения!$B$7>=0),Допущения!$B$7,NA()) -> 7200 | M14: =H14-SUM(I14:L14) -> 69378.285
A15: Месяц 4 | B15: =Допущения!$A$30 -> Старт | C15: =G12 -> 57.636 | D15: =IF(IF(AND(ISNUMBER(Допущения!$D$30),Допущения!$D$30>=0,Допущения!$D$30<=1),Допущения!$D$30,NA())*Допущения!$B$25<=1,C15*IF(AND(ISNUMBER(Допущения!$D$30),Допущения!$D$30>=0,Допущения!$D$30<=1),Допущения!$D$30,NA())*Допущения!$B$25,NA()) -> 3.45816 | E15: =C15-D15 -> 54.17784 | F15: =Привлечение!L15 -> 40 | G15: =E15+F15 -> 94.17784 | H15: =G15*IF(AND(ISNUMBER(Допущения!$B$30),Допущения!$B$30>0),Допущения!$B$30,NA()) -> 461471.42 | I15: =H15*IF(AND(ISNUMBER(Допущения!$B$8),Допущения!$B$8>=0,Допущения!$B$8<=1),Допущения!$B$8,NA()) -> 4614.7142 | J15: =G15*IF(AND(ISNUMBER(Допущения!$E$30),Допущения!$E$30>=0),Допущения!$E$30,NA()) -> 28253.352 | K15: =G15*IF(AND(ISNUMBER(Допущения!$F$30),Допущения!$F$30>=0),Допущения!$F$30,NA())*IF(AND(ISNUMBER(Допущения!$B$7),Допущения!$B$7>=0),Допущения!$B$7,NA()) -> 31078.687 | L15: =F15*IF(AND(ISNUMBER(Допущения!$G$30),Допущения!$G$30>=0),Допущения!$G$30,NA())*IF(AND(ISNUMBER(Допущения!$B$7),Допущения!$B$7>=0),Допущения!$B$7,NA()) -> 20000 | M15: =H15-SUM(I15:L15) -> 377524.66
A16: Месяц 4 | B16: =Допущения!$A$31 -> Команда | C16: =G13 -> 13.1436 | D16: =IF(IF(AND(ISNUMBER(Допущения!$D$31),Допущения!$D$31>=0,Допущения!$D$31<=1),Допущения!$D$31,NA())*Допущения!$B$25<=1,C16*IF(AND(ISNUMBER(Допущения!$D$31),Допущения!$D$31>=0,Допущения!$D$31<=1),Допущения!$D$31,NA())*Допущения!$B$25,NA()) -> 0.525744 | E16: =C16-D16 -> 12.617856 | F16: =Привлечение!L16 -> 9 | G16: =E16+F16 -> 21.617856 | H16: =G16*IF(AND(ISNUMBER(Допущения!$B$31),Допущения!$B$31>0),Допущения!$B$31,NA()) -> 322106.05 | I16: =H16*IF(AND(ISNUMBER(Допущения!$B$8),Допущения!$B$8>=0,Допущения!$B$8<=1),Допущения!$B$8,NA()) -> 3221.0605 | J16: =G16*IF(AND(ISNUMBER(Допущения!$E$31),Допущения!$E$31>=0),Допущения!$E$31,NA()) -> 21617.856 | K16: =G16*IF(AND(ISNUMBER(Допущения!$F$31),Допущения!$F$31>=0),Допущения!$F$31,NA())*IF(AND(ISNUMBER(Допущения!$B$7),Допущения!$B$7>=0),Допущения!$B$7,NA()) -> 21617.856 | L16: =F16*IF(AND(ISNUMBER(Допущения!$G$31),Допущения!$G$31>=0),Допущения!$G$31,NA())*IF(AND(ISNUMBER(Допущения!$B$7),Допущения!$B$7>=0),Допущения!$B$7,NA()) -> 18000 | M16: =H16-SUM(I16:L16) -> 257649.28
A17: Месяц 4 | B17: =Допущения!$A$32 -> Бизнес | C17: =G14 -> 1.785 | D17: =IF(IF(AND(ISNUMBER(Допущения!$D$32),Допущения!$D$32>=0,Допущения!$D$32<=1),Допущения!$D$32,NA())*Допущения!$B$25<=1,C17*IF(AND(ISNUMBER(Допущения!$D$32),Допущения!$D$32>=0,Допущения!$D$32<=1),Допущения!$D$32,NA())*Допущения!$B$25,NA()) -> 0.044625 | E17: =C17-D17 -> 1.740375 | F17: =Привлечение!L17 -> 1.8 | G17: =E17+F17 -> 3.540375 | H17: =G17*IF(AND(ISNUMBER(Допущения!$B$32),Допущения!$B$32>0),Допущения!$B$32,NA()) -> 176664.71 | I17: =H17*IF(AND(ISNUMBER(Допущения!$B$8),Допущения!$B$8>=0,Допущения!$B$8<=1),Допущения!$B$8,NA()) -> 1766.6471 | J17: =G17*IF(AND(ISNUMBER(Допущения!$E$32),Допущения!$E$32>=0),Допущения!$E$32,NA()) -> 12391.312 | K17: =G17*IF(AND(ISNUMBER(Допущения!$F$32),Допущения!$F$32>=0),Допущения!$F$32,NA())*IF(AND(ISNUMBER(Допущения!$B$7),Допущения!$B$7>=0),Допущения!$B$7,NA()) -> 10621.125 | L17: =F17*IF(AND(ISNUMBER(Допущения!$G$32),Допущения!$G$32>=0),Допущения!$G$32,NA())*IF(AND(ISNUMBER(Допущения!$B$7),Допущения!$B$7>=0),Допущения!$B$7,NA()) -> 10800 | M17: =H17-SUM(I17:L17) -> 141085.63
A18: Месяц 5 | B18: =Допущения!$A$30 -> Старт | C18: =G15 -> 94.17784 | D18: =IF(IF(AND(ISNUMBER(Допущения!$D$30),Допущения!$D$30>=0,Допущения!$D$30<=1),Допущения!$D$30,NA())*Допущения!$B$25<=1,C18*IF(AND(ISNUMBER(Допущения!$D$30),Допущения!$D$30>=0,Допущения!$D$30<=1),Допущения!$D$30,NA())*Допущения!$B$25,NA()) -> 5.6506704 | E18: =C18-D18 -> 88.52717 | F18: =Привлечение!L18 -> 40 | G18: =E18+F18 -> 128.52717 | H18: =G18*IF(AND(ISNUMBER(Допущения!$B$30),Допущения!$B$30>0),Допущения!$B$30,NA()) -> 629783.13 | I18: =H18*IF(AND(ISNUMBER(Допущения!$B$8),Допущения!$B$8>=0,Допущения!$B$8<=1),Допущения!$B$8,NA()) -> 6297.8313 | J18: =G18*IF(AND(ISNUMBER(Допущения!$E$30),Допущения!$E$30>=0),Допущения!$E$30,NA()) -> 38558.151 | K18: =G18*IF(AND(ISNUMBER(Допущения!$F$30),Допущения!$F$30>=0),Допущения!$F$30,NA())*IF(AND(ISNUMBER(Допущения!$B$7),Допущения!$B$7>=0),Допущения!$B$7,NA()) -> 42413.966 | L18: =F18*IF(AND(ISNUMBER(Допущения!$G$30),Допущения!$G$30>=0),Допущения!$G$30,NA())*IF(AND(ISNUMBER(Допущения!$B$7),Допущения!$B$7>=0),Допущения!$B$7,NA()) -> 20000 | M18: =H18-SUM(I18:L18) -> 522513.18
A19: Месяц 5 | B19: =Допущения!$A$31 -> Команда | C19: =G16 -> 21.617856 | D19: =IF(IF(AND(ISNUMBER(Допущения!$D$31),Допущения!$D$31>=0,Допущения!$D$31<=1),Допущения!$D$31,NA())*Допущения!$B$25<=1,C19*IF(AND(ISNUMBER(Допущения!$D$31),Допущения!$D$31>=0,Допущения!$D$31<=1),Допущения!$D$31,NA())*Допущения!$B$25,NA()) -> 0.86471424 | E19: =C19-D19 -> 20.753142 | F19: =Привлечение!L19 -> 9 | G19: =E19+F19 -> 29.753142 | H19: =G19*IF(AND(ISNUMBER(Допущения!$B$31),Допущения!$B$31>0),Допущения!$B$31,NA()) -> 443321.81 | I19: =H19*IF(AND(ISNUMBER(Допущения!$B$8),Допущения!$B$8>=0,Допущения!$B$8<=1),Допущения!$B$8,NA()) -> 4433.2181 | J19: =G19*IF(AND(ISNUMBER(Допущения!$E$31),Допущения!$E$31>=0),Допущения!$E$31,NA()) -> 29753.142 | K19: =G19*IF(AND(ISNUMBER(Допущения!$F$31),Допущения!$F$31>=0),Допущения!$F$31,NA())*IF(AND(ISNUMBER(Допущения!$B$7),Допущения!$B$7>=0),Допущения!$B$7,NA()) -> 29753.142 | L19: =F19*IF(AND(ISNUMBER(Допущения!$G$31),Допущения!$G$31>=0),Допущения!$G$31,NA())*IF(AND(ISNUMBER(Допущения!$B$7),Допущения!$B$7>=0),Допущения!$B$7,NA()) -> 18000 | M19: =H19-SUM(I19:L19) -> 361382.31
A20: Месяц 5 | B20: =Допущения!$A$32 -> Бизнес | C20: =G17 -> 3.540375 | D20: =IF(IF(AND(ISNUMBER(Допущения!$D$32),Допущения!$D$32>=0,Допущения!$D$32<=1),Допущения!$D$32,NA())*Допущения!$B$25<=1,C20*IF(AND(ISNUMBER(Допущения!$D$32),Допущения!$D$32>=0,Допущения!$D$32<=1),Допущения!$D$32,NA())*Допущения!$B$25,NA()) -> 0.088509375 | E20: =C20-D20 -> 3.4518656 | F20: =Привлечение!L20 -> 2.4 | G20: =E20+F20 -> 5.8518656 | H20: =G20*IF(AND(ISNUMBER(Допущения!$B$32),Допущения!$B$32>0),Допущения!$B$32,NA()) -> 292008.09 | I20: =H20*IF(AND(ISNUMBER(Допущения!$B$8),Допущения!$B$8>=0,Допущения!$B$8<=1),Допущения!$B$8,NA()) -> 2920.0809 | J20: =G20*IF(AND(ISNUMBER(Допущения!$E$32),Допущения!$E$32>=0),Допущения!$E$32,NA()) -> 20481.53 | K20: =G20*IF(AND(ISNUMBER(Допущения!$F$32),Допущения!$F$32>=0),Допущения!$F$32,NA())*IF(AND(ISNUMBER(Допущения!$B$7),Допущения!$B$7>=0),Допущения!$B$7,NA()) -> 17555.597 | L20: =F20*IF(AND(ISNUMBER(Допущения!$G$32),Допущения!$G$32>=0),Допущения!$G$32,NA())*IF(AND(ISNUMBER(Допущения!$B$7),Допущения!$B$7>=0),Допущения!$B$7,NA()) -> 14400 | M20: =H20-SUM(I20:L20) -> 236650.89
A21: Месяц 6 | B21: =Допущения!$A$30 -> Старт | C21: =G18 -> 128.52717 | D21: =IF(IF(AND(ISNUMBER(Допущения!$D$30),Допущения!$D$30>=0,Допущения!$D$30<=1),Допущения!$D$30,NA())*Допущения!$B$25<=1,C21*IF(AND(ISNUMBER(Допущения!$D$30),Допущения!$D$30>=0,Допущения!$D$30<=1),Допущения!$D$30,NA())*Допущения!$B$25,NA()) -> 7.7116302 | E21: =C21-D21 -> 120.81554 | F21: =Привлечение!L21 -> 40 | G21: =E21+F21 -> 160.81554 | H21: =G21*IF(AND(ISNUMBER(Допущения!$B$30),Допущения!$B$30>0),Допущения!$B$30,NA()) -> 787996.14 | I21: =H21*IF(AND(ISNUMBER(Допущения!$B$8),Допущения!$B$8>=0,Допущения!$B$8<=1),Допущения!$B$8,NA()) -> 7879.9614 | J21: =G21*IF(AND(ISNUMBER(Допущения!$E$30),Допущения!$E$30>=0),Допущения!$E$30,NA()) -> 48244.662 | K21: =G21*IF(AND(ISNUMBER(Допущения!$F$30),Допущения!$F$30>=0),Допущения!$F$30,NA())*IF(AND(ISNUMBER(Допущения!$B$7),Допущения!$B$7>=0),Допущения!$B$7,NA()) -> 53069.128 | L21: =F21*IF(AND(ISNUMBER(Допущения!$G$30),Допущения!$G$30>=0),Допущения!$G$30,NA())*IF(AND(ISNUMBER(Допущения!$B$7),Допущения!$B$7>=0),Допущения!$B$7,NA()) -> 20000 | M21: =H21-SUM(I21:L21) -> 658802.39
A22: Месяц 6 | B22: =Допущения!$A$31 -> Команда | C22: =G19 -> 29.753142 | D22: =IF(IF(AND(ISNUMBER(Допущения!$D$31),Допущения!$D$31>=0,Допущения!$D$31<=1),Допущения!$D$31,NA())*Допущения!$B$25<=1,C22*IF(AND(ISNUMBER(Допущения!$D$31),Допущения!$D$31>=0,Допущения!$D$31<=1),Допущения!$D$31,NA())*Допущения!$B$25,NA()) -> 1.1901257 | E22: =C22-D22 -> 28.563016 | F22: =Привлечение!L22 -> 9 | G22: =E22+F22 -> 37.563016 | H22: =G22*IF(AND(ISNUMBER(Допущения!$B$31),Допущения!$B$31>0),Допущения!$B$31,NA()) -> 559688.94 | I22: =H22*IF(AND(ISNUMBER(Допущения!$B$8),Допущения!$B$8>=0,Допущения!$B$8<=1),Допущения!$B$8,NA()) -> 5596.8894 | J22: =G22*IF(AND(ISNUMBER(Допущения!$E$31),Допущения!$E$31>=0),Допущения!$E$31,NA()) -> 37563.016 | K22: =G22*IF(AND(ISNUMBER(Допущения!$F$31),Допущения!$F$31>=0),Допущения!$F$31,NA())*IF(AND(ISNUMBER(Допущения!$B$7),Допущения!$B$7>=0),Допущения!$B$7,NA()) -> 37563.016 | L22: =F22*IF(AND(ISNUMBER(Допущения!$G$31),Допущения!$G$31>=0),Допущения!$G$31,NA())*IF(AND(ISNUMBER(Допущения!$B$7),Допущения!$B$7>=0),Допущения!$B$7,NA()) -> 18000 | M22: =H22-SUM(I22:L22) -> 460966.02
A23: Месяц 6 | B23: =Допущения!$A$32 -> Бизнес | C23: =G20 -> 5.8518656 | D23: =IF(IF(AND(ISNUMBER(Допущения!$D$32),Допущения!$D$32>=0,Допущения!$D$32<=1),Допущения!$D$32,NA())*Допущения!$B$25<=1,C23*IF(AND(ISNUMBER(Допущения!$D$32),Допущения!$D$32>=0,Допущения!$D$32<=1),Допущения!$D$32,NA())*Допущения!$B$25,NA()) -> 0.14629664 | E23: =C23-D23 -> 5.705569 | F23: =Привлечение!L23 -> 2.4 | G23: =E23+F23 -> 8.105569 | H23: =G23*IF(AND(ISNUMBER(Допущения!$B$32),Допущения!$B$32>0),Допущения!$B$32,NA()) -> 404467.89 | I23: =H23*IF(AND(ISNUMBER(Допущения!$B$8),Допущения!$B$8>=0,Допущения!$B$8<=1),Допущения!$B$8,NA()) -> 4044.6789 | J23: =G23*IF(AND(ISNUMBER(Допущения!$E$32),Допущения!$E$32>=0),Допущения!$E$32,NA()) -> 28369.491 | K23: =G23*IF(AND(ISNUMBER(Допущения!$F$32),Допущения!$F$32>=0),Допущения!$F$32,NA())*IF(AND(ISNUMBER(Допущения!$B$7),Допущения!$B$7>=0),Допущения!$B$7,NA()) -> 24316.707 | L23: =F23*IF(AND(ISNUMBER(Допущения!$G$32),Допущения!$G$32>=0),Допущения!$G$32,NA())*IF(AND(ISNUMBER(Допущения!$B$7),Допущения!$B$7>=0),Допущения!$B$7,NA()) -> 14400 | M23: =H23-SUM(I23:L23) -> 333337.01
A24: Месяц 7 | B24: =Допущения!$A$30 -> Старт | C24: =G21 -> 160.81554 | D24: =IF(IF(AND(ISNUMBER(Допущения!$D$30),Допущения!$D$30>=0,Допущения!$D$30<=1),Допущения!$D$30,NA())*Допущения!$B$25<=1,C24*IF(AND(ISNUMBER(Допущения!$D$30),Допущения!$D$30>=0,Допущения!$D$30<=1),Допущения!$D$30,NA())*Допущения!$B$25,NA()) -> 9.6489324 | E24: =C24-D24 -> 151.16661 | F24: =Привлечение!L24 -> 40 | G24: =E24+F24 -> 191.16661 | H24: =G24*IF(AND(ISNUMBER(Допущения!$B$30),Допущения!$B$30>0),Допущения!$B$30,NA()) -> 936716.37 | I24: =H24*IF(AND(ISNUMBER(Допущения!$B$8),Допущения!$B$8>=0,Допущения!$B$8<=1),Допущения!$B$8,NA()) -> 9367.1637 | J24: =G24*IF(AND(ISNUMBER(Допущения!$E$30),Допущения!$E$30>=0),Допущения!$E$30,NA()) -> 57349.982 | K24: =G24*IF(AND(ISNUMBER(Допущения!$F$30),Допущения!$F$30>=0),Допущения!$F$30,NA())*IF(AND(ISNUMBER(Допущения!$B$7),Допущения!$B$7>=0),Допущения!$B$7,NA()) -> 63084.98 | L24: =F24*IF(AND(ISNUMBER(Допущения!$G$30),Допущения!$G$30>=0),Допущения!$G$30,NA())*IF(AND(ISNUMBER(Допущения!$B$7),Допущения!$B$7>=0),Допущения!$B$7,NA()) -> 20000 | M24: =H24-SUM(I24:L24) -> 786914.25
A25: Месяц 7 | B25: =Допущения!$A$31 -> Команда | C25: =G22 -> 37.563016 | D25: =IF(IF(AND(ISNUMBER(Допущения!$D$31),Допущения!$D$31>=0,Допущения!$D$31<=1),Допущения!$D$31,NA())*Допущения!$B$25<=1,C25*IF(AND(ISNUMBER(Допущения!$D$31),Допущения!$D$31>=0,Допущения!$D$31<=1),Допущения!$D$31,NA())*Допущения!$B$25,NA()) -> 1.5025206 | E25: =C25-D25 -> 36.060495 | F25: =Привлечение!L25 -> 9 | G25: =E25+F25 -> 45.060495 | H25: =G25*IF(AND(ISNUMBER(Допущения!$B$31),Допущения!$B$31>0),Допущения!$B$31,NA()) -> 671401.38 | I25: =H25*IF(AND(ISNUMBER(Допущения!$B$8),Допущения!$B$8>=0,Допущения!$B$8<=1),Допущения!$B$8,NA()) -> 6714.0138 | J25: =G25*IF(AND(ISNUMBER(Допущения!$E$31),Допущения!$E$31>=0),Допущения!$E$31,NA()) -> 45060.495 | K25: =G25*IF(AND(ISNUMBER(Допущения!$F$31),Допущения!$F$31>=0),Допущения!$F$31,NA())*IF(AND(ISNUMBER(Допущения!$B$7),Допущения!$B$7>=0),Допущения!$B$7,NA()) -> 45060.495 | L25: =F25*IF(AND(ISNUMBER(Допущения!$G$31),Допущения!$G$31>=0),Допущения!$G$31,NA())*IF(AND(ISNUMBER(Допущения!$B$7),Допущения!$B$7>=0),Допущения!$B$7,NA()) -> 18000 | M25: =H25-SUM(I25:L25) -> 556566.38
A26: Месяц 7 | B26: =Допущения!$A$32 -> Бизнес | C26: =G23 -> 8.105569 | D26: =IF(IF(AND(ISNUMBER(Допущения!$D$32),Допущения!$D$32>=0,Допущения!$D$32<=1),Допущения!$D$32,NA())*Допущения!$B$25<=1,C26*IF(AND(ISNUMBER(Допущения!$D$32),Допущения!$D$32>=0,Допущения!$D$32<=1),Допущения!$D$32,NA())*Допущения!$B$25,NA()) -> 0.20263922 | E26: =C26-D26 -> 7.9029298 | F26: =Привлечение!L26 -> 2.4 | G26: =E26+F26 -> 10.30293 | H26: =G26*IF(AND(ISNUMBER(Допущения!$B$32),Допущения!$B$32>0),Допущения!$B$32,NA()) -> 514116.2 | I26: =H26*IF(AND(ISNUMBER(Допущения!$B$8),Допущения!$B$8>=0,Допущения!$B$8<=1),Допущения!$B$8,NA()) -> 5141.162 | J26: =G26*IF(AND(ISNUMBER(Допущения!$E$32),Допущения!$E$32>=0),Допущения!$E$32,NA()) -> 36060.254 | K26: =G26*IF(AND(ISNUMBER(Допущения!$F$32),Допущения!$F$32>=0),Допущения!$F$32,NA())*IF(AND(ISNUMBER(Допущения!$B$7),Допущения!$B$7>=0),Допущения!$B$7,NA()) -> 30908.789 | L26: =F26*IF(AND(ISNUMBER(Допущения!$G$32),Допущения!$G$32>=0),Допущения!$G$32,NA())*IF(AND(ISNUMBER(Допущения!$B$7),Допущения!$B$7>=0),Допущения!$B$7,NA()) -> 14400 | M26: =H26-SUM(I26:L26) -> 427605.99
A27: Месяц 8 | B27: =Допущения!$A$30 -> Старт | C27: =G24 -> 191.16661 | D27: =IF(IF(AND(ISNUMBER(Допущения!$D$30),Допущения!$D$30>=0,Допущения!$D$30<=1),Допущения!$D$30,NA())*Допущения!$B$25<=1,C27*IF(AND(ISNUMBER(Допущения!$D$30),Допущения!$D$30>=0,Допущения!$D$30<=1),Допущения!$D$30,NA())*Допущения!$B$25,NA()) -> 11.469996 | E27: =C27-D27 -> 179.69661 | F27: =Привлечение!L27 -> 40 | G27: =E27+F27 -> 219.69661 | H27: =G27*IF(AND(ISNUMBER(Допущения!$B$30),Допущения!$B$30>0),Допущения!$B$30,NA()) -> 1076513.4 | I27: =H27*IF(AND(ISNUMBER(Допущения!$B$8),Допущения!$B$8>=0,Допущения!$B$8<=1),Допущения!$B$8,NA()) -> 10765.134 | J27: =G27*IF(AND(ISNUMBER(Допущения!$E$30),Допущения!$E$30>=0),Допущения!$E$30,NA()) -> 65908.983 | K27: =G27*IF(AND(ISNUMBER(Допущения!$F$30),Допущения!$F$30>=0),Допущения!$F$30,NA())*IF(AND(ISNUMBER(Допущения!$B$7),Допущения!$B$7>=0),Допущения!$B$7,NA()) -> 72499.882 | L27: =F27*IF(AND(ISNUMBER(Допущения!$G$30),Допущения!$G$30>=0),Допущения!$G$30,NA())*IF(AND(ISNUMBER(Допущения!$B$7),Допущения!$B$7>=0),Допущения!$B$7,NA()) -> 20000 | M27: =H27-SUM(I27:L27) -> 907339.39
A28: Месяц 8 | B28: =Допущения!$A$31 -> Команда | C28: =G25 -> 45.060495 | D28: =IF(IF(AND(ISNUMBER(Допущения!$D$31),Допущения!$D$31>=0,Допущения!$D$31<=1),Допущения!$D$31,NA())*Допущения!$B$25<=1,C28*IF(AND(ISNUMBER(Допущения!$D$31),Допущения!$D$31>=0,Допущения!$D$31<=1),Допущения!$D$31,NA())*Допущения!$B$25,NA()) -> 1.8024198 | E28: =C28-D28 -> 43.258076 | F28: =Привлечение!L28 -> 9 | G28: =E28+F28 -> 52.258076 | H28: =G28*IF(AND(ISNUMBER(Допущения!$B$31),Допущения!$B$31>0),Допущения!$B$31,NA()) -> 778645.33 | I28: =H28*IF(AND(ISNUMBER(Допущения!$B$8),Допущения!$B$8>=0,Допущения!$B$8<=1),Допущения!$B$8,NA()) -> 7786.4533 | J28: =G28*IF(AND(ISNUMBER(Допущения!$E$31),Допущения!$E$31>=0),Допущения!$E$31,NA()) -> 52258.076 | K28: =G28*IF(AND(ISNUMBER(Допущения!$F$31),Допущения!$F$31>=0),Допущения!$F$31,NA())*IF(AND(ISNUMBER(Допущения!$B$7),Допущения!$B$7>=0),Допущения!$B$7,NA()) -> 52258.076 | L28: =F28*IF(AND(ISNUMBER(Допущения!$G$31),Допущения!$G$31>=0),Допущения!$G$31,NA())*IF(AND(ISNUMBER(Допущения!$B$7),Допущения!$B$7>=0),Допущения!$B$7,NA()) -> 18000 | M28: =H28-SUM(I28:L28) -> 648342.72
A29: Месяц 8 | B29: =Допущения!$A$32 -> Бизнес | C29: =G26 -> 10.30293 | D29: =IF(IF(AND(ISNUMBER(Допущения!$D$32),Допущения!$D$32>=0,Допущения!$D$32<=1),Допущения!$D$32,NA())*Допущения!$B$25<=1,C29*IF(AND(ISNUMBER(Допущения!$D$32),Допущения!$D$32>=0,Допущения!$D$32<=1),Допущения!$D$32,NA())*Допущения!$B$25,NA()) -> 0.25757324 | E29: =C29-D29 -> 10.045357 | F29: =Привлечение!L29 -> 2.4 | G29: =E29+F29 -> 12.445357 | H29: =G29*IF(AND(ISNUMBER(Допущения!$B$32),Допущения!$B$32>0),Допущения!$B$32,NA()) -> 621023.29 | I29: =H29*IF(AND(ISNUMBER(Допущения!$B$8),Допущения!$B$8>=0,Допущения!$B$8<=1),Допущения!$B$8,NA()) -> 6210.2329 | J29: =G29*IF(AND(ISNUMBER(Допущения!$E$32),Допущения!$E$32>=0),Допущения!$E$32,NA()) -> 43558.748 | K29: =G29*IF(AND(ISNUMBER(Допущения!$F$32),Допущения!$F$32>=0),Допущения!$F$32,NA())*IF(AND(ISNUMBER(Допущения!$B$7),Допущения!$B$7>=0),Допущения!$B$7,NA()) -> 37336.07 | L29: =F29*IF(AND(ISNUMBER(Допущения!$G$32),Допущения!$G$32>=0),Допущения!$G$32,NA())*IF(AND(ISNUMBER(Допущения!$B$7),Допущения!$B$7>=0),Допущения!$B$7,NA()) -> 14400 | M29: =H29-SUM(I29:L29) -> 519518.24
A30: Месяц 9 | B30: =Допущения!$A$30 -> Старт | C30: =G27 -> 219.69661 | D30: =IF(IF(AND(ISNUMBER(Допущения!$D$30),Допущения!$D$30>=0,Допущения!$D$30<=1),Допущения!$D$30,NA())*Допущения!$B$25<=1,C30*IF(AND(ISNUMBER(Допущения!$D$30),Допущения!$D$30>=0,Допущения!$D$30<=1),Допущения!$D$30,NA())*Допущения!$B$25,NA()) -> 13.181797 | E30: =C30-D30 -> 206.51481 | F30: =Привлечение!L30 -> 40 | G30: =E30+F30 -> 246.51481 | H30: =G30*IF(AND(ISNUMBER(Допущения!$B$30),Допущения!$B$30>0),Допущения!$B$30,NA()) -> 1207922.6 | I30: =H30*IF(AND(ISNUMBER(Допущения!$B$8),Допущения!$B$8>=0,Допущения!$B$8<=1),Допущения!$B$8,NA()) -> 12079.226 | J30: =G30*IF(AND(ISNUMBER(Допущения!$E$30),Допущения!$E$30>=0),Допущения!$E$30,NA()) -> 73954.444 | K30: =G30*IF(AND(ISNUMBER(Допущения!$F$30),Допущения!$F$30>=0),Допущения!$F$30,NA())*IF(AND(ISNUMBER(Допущения!$B$7),Допущения!$B$7>=0),Допущения!$B$7,NA()) -> 81349.889 | L30: =F30*IF(AND(ISNUMBER(Допущения!$G$30),Допущения!$G$30>=0),Допущения!$G$30,NA())*IF(AND(ISNUMBER(Допущения!$B$7),Допущения!$B$7>=0),Допущения!$B$7,NA()) -> 20000 | M30: =H30-SUM(I30:L30) -> 1020539
A31: Месяц 9 | B31: =Допущения!$A$31 -> Команда | C31: =G28 -> 52.258076 | D31: =IF(IF(AND(ISNUMBER(Допущения!$D$31),Допущения!$D$31>=0,Допущения!$D$31<=1),Допущения!$D$31,NA())*Допущения!$B$25<=1,C31*IF(AND(ISNUMBER(Допущения!$D$31),Допущения!$D$31>=0,Допущения!$D$31<=1),Допущения!$D$31,NA())*Допущения!$B$25,NA()) -> 2.090323 | E31: =C31-D31 -> 50.167753 | F31: =Привлечение!L31 -> 9 | G31: =E31+F31 -> 59.167753 | H31: =G31*IF(AND(ISNUMBER(Допущения!$B$31),Допущения!$B$31>0),Допущения!$B$31,NA()) -> 881599.51 | I31: =H31*IF(AND(ISNUMBER(Допущения!$B$8),Допущения!$B$8>=0,Допущения!$B$8<=1),Допущения!$B$8,NA()) -> 8815.9951 | J31: =G31*IF(AND(ISNUMBER(Допущения!$E$31),Допущения!$E$31>=0),Допущения!$E$31,NA()) -> 59167.753 | K31: =G31*IF(AND(ISNUMBER(Допущения!$F$31),Допущения!$F$31>=0),Допущения!$F$31,NA())*IF(AND(ISNUMBER(Допущения!$B$7),Допущения!$B$7>=0),Допущения!$B$7,NA()) -> 59167.753 | L31: =F31*IF(AND(ISNUMBER(Допущения!$G$31),Допущения!$G$31>=0),Допущения!$G$31,NA())*IF(AND(ISNUMBER(Допущения!$B$7),Допущения!$B$7>=0),Допущения!$B$7,NA()) -> 18000 | M31: =H31-SUM(I31:L31) -> 736448.01
A32: Месяц 9 | B32: =Допущения!$A$32 -> Бизнес | C32: =G29 -> 12.445357 | D32: =IF(IF(AND(ISNUMBER(Допущения!$D$32),Допущения!$D$32>=0,Допущения!$D$32<=1),Допущения!$D$32,NA())*Допущения!$B$25<=1,C32*IF(AND(ISNUMBER(Допущения!$D$32),Допущения!$D$32>=0,Допущения!$D$32<=1),Допущения!$D$32,NA())*Допущения!$B$25,NA()) -> 0.31113391 | E32: =C32-D32 -> 12.134223 | F32: =Привлечение!L32 -> 2.4 | G32: =E32+F32 -> 14.534223 | H32: =G32*IF(AND(ISNUMBER(Допущения!$B$32),Допущения!$B$32>0),Допущения!$B$32,NA()) -> 725257.71 | I32: =H32*IF(AND(ISNUMBER(Допущения!$B$8),Допущения!$B$8>=0,Допущения!$B$8<=1),Допущения!$B$8,NA()) -> 7252.5771 | J32: =G32*IF(AND(ISNUMBER(Допущения!$E$32),Допущения!$E$32>=0),Допущения!$E$32,NA()) -> 50869.779 | K32: =G32*IF(AND(ISNUMBER(Допущения!$F$32),Допущения!$F$32>=0),Допущения!$F$32,NA())*IF(AND(ISNUMBER(Допущения!$B$7),Допущения!$B$7>=0),Допущения!$B$7,NA()) -> 43602.668 | L32: =F32*IF(AND(ISNUMBER(Допущения!$G$32),Допущения!$G$32>=0),Допущения!$G$32,NA())*IF(AND(ISNUMBER(Допущения!$B$7),Допущения!$B$7>=0),Допущения!$B$7,NA()) -> 14400 | M32: =H32-SUM(I32:L32) -> 609132.68
A33: Месяц 10 | B33: =Допущения!$A$30 -> Старт | C33: =G30 -> 246.51481 | D33: =IF(IF(AND(ISNUMBER(Допущения!$D$30),Допущения!$D$30>=0,Допущения!$D$30<=1),Допущения!$D$30,NA())*Допущения!$B$25<=1,C33*IF(AND(ISNUMBER(Допущения!$D$30),Допущения!$D$30>=0,Допущения!$D$30<=1),Допущения!$D$30,NA())*Допущения!$B$25,NA()) -> 14.790889 | E33: =C33-D33 -> 231.72393 | F33: =Привлечение!L33 -> 40 | G33: =E33+F33 -> 271.72393 | H33: =G33*IF(AND(ISNUMBER(Допущения!$B$30),Допущения!$B$30>0),Допущения!$B$30,NA()) -> 1331447.2 | I33: =H33*IF(AND(ISNUMBER(Допущения!$B$8),Допущения!$B$8>=0,Допущения!$B$8<=1),Допущения!$B$8,NA()) -> 13314.472 | J33: =G33*IF(AND(ISNUMBER(Допущения!$E$30),Допущения!$E$30>=0),Допущения!$E$30,NA()) -> 81517.178 | K33: =G33*IF(AND(ISNUMBER(Допущения!$F$30),Допущения!$F$30>=0),Допущения!$F$30,NA())*IF(AND(ISNUMBER(Допущения!$B$7),Допущения!$B$7>=0),Допущения!$B$7,NA()) -> 89668.895 | L33: =F33*IF(AND(ISNUMBER(Допущения!$G$30),Допущения!$G$30>=0),Допущения!$G$30,NA())*IF(AND(ISNUMBER(Допущения!$B$7),Допущения!$B$7>=0),Допущения!$B$7,NA()) -> 20000 | M33: =H33-SUM(I33:L33) -> 1126946.7
A34: Месяц 10 | B34: =Допущения!$A$31 -> Команда | C34: =G31 -> 59.167753 | D34: =IF(IF(AND(ISNUMBER(Допущения!$D$31),Допущения!$D$31>=0,Допущения!$D$31<=1),Допущения!$D$31,NA())*Допущения!$B$25<=1,C34*IF(AND(ISNUMBER(Допущения!$D$31),Допущения!$D$31>=0,Допущения!$D$31<=1),Допущения!$D$31,NA())*Допущения!$B$25,NA()) -> 2.3667101 | E34: =C34-D34 -> 56.801042 | F34: =Привлечение!L34 -> 9 | G34: =E34+F34 -> 65.801042 | H34: =G34*IF(AND(ISNUMBER(Допущения!$B$31),Допущения!$B$31>0),Допущения!$B$31,NA()) -> 980435.53 | I34: =H34*IF(AND(ISNUMBER(Допущения!$B$8),Допущения!$B$8>=0,Допущения!$B$8<=1),Допущения!$B$8,NA()) -> 9804.3553 | J34: =G34*IF(AND(ISNUMBER(Допущения!$E$31),Допущения!$E$31>=0),Допущения!$E$31,NA()) -> 65801.042 | K34: =G34*IF(AND(ISNUMBER(Допущения!$F$31),Допущения!$F$31>=0),Допущения!$F$31,NA())*IF(AND(ISNUMBER(Допущения!$B$7),Допущения!$B$7>=0),Допущения!$B$7,NA()) -> 65801.042 | L34: =F34*IF(AND(ISNUMBER(Допущения!$G$31),Допущения!$G$31>=0),Допущения!$G$31,NA())*IF(AND(ISNUMBER(Допущения!$B$7),Допущения!$B$7>=0),Допущения!$B$7,NA()) -> 18000 | M34: =H34-SUM(I34:L34) -> 821029.09
A35: Месяц 10 | B35: =Допущения!$A$32 -> Бизнес | C35: =G32 -> 14.534223 | D35: =IF(IF(AND(ISNUMBER(Допущения!$D$32),Допущения!$D$32>=0,Допущения!$D$32<=1),Допущения!$D$32,NA())*Допущения!$B$25<=1,C35*IF(AND(ISNUMBER(Допущения!$D$32),Допущения!$D$32>=0,Допущения!$D$32<=1),Допущения!$D$32,NA())*Допущения!$B$25,NA()) -> 0.36335557 | E35: =C35-D35 -> 14.170867 | F35: =Привлечение!L35 -> 2.4 | G35: =E35+F35 -> 16.570867 | H35: =G35*IF(AND(ISNUMBER(Допущения!$B$32),Допущения!$B$32>0),Допущения!$B$32,NA()) -> 826886.27 | I35: =H35*IF(AND(ISNUMBER(Допущения!$B$8),Допущения!$B$8>=0,Допущения!$B$8<=1),Допущения!$B$8,NA()) -> 8268.8627 | J35: =G35*IF(AND(ISNUMBER(Допущения!$E$32),Допущения!$E$32>=0),Допущения!$E$32,NA()) -> 57998.035 | K35: =G35*IF(AND(ISNUMBER(Допущения!$F$32),Допущения!$F$32>=0),Допущения!$F$32,NA())*IF(AND(ISNUMBER(Допущения!$B$7),Допущения!$B$7>=0),Допущения!$B$7,NA()) -> 49712.601 | L35: =F35*IF(AND(ISNUMBER(Допущения!$G$32),Допущения!$G$32>=0),Допущения!$G$32,NA())*IF(AND(ISNUMBER(Допущения!$B$7),Допущения!$B$7>=0),Допущения!$B$7,NA()) -> 14400 | M35: =H35-SUM(I35:L35) -> 696506.77
A36: Месяц 11 | B36: =Допущения!$A$30 -> Старт | C36: =G33 -> 271.72393 | D36: =IF(IF(AND(ISNUMBER(Допущения!$D$30),Допущения!$D$30>=0,Допущения!$D$30<=1),Допущения!$D$30,NA())*Допущения!$B$25<=1,C36*IF(AND(ISNUMBER(Допущения!$D$30),Допущения!$D$30>=0,Допущения!$D$30<=1),Допущения!$D$30,NA())*Допущения!$B$25,NA()) -> 16.303436 | E36: =C36-D36 -> 255.42049 | F36: =Привлечение!L36 -> 40 | G36: =E36+F36 -> 295.42049 | H36: =G36*IF(AND(ISNUMBER(Допущения!$B$30),Допущения!$B$30>0),Допущения!$B$30,NA()) -> 1447560.4 | I36: =H36*IF(AND(ISNUMBER(Допущения!$B$8),Допущения!$B$8>=0,Допущения!$B$8<=1),Допущения!$B$8,NA()) -> 14475.604 | J36: =G36*IF(AND(ISNUMBER(Допущения!$E$30),Допущения!$E$30>=0),Допущения!$E$30,NA()) -> 88626.147 | K36: =G36*IF(AND(ISNUMBER(Допущения!$F$30),Допущения!$F$30>=0),Допущения!$F$30,NA())*IF(AND(ISNUMBER(Допущения!$B$7),Допущения!$B$7>=0),Допущения!$B$7,NA()) -> 97488.762 | L36: =F36*IF(AND(ISNUMBER(Допущения!$G$30),Допущения!$G$30>=0),Допущения!$G$30,NA())*IF(AND(ISNUMBER(Допущения!$B$7),Допущения!$B$7>=0),Допущения!$B$7,NA()) -> 20000 | M36: =H36-SUM(I36:L36) -> 1226969.9
A37: Месяц 11 | B37: =Допущения!$A$31 -> Команда | C37: =G34 -> 65.801042 | D37: =IF(IF(AND(ISNUMBER(Допущения!$D$31),Допущения!$D$31>=0,Допущения!$D$31<=1),Допущения!$D$31,NA())*Допущения!$B$25<=1,C37*IF(AND(ISNUMBER(Допущения!$D$31),Допущения!$D$31>=0,Допущения!$D$31<=1),Допущения!$D$31,NA())*Допущения!$B$25,NA()) -> 2.6320417 | E37: =C37-D37 -> 63.169001 | F37: =Привлечение!L37 -> 9 | G37: =E37+F37 -> 72.169001 | H37: =G37*IF(AND(ISNUMBER(Допущения!$B$31),Допущения!$B$31>0),Допущения!$B$31,NA()) -> 1075318.1 | I37: =H37*IF(AND(ISNUMBER(Допущения!$B$8),Допущения!$B$8>=0,Допущения!$B$8<=1),Допущения!$B$8,NA()) -> 10753.181 | J37: =G37*IF(AND(ISNUMBER(Допущения!$E$31),Допущения!$E$31>=0),Допущения!$E$31,NA()) -> 72169.001 | K37: =G37*IF(AND(ISNUMBER(Допущения!$F$31),Допущения!$F$31>=0),Допущения!$F$31,NA())*IF(AND(ISNUMBER(Допущения!$B$7),Допущения!$B$7>=0),Допущения!$B$7,NA()) -> 72169.001 | L37: =F37*IF(AND(ISNUMBER(Допущения!$G$31),Допущения!$G$31>=0),Допущения!$G$31,NA())*IF(AND(ISNUMBER(Допущения!$B$7),Допущения!$B$7>=0),Допущения!$B$7,NA()) -> 18000 | M37: =H37-SUM(I37:L37) -> 902226.93
A38: Месяц 11 | B38: =Допущения!$A$32 -> Бизнес | C38: =G35 -> 16.570867 | D38: =IF(IF(AND(ISNUMBER(Допущения!$D$32),Допущения!$D$32>=0,Допущения!$D$32<=1),Допущения!$D$32,NA())*Допущения!$B$25<=1,C38*IF(AND(ISNUMBER(Допущения!$D$32),Допущения!$D$32>=0,Допущения!$D$32<=1),Допущения!$D$32,NA())*Допущения!$B$25,NA()) -> 0.41427168 | E38: =C38-D38 -> 16.156595 | F38: =Привлечение!L38 -> 2.4 | G38: =E38+F38 -> 18.556595 | H38: =G38*IF(AND(ISNUMBER(Допущения!$B$32),Допущения!$B$32>0),Допущения!$B$32,NA()) -> 925974.11 | I38: =H38*IF(AND(ISNUMBER(Допущения!$B$8),Допущения!$B$8>=0,Допущения!$B$8<=1),Допущения!$B$8,NA()) -> 9259.7411 | J38: =G38*IF(AND(ISNUMBER(Допущения!$E$32),Допущения!$E$32>=0),Допущения!$E$32,NA()) -> 64948.084 | K38: =G38*IF(AND(ISNUMBER(Допущения!$F$32),Допущения!$F$32>=0),Допущения!$F$32,NA())*IF(AND(ISNUMBER(Допущения!$B$7),Допущения!$B$7>=0),Допущения!$B$7,NA()) -> 55669.786 | L38: =F38*IF(AND(ISNUMBER(Допущения!$G$32),Допущения!$G$32>=0),Допущения!$G$32,NA())*IF(AND(ISNUMBER(Допущения!$B$7),Допущения!$B$7>=0),Допущения!$B$7,NA()) -> 14400 | M38: =H38-SUM(I38:L38) -> 781696.5
A39: Месяц 12 | B39: =Допущения!$A$30 -> Старт | C39: =G36 -> 295.42049 | D39: =IF(IF(AND(ISNUMBER(Допущения!$D$30),Допущения!$D$30>=0,Допущения!$D$30<=1),Допущения!$D$30,NA())*Допущения!$B$25<=1,C39*IF(AND(ISNUMBER(Допущения!$D$30),Допущения!$D$30>=0,Допущения!$D$30<=1),Допущения!$D$30,NA())*Допущения!$B$25,NA()) -> 17.725229 | E39: =C39-D39 -> 277.69526 | F39: =Привлечение!L39 -> 40 | G39: =E39+F39 -> 317.69526 | H39: =G39*IF(AND(ISNUMBER(Допущения!$B$30),Допущения!$B$30>0),Допущения!$B$30,NA()) -> 1556706.8 | I39: =H39*IF(AND(ISNUMBER(Допущения!$B$8),Допущения!$B$8>=0,Допущения!$B$8<=1),Допущения!$B$8,NA()) -> 15567.068 | J39: =G39*IF(AND(ISNUMBER(Допущения!$E$30),Допущения!$E$30>=0),Допущения!$E$30,NA()) -> 95308.578 | K39: =G39*IF(AND(ISNUMBER(Допущения!$F$30),Допущения!$F$30>=0),Допущения!$F$30,NA())*IF(AND(ISNUMBER(Допущения!$B$7),Допущения!$B$7>=0),Допущения!$B$7,NA()) -> 104839.44 | L39: =F39*IF(AND(ISNUMBER(Допущения!$G$30),Допущения!$G$30>=0),Допущения!$G$30,NA())*IF(AND(ISNUMBER(Допущения!$B$7),Допущения!$B$7>=0),Допущения!$B$7,NA()) -> 20000 | M39: =H39-SUM(I39:L39) -> 1320991.7
A40: Месяц 12 | B40: =Допущения!$A$31 -> Команда | C40: =G37 -> 72.169001 | D40: =IF(IF(AND(ISNUMBER(Допущения!$D$31),Допущения!$D$31>=0,Допущения!$D$31<=1),Допущения!$D$31,NA())*Допущения!$B$25<=1,C40*IF(AND(ISNUMBER(Допущения!$D$31),Допущения!$D$31>=0,Допущения!$D$31<=1),Допущения!$D$31,NA())*Допущения!$B$25,NA()) -> 2.88676 | E40: =C40-D40 -> 69.282241 | F40: =Привлечение!L40 -> 9 | G40: =E40+F40 -> 78.282241 | H40: =G40*IF(AND(ISNUMBER(Допущения!$B$31),Допущения!$B$31>0),Допущения!$B$31,NA()) -> 1166405.4 | I40: =H40*IF(AND(ISNUMBER(Допущения!$B$8),Допущения!$B$8>=0,Допущения!$B$8<=1),Допущения!$B$8,NA()) -> 11664.054 | J40: =G40*IF(AND(ISNUMBER(Допущения!$E$31),Допущения!$E$31>=0),Допущения!$E$31,NA()) -> 78282.241 | K40: =G40*IF(AND(ISNUMBER(Допущения!$F$31),Допущения!$F$31>=0),Допущения!$F$31,NA())*IF(AND(ISNUMBER(Допущения!$B$7),Допущения!$B$7>=0),Допущения!$B$7,NA()) -> 78282.241 | L40: =F40*IF(AND(ISNUMBER(Допущения!$G$31),Допущения!$G$31>=0),Допущения!$G$31,NA())*IF(AND(ISNUMBER(Допущения!$B$7),Допущения!$B$7>=0),Допущения!$B$7,NA()) -> 18000 | M40: =H40-SUM(I40:L40) -> 980176.85
A41: Месяц 12 | B41: =Допущения!$A$32 -> Бизнес | C41: =G38 -> 18.556595 | D41: =IF(IF(AND(ISNUMBER(Допущения!$D$32),Допущения!$D$32>=0,Допущения!$D$32<=1),Допущения!$D$32,NA())*Допущения!$B$25<=1,C41*IF(AND(ISNUMBER(Допущения!$D$32),Допущения!$D$32>=0,Допущения!$D$32<=1),Допущения!$D$32,NA())*Допущения!$B$25,NA()) -> 0.46391488 | E41: =C41-D41 -> 18.09268 | F41: =Привлечение!L41 -> 2.4 | G41: =E41+F41 -> 20.49268 | H41: =G41*IF(AND(ISNUMBER(Допущения!$B$32),Допущения!$B$32>0),Допущения!$B$32,NA()) -> 1022584.8 | I41: =H41*IF(AND(ISNUMBER(Допущения!$B$8),Допущения!$B$8>=0,Допущения!$B$8<=1),Допущения!$B$8,NA()) -> 10225.848 | J41: =G41*IF(AND(ISNUMBER(Допущения!$E$32),Допущения!$E$32>=0),Допущения!$E$32,NA()) -> 71724.382 | K41: =G41*IF(AND(ISNUMBER(Допущения!$F$32),Допущения!$F$32>=0),Допущения!$F$32,NA())*IF(AND(ISNUMBER(Допущения!$B$7),Допущения!$B$7>=0),Допущения!$B$7,NA()) -> 61478.041 | L41: =F41*IF(AND(ISNUMBER(Допущения!$G$32),Допущения!$G$32>=0),Допущения!$G$32,NA())*IF(AND(ISNUMBER(Допущения!$B$7),Допущения!$B$7>=0),Допущения!$B$7,NA()) -> 14400 | M41: =H41-SUM(I41:L41) -> 864756.49
A45: Тариф | B45: Вклад / месяц, ₽ | C45: Подключение, ₽ | D45: Отток в расчёте | E45: Ожидаемый вклад клиента, ₽
A46: =Допущения!$A$30 -> Старт | B46: =IF(AND(ISNUMBER(Допущения!$B$30),Допущения!$B$30>0),Допущения!$B$30,NA())*(1-IF(AND(ISNUMBER(Допущения!$B$8),Допущения!$B$8>=0,Допущения!$B$8<=1),Допущения!$B$8,NA()))-IF(AND(ISNUMBER(Допущения!$E$30),Допущения!$E$30>=0),Допущения!$E$30,NA())-IF(AND(ISNUMBER(Допущения!$F$30),Допущения!$F$30>=0),Допущения!$F$30,NA())*IF(AND(ISNUMBER(Допущения!$B$7),Допущения!$B$7>=0),Допущения!$B$7,NA()) -> 4221 | C46: =IF(AND(ISNUMBER(Допущения!$G$30),Допущения!$G$30>=0),Допущения!$G$30,NA())*IF(AND(ISNUMBER(Допущения!$B$7),Допущения!$B$7>=0),Допущения!$B$7,NA()) -> 500 | D46: =IF(IF(AND(ISNUMBER(Допущения!$D$30),Допущения!$D$30>=0,Допущения!$D$30<=1),Допущения!$D$30,NA())*Допущения!$B$25<=1,IF(AND(ISNUMBER(Допущения!$D$30),Допущения!$D$30>=0,Допущения!$D$30<=1),Допущения!$D$30,NA())*Допущения!$B$25,NA()) -> 0.06 | E46: =B46*IF(D46=0,IF(AND(ISNUMBER(Допущения!$B$16),Допущения!$B$16>=0,Допущения!$B$16=INT(Допущения!$B$16),Допущения!$B$16<=120,Допущения!$B$16>0),Допущения!$B$16,NA()),(1-(1-D46)^IF(AND(ISNUMBER(Допущения!$B$16),Допущения!$B$16>=0,Допущения!$B$16=INT(Допущения!$B$16),Допущения!$B$16<=120,Допущения!$B$16>0),Допущения!$B$16,NA()))/D46)-C46 -> 21317.661
A47: =Допущения!$A$31 -> Команда | B47: =IF(AND(ISNUMBER(Допущения!$B$31),Допущения!$B$31>0),Допущения!$B$31,NA())*(1-IF(AND(ISNUMBER(Допущения!$B$8),Допущения!$B$8>=0,Допущения!$B$8<=1),Допущения!$B$8,NA()))-IF(AND(ISNUMBER(Допущения!$E$31),Допущения!$E$31>=0),Допущения!$E$31,NA())-IF(AND(ISNUMBER(Допущения!$F$31),Допущения!$F$31>=0),Допущения!$F$31,NA())*IF(AND(ISNUMBER(Допущения!$B$7),Допущения!$B$7>=0),Допущения!$B$7,NA()) -> 12751 | C47: =IF(AND(ISNUMBER(Допущения!$G$31),Допущения!$G$31>=0),Допущения!$G$31,NA())*IF(AND(ISNUMBER(Допущения!$B$7),Допущения!$B$7>=0),Допущения!$B$7,NA()) -> 2000 | D47: =IF(IF(AND(ISNUMBER(Допущения!$D$31),Допущения!$D$31>=0,Допущения!$D$31<=1),Допущения!$D$31,NA())*Допущения!$B$25<=1,IF(AND(ISNUMBER(Допущения!$D$31),Допущения!$D$31>=0,Допущения!$D$31<=1),Допущения!$D$31,NA())*Допущения!$B$25,NA()) -> 0.04 | E47: =B47*IF(D47=0,IF(AND(ISNUMBER(Допущения!$B$16),Допущения!$B$16>=0,Допущения!$B$16=INT(Допущения!$B$16),Допущения!$B$16<=120,Допущения!$B$16>0),Допущения!$B$16,NA()),(1-(1-D47)^IF(AND(ISNUMBER(Допущения!$B$16),Допущения!$B$16>=0,Допущения!$B$16=INT(Допущения!$B$16),Допущения!$B$16<=120,Допущения!$B$16>0),Допущения!$B$16,NA()))/D47)-C47 -> 67251.386
A48: =Допущения!$A$32 -> Бизнес | B48: =IF(AND(ISNUMBER(Допущения!$B$32),Допущения!$B$32>0),Допущения!$B$32,NA())*(1-IF(AND(ISNUMBER(Допущения!$B$8),Допущения!$B$8>=0,Допущения!$B$8<=1),Допущения!$B$8,NA()))-IF(AND(ISNUMBER(Допущения!$E$32),Допущения!$E$32>=0),Допущения!$E$32,NA())-IF(AND(ISNUMBER(Допущения!$F$32),Допущения!$F$32>=0),Допущения!$F$32,NA())*IF(AND(ISNUMBER(Допущения!$B$7),Допущения!$B$7>=0),Допущения!$B$7,NA()) -> 42901 | C48: =IF(AND(ISNUMBER(Допущения!$G$32),Допущения!$G$32>=0),Допущения!$G$32,NA())*IF(AND(ISNUMBER(Допущения!$B$7),Допущения!$B$7>=0),Допущения!$B$7,NA()) -> 6000 | D48: =IF(IF(AND(ISNUMBER(Допущения!$D$32),Допущения!$D$32>=0,Допущения!$D$32<=1),Допущения!$D$32,NA())*Допущения!$B$25<=1,IF(AND(ISNUMBER(Допущения!$D$32),Допущения!$D$32>=0,Допущения!$D$32<=1),Допущения!$D$32,NA())*Допущения!$B$25,NA()) -> 0.025 | E48: =B48*IF(D48=0,IF(AND(ISNUMBER(Допущения!$B$16),Допущения!$B$16>=0,Допущения!$B$16=INT(Допущения!$B$16),Допущения!$B$16<=120,Допущения!$B$16>0),Допущения!$B$16,NA()),(1-(1-D48)^IF(AND(ISNUMBER(Допущения!$B$16),Допущения!$B$16>=0,Допущения!$B$16=INT(Допущения!$B$16),Допущения!$B$16<=120,Допущения!$B$16>0),Допущения!$B$16,NA()))/D48)-C48 -> 235844.43
A50: ="Вклад клиента за "&Допущения!B16&" месяцев — после обслуживания и подключения, до привлечения и постоянных расходов." -> Вклад клиента за 6 месяцев — после обслуживания и подключения, до привлечения и постоянных расходов.

Sheet Деньги
A1: Деньги • сколько нужно на запуск
A3: Сценарий: | B3: =IFERROR(CHOOSE(Допущения!$B$3,"Осторожный","Базовый","Сильный"),"Проверьте выбор") -> Базовый | D3: Продажи: | E3: =IFERROR(CHOOSE(Допущения!$B$4,"Самостоятельно","Через демо","Смешанные"),"Проверьте выбор") -> Смешанные
A5: Месяц | B5: Новые компании | C5: Активные компании | D5: Выручка, ₽ | E5: Обслуживание и комиссия, ₽ | F5: Подключение, ₽ | G5: Реклама, ₽ | H5: Менеджер, ₽ | I5: Постоянные расходы, ₽ | J5: Поток за месяц, ₽ | K5: Накопленный поток, ₽ | L5: Макс. дефицит, ₽ | M5: Месяц в плюсе | N5: Затраты вернулись
A6: До запуска | B6: =0 -> 0 | C6: =0 -> 0 | D6: =0 -> 0 | E6: =0 -> 0 | F6: =0 -> 0 | G6: =0 -> 0 | H6: =0 -> 0 | I6: =0 -> 0 | J6: =-SUM(IF(AND(ISNUMBER(Допущения!$B$10),Допущения!$B$10>=0),Допущения!$B$10,NA()),IF(AND(ISNUMBER(Допущения!$B$11),Допущения!$B$11>=0),Допущения!$B$11,NA()),IF(AND(ISNUMBER(Допущения!$B$12),Допущения!$B$12>=0),Допущения!$B$12,NA())) -> -1450000 | K6: =J6 -> -1450000 | L6: =MAX(0,-K6) -> 1450000 | M6: =0 -> 0 | N6: =IF(K6>=0,1,0) -> 0
A7: Месяц 1 | B7: =SUM(Подписка!F6:F8) -> 12.25 | C7: =SUM(Подписка!G6:G8) -> 12.25 | D7: =SUM(Подписка!H6:H8) -> 82525 | E7: =SUM(Подписка!I6:K8) -> 11625.25 | F7: =SUM(Подписка!L6:L8) -> 9500 | G7: =SUM(Привлечение!D6:D8) -> 50000 | H7: =SUM(Привлечение!N6:N8) -> 3000 | I7: =SUM(IF(AND(ISNUMBER(Допущения!$B$13),Допущения!$B$13>=0),Допущения!$B$13,NA()),IF(AND(ISNUMBER(Допущения!$B$14),Допущения!$B$14>=0),Допущения!$B$14,NA()),IF(AND(ISNUMBER(Допущения!$B$15),Допущения!$B$15>=0),Допущения!$B$15,NA())) -> 400000 | J7: =D7-SUM(E7:I7) -> -391600.25 | K7: =K6+J7 -> -1841600.2 | L7: =MAX(L6,-K7,0) -> 1841600.2 | M7: =IF(J7>0,1,0) -> 0 | N7: =IF(K7>=0,1,0) -> 0
A8: Месяц 2 | B8: =SUM(Подписка!F9:F11) -> 25.1 | C8: =SUM(Подписка!G9:G11) -> 36.66 | D8: =SUM(Подписка!H9:H11) -> 273234 | E8: =SUM(Подписка!I9:K11) -> 38474.34 | F8: =SUM(Подписка!L9:L11) -> 22600 | G8: =SUM(Привлечение!D9:D11) -> 100000 | H8: =SUM(Привлечение!N9:N11) -> 6000 | I8: =SUM(IF(AND(ISNUMBER(Допущения!$B$13),Допущения!$B$13>=0),Допущения!$B$13,NA()),IF(AND(ISNUMBER(Допущения!$B$14),Допущения!$B$14>=0),Допущения!$B$14,NA()),IF(AND(ISNUMBER(Допущения!$B$15),Допущения!$B$15>=0),Допущения!$B$15,NA())) -> 400000 | J8: =D8-SUM(E8:I8) -> -293840.34 | K8: =K7+J8 -> -2135440.6 | L8: =MAX(L7,-K8,0) -> 2135440.6 | M8: =IF(J8>0,1,0) -> 0 | N8: =IF(K8>=0,1,0) -> 0
A9: Месяц 3 | B9: =SUM(Подписка!F12:F14) -> 37.95 | C9: =SUM(Подписка!G12:G14) -> 72.5646 | D9: =SUM(Подписка!H12:H14) -> 567327.54 | E9: =SUM(Подписка!I12:K14) -> 79873.655 | F9: =SUM(Подписка!L12:L14) -> 35700 | G9: =SUM(Привлечение!D12:D14) -> 150000 | H9: =SUM(Привлечение!N12:N14) -> 9000 | I9: =SUM(IF(AND(ISNUMBER(Допущения!$B$13),Допущения!$B$13>=0),Допущения!$B$13,NA()),IF(AND(ISNUMBER(Допущения!$B$14),Допущения!$B$14>=0),Допущения!$B$14,NA()),IF(AND(ISNUMBER(Допущения!$B$15),Допущения!$B$15>=0),Допущения!$B$15,NA())) -> 400000 | J9: =D9-SUM(E9:I9) -> -107246.12 | K9: =K8+J9 -> -2242686.7 | L9: =MAX(L8,-K9,0) -> 2242686.7 | M9: =IF(J9>0,1,0) -> 0 | N9: =IF(K9>=0,1,0) -> 0
A10: Месяц 4 | B10: =SUM(Подписка!F15:F17) -> 50.8 | C10: =SUM(Подписка!G15:G17) -> 119.33607 | D10: =SUM(Подписка!H15:H17) -> 960242.18 | E10: =SUM(Подписка!I15:K17) -> 135182.61 | F10: =SUM(Подписка!L15:L17) -> 48800 | G10: =SUM(Привлечение!D15:D17) -> 200000 | H10: =SUM(Привлечение!N15:N17) -> 12000 | I10: =SUM(IF(AND(ISNUMBER(Допущения!$B$13),Допущения!$B$13>=0),Допущения!$B$13,NA()),IF(AND(ISNUMBER(Допущения!$B$14),Допущения!$B$14>=0),Допущения!$B$14,NA()),IF(AND(ISNUMBER(Допущения!$B$15),Допущения!$B$15>=0),Допущения!$B$15,NA())) -> 400000 | J10: =D10-SUM(E10:I10) -> 164259.57 | K10: =K9+J10 -> -2078427.1 | L10: =MAX(L9,-K10,0) -> 2242686.7 | M10: =IF(J10>0,1,0) -> 1 | N10: =IF(K10>=0,1,0) -> 0
A11: Месяц 5 | B11: =SUM(Подписка!F18:F20) -> 51.4 | C11: =SUM(Подписка!G18:G20) -> 164.13218 | D11: =SUM(Подписка!H18:H20) -> 1365113 | E11: =SUM(Подписка!I18:K20) -> 192166.66 | F11: =SUM(Подписка!L18:L20) -> 52400 | G11: =SUM(Привлечение!D18:D20) -> 200000 | H11: =SUM(Привлечение!N18:N20) -> 12000 | I11: =SUM(IF(AND(ISNUMBER(Допущения!$B$13),Допущения!$B$13>=0),Допущения!$B$13,NA()),IF(AND(ISNUMBER(Допущения!$B$14),Допущения!$B$14>=0),Допущения!$B$14,NA()),IF(AND(ISNUMBER(Допущения!$B$15),Допущения!$B$15>=0),Допущения!$B$15,NA())) -> 400000 | J11: =D11-SUM(E11:I11) -> 508546.38 | K11: =K10+J11 -> -1569880.8 | L11: =MAX(L10,-K11,0) -> 2242686.7 | M11: =IF(J11>0,1,0) -> 1 | N11: =IF(K11>=0,1,0) -> 0
A12: Месяц 6 | B12: =SUM(Подписка!F21:F23) -> 51.4 | C12: =SUM(Подписка!G21:G23) -> 206.48412 | D12: =SUM(Подписка!H21:H23) -> 1752153 | E12: =SUM(Подписка!I21:K23) -> 246647.55 | F12: =SUM(Подписка!L21:L23) -> 52400 | G12: =SUM(Привлечение!D21:D23) -> 200000 | H12: =SUM(Привлечение!N21:N23) -> 12000 | I12: =SUM(IF(AND(ISNUMBER(Допущения!$B$13),Допущения!$B$13>=0),Допущения!$B$13,NA()),IF(AND(ISNUMBER(Допущения!$B$14),Допущения!$B$14>=0),Допущения!$B$14,NA()),IF(AND(ISNUMBER(Допущения!$B$15),Допущения!$B$15>=0),Допущения!$B$15,NA())) -> 400000 | J12: =D12-SUM(E12:I12) -> 841105.43 | K12: =K11+J12 -> -728775.33 | L12: =MAX(L11,-K12,0) -> 2242686.7 | M12: =IF(J12>0,1,0) -> 1 | N12: =IF(K12>=0,1,0) -> 0
A13: Месяц 7 | B13: =SUM(Подписка!F24:F26) -> 51.4 | C13: =SUM(Подписка!G24:G26) -> 246.53003 | D13: =SUM(Подписка!H24:H26) -> 2122234 | E13: =SUM(Подписка!I24:K26) -> 298747.34 | F13: =SUM(Подписка!L24:L26) -> 52400 | G13: =SUM(Привлечение!D24:D26) -> 200000 | H13: =SUM(Привлечение!N24:N26) -> 12000 | I13: =SUM(IF(AND(ISNUMBER(Допущения!$B$13),Допущения!$B$13>=0),Допущения!$B$13,NA()),IF(AND(ISNUMBER(Допущения!$B$14),Допущения!$B$14>=0),Допущения!$B$14,NA()),IF(AND(ISNUMBER(Допущения!$B$15),Допущения!$B$15>=0),Допущения!$B$15,NA())) -> 400000 | J13: =D13-SUM(E13:I13) -> 1159086.6 | K13: =K12+J13 -> 430311.29 | L13: =MAX(L12,-K13,0) -> 2242686.7 | M13: =IF(J13>0,1,0) -> 1 | N13: =IF(K13>=0,1,0) -> 1
A14: Месяц 8 | B14: =SUM(Подписка!F27:F29) -> 51.4 | C14: =SUM(Подписка!G27:G29) -> 284.40004 | D14: =SUM(Подписка!H27:H29) -> 2476182 | E14: =SUM(Подписка!I27:K29) -> 348581.65 | F14: =SUM(Подписка!L27:L29) -> 52400 | G14: =SUM(Привлечение!D27:D29) -> 200000 | H14: =SUM(Привлечение!N27:N29) -> 12000 | I14: =SUM(IF(AND(ISNUMBER(Допущения!$B$13),Допущения!$B$13>=0),Допущения!$B$13,NA()),IF(AND(ISNUMBER(Допущения!$B$14),Допущения!$B$14>=0),Допущения!$B$14,NA()),IF(AND(ISNUMBER(Допущения!$B$15),Допущения!$B$15>=0),Допущения!$B$15,NA())) -> 400000 | J14: =D14-SUM(E14:I14) -> 1463200.4 | K14: =K13+J14 -> 1893511.6 | L14: =MAX(L13,-K14,0) -> 2242686.7 | M14: =IF(J14>0,1,0) -> 1 | N14: =IF(K14>=0,1,0) -> 1
A15: Месяц 9 | B15: =SUM(Подписка!F30:F32) -> 51.4 | C15: =SUM(Подписка!G30:G32) -> 320.21679 | D15: =SUM(Подписка!H30:H32) -> 2814779.8 | E15: =SUM(Подписка!I30:K32) -> 396260.08 | F15: =SUM(Подписка!L30:L32) -> 52400 | G15: =SUM(Привлечение!D30:D32) -> 200000 | H15: =SUM(Привлечение!N30:N32) -> 12000 | I15: =SUM(IF(AND(ISNUMBER(Допущения!$B$13),Допущения!$B$13>=0),Допущения!$B$13,NA()),IF(AND(ISNUMBER(Допущения!$B$14),Допущения!$B$14>=0),Допущения!$B$14,NA()),IF(AND(ISNUMBER(Допущения!$B$15),Допущения!$B$15>=0),Допущения!$B$15,NA())) -> 400000 | J15: =D15-SUM(E15:I15) -> 1754119.7 | K15: =K14+J15 -> 3647631.4 | L15: =MAX(L14,-K15,0) -> 2242686.7 | M15: =IF(J15>0,1,0) -> 1 | N15: =IF(K15>=0,1,0) -> 1
A16: Месяц 10 | B16: =SUM(Подписка!F33:F35) -> 51.4 | C16: =SUM(Подписка!G33:G35) -> 354.09583 | D16: =SUM(Подписка!H33:H35) -> 3138769 | E16: =SUM(Подписка!I33:K35) -> 441886.48 | F16: =SUM(Подписка!L33:L35) -> 52400 | G16: =SUM(Привлечение!D33:D35) -> 200000 | H16: =SUM(Привлечение!N33:N35) -> 12000 | I16: =SUM(IF(AND(ISNUMBER(Допущения!$B$13),Допущения!$B$13>=0),Допущения!$B$13,NA()),IF(AND(ISNUMBER(Допущения!$B$14),Допущения!$B$14>=0),Допущения!$B$14,NA()),IF(AND(ISNUMBER(Допущения!$B$15),Допущения!$B$15>=0),Допущения!$B$15,NA())) -> 400000 | J16: =D16-SUM(E16:I16) -> 2032482.5 | K16: =K15+J16 -> 5680113.9 | L16: =MAX(L15,-K16,0) -> 2242686.7 | M16: =IF(J16>0,1,0) -> 1 | N16: =IF(K16>=0,1,0) -> 1
A17: Месяц 11 | B17: =SUM(Подписка!F36:F38) -> 51.4 | C17: =SUM(Подписка!G36:G38) -> 386.14609 | D17: =SUM(Подписка!H36:H38) -> 3448852.6 | E17: =SUM(Подписка!I36:K38) -> 485559.31 | F17: =SUM(Подписка!L36:L38) -> 52400 | G17: =SUM(Привлечение!D36:D38) -> 200000 | H17: =SUM(Привлечение!N36:N38) -> 12000 | I17: =SUM(IF(AND(ISNUMBER(Допущения!$B$13),Допущения!$B$13>=0),Допущения!$B$13,NA()),IF(AND(ISNUMBER(Допущения!$B$14),Допущения!$B$14>=0),Допущения!$B$14,NA()),IF(AND(ISNUMBER(Допущения!$B$15),Допущения!$B$15>=0),Допущения!$B$15,NA())) -> 400000 | J17: =D17-SUM(E17:I17) -> 2298893.3 | K17: =K16+J17 -> 7979007.2 | L17: =MAX(L16,-K17,0) -> 2242686.7 | M17: =IF(J17>0,1,0) -> 1 | N17: =IF(K17>=0,1,0) -> 1
A18: Месяц 12 | B18: =SUM(Подписка!F39:F41) -> 51.4 | C18: =SUM(Подписка!G39:G41) -> 416.47018 | D18: =SUM(Подписка!H39:H41) -> 3745696.9 | E18: =SUM(Подписка!I39:K41) -> 527371.89 | F18: =SUM(Подписка!L39:L41) -> 52400 | G18: =SUM(Привлечение!D39:D41) -> 200000 | H18: =SUM(Привлечение!N39:N41) -> 12000 | I18: =SUM(IF(AND(ISNUMBER(Допущения!$B$13),Допущения!$B$13>=0),Допущения!$B$13,NA()),IF(AND(ISNUMBER(Допущения!$B$14),Допущения!$B$14>=0),Допущения!$B$14,NA()),IF(AND(ISNUMBER(Допущения!$B$15),Допущения!$B$15>=0),Допущения!$B$15,NA())) -> 400000 | J18: =D18-SUM(E18:I18) -> 2553925 | K18: =K17+J18 -> 10532932 | L18: =MAX(L17,-K18,0) -> 2242686.7 | M18: =IF(J18>0,1,0) -> 1 | N18: =IF(K18>=0,1,0) -> 1
A20: Выручка = месячные оплаты. Поток — деньги после расходов, до налогов и финансирования.
